Workbook
Name Slicer_Product_Type: #N/A
Name Slicer_Product_Type1: #N/A
Name Slicer_Quarter: #N/A
Name Slicer_Sales_Rep: #N/A

Sheet Dashboard
B1: Mobility Sales Dashboard
B2: KPIs, discount effectiveness and key charts | Source: 'Mobility sales data' sheet (Table3) and pivots
B4: Net sales (EUR) | D4: Units | F4: € / unit | H4: Avg discount | J4: Best month | L4: Top rep
B5: =SUM(Table3[Total Sales (EUR)]) -> 36382530 | D5: =SUM(Table3[Units Sold]) -> 65480 | F5: =B5/D5 -> 555.62813 | H5: =SUM(Table3[Discount (EUR)])/SUM(Table3[Gross Sales (EUR)]) -> 0.040266413 | J5: =INDEX('Pivot Time'!M4:M15,MATCH(MAX('Pivot Time'!N4:N15),'Pivot Time'!N4:N15,0)) -> June | L5: =INDEX('Pivot Reps & Products'!J4:J7,MATCH(MAX('Pivot Reps & Products'!K4:K7),'Pivot Reps & Products'!K4:K7,0)) -> Liu, Fang
B7: Discount effectiveness
B8: Average units per order with vs without discount
B9: Product | C9: Units/order (no disc.) | D9: Units/order (with disc.) | E9: Uplift | F9: Avg discount (if >0)
B10: Electric Scooter | C10: =AVERAGEIFS(Table3[Units Sold],Table3[Product Type],$B10,Table3[Discount (%)],0) -> 635.55556 | D10: =AVERAGEIFS(Table3[Units Sold],Table3[Product Type],$B10,Table3[Discount (%)],">0") -> 644.16667 | E10: =IFERROR(D10/C10-1,"-") -> 0.013548951 | F10: =AVERAGEIFS(Table3[Discount (%)],Table3[Product Type],$B10,Table3[Discount (%)],">0")/100 -> 0.15
B11: Electric Skateboard | C11: =AVERAGEIFS(Table3[Units Sold],Table3[Product Type],$B11,Table3[Discount (%)],0) -> 439.16667 | D11: =AVERAGEIFS(Table3[Units Sold],Table3[Product Type],$B11,Table3[Discount (%)],">0") -> 440 | E11: =IFERROR(D11/C11-1,"-") -> 0.0018975332 | F11: =AVERAGEIFS(Table3[Discount (%)],Table3[Product Type],$B11,Table3[Discount (%)],">0")/100 -> 0.15
B12: Electric Unicycle | C12: =AVERAGEIFS(Table3[Units Sold],Table3[Product Type],$B12,Table3[Discount (%)],0) -> 288.88889 | D12: =AVERAGEIFS(Table3[Units Sold],Table3[Product Type],$B12,Table3[Discount (%)],">0") -> 281.66667 | E12: =IFERROR(D12/C12-1,"-") -> -0.025 | F12: =AVERAGEIFS(Table3[Discount (%)],Table3[Product Type],$B12,Table3[Discount (%)],">0")/100 -> 0.15
B13: Total | C13: =AVERAGEIFS(Table3[Units Sold],Table3[Discount (%)],0) -> 454.53704 | D13: =AVERAGEIFS(Table3[Units Sold],Table3[Discount (%)],">0") -> 455.27778 | E13: =IFERROR(D13/C13-1,"-") -> 0.0016296598 | F13: =AVERAGEIFS(Table3[Discount (%)],Table3[Discount (%)],">0")/100 -> 0.15
B49: Chart data (mirror of the pivots — do not edit)
B50: ='Pivot Time'!M3 -> Month | C50: ='Pivot Time'!N3 -> Sales (EUR) | E50: ='Pivot Time'!P3 -> Quarter | F50: ='Pivot Time'!Q3 -> Sales (EUR) | G50: ='Pivot Time'!R3 -> Discounts (EUR) | I50: ='Pivot Reps & Products'!J3 -> Sales Rep | J50: ='Pivot Reps & Products'!K3 -> Sales (EUR) | L50: ='Pivot Reps & Products'!M3 -> Product | M50: ='Pivot Reps & Products'!N3 -> Sales (EUR)
B51: ='Pivot Time'!M4 -> January | C51: ='Pivot Time'!N4 -> 2076593 | E51: ='Pivot Time'!P4 -> Q1 | F51: ='Pivot Time'!Q4 -> 7180763 | G51: ='Pivot Time'!R4 -> 230730 | I51: ='Pivot Reps & Products'!J4 -> Liu, Fang | J51: ='Pivot Reps & Products'!K4 -> 18770889 | L51: ='Pivot Reps & Products'!M4 -> Electric Scooter | M51: ='Pivot Reps & Products'!N4 -> 14904265
B52: ='Pivot Time'!M5 -> February | C52: ='Pivot Time'!N5 -> 2552085 | E52: ='Pivot Time'!P5 -> Q2 | F52: ='Pivot Time'!Q5 -> 10284291 | G52: ='Pivot Time'!R5 -> 0 | I52: ='Pivot Reps & Products'!J5 -> Bernard, Théo | J52: ='Pivot Reps & Products'!K5 -> 8059775 | L52: ='Pivot Reps & Products'!M5 -> Electric Skateboard | M52: ='Pivot Reps & Products'!N5 -> 12366531
B53: ='Pivot Time'!M6 -> March | C53: ='Pivot Time'!N6 -> 2552085 | E53: ='Pivot Time'!P6 -> Q3 | F53: ='Pivot Time'!Q6 -> 10141023 | G53: ='Pivot Time'!R6 -> 0 | I53: ='Pivot Reps & Products'!J6 -> Fischer, Jonas | J53: ='Pivot Reps & Products'!K6 -> 7068725 | L53: ='Pivot Reps & Products'!M6 -> Electric Unicycle | M53: ='Pivot Reps & Products'!N6 -> 9111734
B54: ='Pivot Time'!M7 -> April | C54: ='Pivot Time'!N7 -> 3167122 | E54: ='Pivot Time'!P7 -> Q4 | F54: ='Pivot Time'!Q7 -> 8776453 | G54: ='Pivot Time'!R7 -> 1295729 | I54: ='Pivot Reps & Products'!J7 -> Joshi, Sanya | J54: ='Pivot Reps & Products'!K7 -> 2483141
B55: ='Pivot Time'!M8 -> May | C55: ='Pivot Time'!N8 -> 3311633
B56: ='Pivot Time'!M9 -> June | C56: ='Pivot Time'!N9 -> 3805536
B57: ='Pivot Time'!M10 -> July | C57: ='Pivot Time'!N10 -> 3744231
B58: ='Pivot Time'!M11 -> August | C58: ='Pivot Time'!N11 -> 3308633
B59: ='Pivot Time'!M12 -> September | C59: ='Pivot Time'!N12 -> 3088159
B60: ='Pivot Time'!M13 -> October | C60: ='Pivot Time'!N13 -> 2817184
B61: ='Pivot Time'!M14 -> November | C61: ='Pivot Time'!N14 -> 2639595
B62: ='Pivot Time'!M15 -> December | C62: ='Pivot Time'!N15 -> 3319674

Sheet Mobility sales data
A1: Sales Rep ID | B1: Rep First Name | C1: Rep Last Name | D1: Sales Rep | E1: Month | F1: Product Type | G1: Min Speed (original, incomplete) | H1: Min Speed (mph) | I1: Speed | J1: Distance | K1: Min Speed (km/h) | L1: Max Speed (km/h) | M1: Speed Range (km/h) | N1: Distance (km) | O1: Shipping Address | P1: Street | Q1: City | R1: Postcode | S1: Country Code | T1: Country Name | U1: Continent | V1: Unit Price | W1: Currency | X1: Unit Price (local) | Y1: FX Rate (per EUR) | Z1: Unit Price (EUR) | AA1: Units Sold | AB1: Discount (%) | AC1: Gross Sales (EUR) | AD1: Total Sales (EUR) | AE1: Month No | AF1: Month (sorted) | AG1: Quarter | AH1: Discount (EUR) | AI1: Month (date)
A2: 1 | B2: Sanya | C2: Joshi | D2: =TRIM(Table3[[#This Row],[Rep Last Name]])&", "&TRIM(Table3[[#This Row],[Rep First Name]]) -> Joshi, Sanya | E2: January | F2: Electric Unicycle | G2: 15 mph | H2: =IF(Table3[[#This Row],[Min Speed (original, incomplete)]]="",_xlfn.IFNA(_xlfn.XLOOKUP(Table3[[#This Row],[Product Type]],Lookups!$G$2:$G$4,Lookups!$H$2:$H$4),"CHECK PRODUCT"),Table3[[#This Row],[Min Speed (original, incomplete)]]) -> 15 mph | I2: 30 mph | J2: 30 miles | K2: =ROUND(VALUE(SUBSTITUTE(Table3[[#This Row],[Min Speed (mph)]]," mph",""))*Lookups!$L$2,0) -> 24 | L2: =ROUND(VALUE(SUBSTITUTE(Table3[[#This Row],[Speed]]," mph",""))*Lookups!$L$2,0) -> 48 | M2: =Table3[[#This Row],[Min Speed (km/h)]]&" – "&Table3[[#This Row],[Max Speed (km/h)]]&" km/h" -> 24 – 48 km/h | N2: =IF(ISNUMBER(SEARCH("mile",Table3[[#This Row],[Distance]])),ROUND(VALUE(SUBSTITUTE(Table3[[#This Row],[Distance]]," miles",""))*Lookups!$L$3,0),ROUND(VALUE(SUBSTITUTE(Table3[[#This Row],[Distance]]," meters",""))*Lookups!$L$4,0)) -> 48 | O2: 456 Brigade Road, Bengaluru, 560001 | P2: =TRIM(LEFT(Table3[[#This Row],[Shipping Address]],FIND(",",Table3[[#This Row],[Shipping Address]])-1)) -> 456 Brigade Road | Q2: =TRIM(MID(Table3[[#This Row],[Shipping Address]],FIND(",",Table3[[#This Row],[Shipping Address]])+1,FIND(",",Table3[[#This Row],[Shipping Address]],FIND(",",Table3[[#This Row],[Shipping Address]])+1)-FIND(",",Table3[[#This Row],[Shipping Address]])-1)) -> Bengaluru | R2: =TRIM(MID(Table3[[#This Row],[Shipping Address]],FIND(",",Table3[[#This Row],[Shipping Address]],FIND(",",Table3[[#This Row],[Shipping Address]])+1)+1,20)) -> 560001 | S2: IN | T2: =_xlfn.IFNA(_xlfn.XLOOKUP(Table3[[#This Row],[Country Code]],Lookups!$A$2:$A$5,Lookups!$B$2:$B$5),"CHECK CODE") -> India | U2: =_xlfn.IFNA(_xlfn.XLOOKUP(Table3[[#This Row],[Country Code]],Lookups!$A$2:$A$5,Lookups!$C$2:$C$5),"CHECK CODE") -> Asia | V2: ₹30,000 | W2: =_xlfn.IFNA(_xlfn.XLOOKUP(Table3[[#This Row],[Country Code]],Lookups!$A$2:$A$5,Lookups!$D$2:$D$5),"CHECK CODE") -> INR | X2: =VALUE(MID(Table3[[#This Row],[Unit Price]],2,50)) -> 30000 | Y2: =_xlfn.IFNA(_xlfn.XLOOKUP(Table3[[#This Row],[Country Code]],Lookups!$A$2:$A$5,Lookups!$E$2:$E$5),"") -> 109.882 | Z2: =Table3[[#This Row],[Unit Price (local)]]/Table3[[#This Row],[FX Rate (per EUR)]] -> 273.02015 | AA2: 150 | AB2: 10 | AC2: =ROUND(Table3[[#This Row],[Unit Price (EUR)]]*Table3[[#This Row],[Units Sold]],0) -> 40953 | AD2: =ROUND(Table3[[#This Row],[Gross Sales (EUR)]]*(1-Table3[[#This Row],[Discount (%)]]/100),0) -> 36858 | AE2: =_xlfn.IFNA(_xlfn.XLOOKUP(Table3[[#This Row],[Month]],Lookups!$N$2:$N$13,Lookups!$O$2:$O$13),"CHECK MONTH") -> 1 | AF2: =TEXT(Table3[[#This Row],[Month No]],"00")&" - "&Table3[[#This Row],[Month]] -> 01 - January | AG2: =_xlfn.IFNA(_xlfn.XLOOKUP(Table3[[#This Row],[Month]],Lookups!$N$2:$N$13,Lookups!$P$2:$P$13),"CHECK MONTH") -> Q1 | AH2: =Table3[[#This Row],[Gross Sales (EUR)]]-Table3[[#This Row],[Total Sales (EUR)]] -> 4095 | AI2: =DATE(Lookups!$O$15,Table3[[#This Row],[Month No]],1) -> 45658
A3: 2 | B3: Sanya | C3: Joshi | D3: =TRIM(Table3[[#This Row],[Rep Last Name]])&", "&TRIM(Table3[[#This Row],[Rep First Name]]) -> Joshi, Sanya | E3: January | F3: Electric Scooter | G3: 20 mph | H3: =IF(Table3[[#This Row],[Min Speed (original, incomplete)]]="",_xlfn.IFNA(_xlfn.XLOOKUP(Table3[[#This Row],[Product Type]],Lookups!$G$2:$G$4,Lookups!$H$2:$H$4),"CHECK PRODUCT"),Table3[[#This Row],[Min Speed (original, incomplete)]]) -> 20 mph | I3: 35 mph | J3: 40 miles | K3: =ROUND(VALUE(SUBSTITUTE(Table3[[#This Row],[Min Speed (mph)]]," mph",""))*Lookups!$L$2,0) -> 32 | L3: =ROUND(VALUE(SUBSTITUTE(Table3[[#This Row],[Speed]]," mph",""))*Lookups!$L$2,0) -> 56 | M3: =Table3[[#This Row],[Min Speed (km/h)]]&" – "&Table3[[#This Row],[Max Speed (km/h)]]&" km/h" -> 32 – 56 km/h | N3: =IF(ISNUMBER(SEARCH("mile",Table3[[#This Row],[Distance]])),ROUND(VALUE(SUBSTITUTE(Table3[[#This Row],[Distance]]," miles",""))*Lookups!$L$3,0),ROUND(VALUE(SUBSTITUTE(Table3[[#This Row],[Distance]]," meters",""))*Lookups!$L$4,0)) -> 64 | O3: 457 Brigade Road, Bengaluru, 560001 | P3: =TRIM(LEFT(Table3[[#This Row],[Shipping Address]],FIND(",",Table3[[#This Row],[Shipping Address]])-1)) -> 457 Brigade Road | Q3: =TRIM(MID(Table3[[#This Row],[Shipping Address]],FIND(",",Table3[[#This Row],[Shipping Address]])+1,FIND(",",Table3[[#This Row],[Shipping Address]],FIND(",",Table3[[#This Row],[Shipping Address]])+1)-FIND(",",Table3[[#This Row],[Shipping Address]])-1)) -> Bengaluru | R3: =TRIM(MID(Table3[[#This Row],[Shipping Address]],FIND(",",Table3[[#This Row],[Shipping Address]],FIND(",",Table3[[#This Row],[Shipping Address]])+1)+1,20)) -> 560001 | S3: IN | T3: =_xlfn.IFNA(_xlfn.XLOOKUP(Table3[[#This Row],[Country Code]],Lookups!$A$2:$A$5,Lookups!$B$2:$B$5),"CHECK CODE") -> India | U3: =_xlfn.IFNA(_xlfn.XLOOKUP(Table3[[#This Row],[Country Code]],Lookups!$A$2:$A$5,Lookups!$C$2:$C$5),"CHECK CODE") -> Asia | V3: ₹25,000 | W3: =_xlfn.IFNA(_xlfn.XLOOKUP(Table3[[#This Row],[Country Code]],Lookups!$A$2:$A$5,Lookups!$D$2:$D$5),"CHECK CODE") -> INR | X3: =VALUE(MID(Table3[[#This Row],[Unit Price]],2,50)) -> 25000 | Y3: =_xlfn.IFNA(_xlfn.XLOOKUP(Table3[[#This Row],[Country Code]],Lookups!$A$2:$A$5,Lookups!$E$2:$E$5),"") -> 109.882 | Z3: =Table3[[#This Row],[Unit Price (local)]]/Table3[[#This Row],[FX Rate (per EUR)]] -> 227.51679 | AA3: 300 | AB3: 10 | AC3: =ROUND(Table3[[#This Row],[Unit Price (EUR)]]*Table3[[#This Row],[Units Sold]],0) -> 68255 | AD3: =ROUND(Table3[[#This Row],[Gross Sales (EUR)]]*(1-Table3[[#This Row],[Discount (%)]]/100),0) -> 61430 | AE3: =_xlfn.IFNA(_xlfn.XLOOKUP(Table3[[#This Row],[Month]],Lookups!$N$2:$N$13,Lookups!$O$2:$O$13),"CHECK MONTH") -> 1 | AF3: =TEXT(Table3[[#This Row],[Month No]],"00")&" - "&Table3[[#This Row],[Month]] -> 01 - January | AG3: =_xlfn.IFNA(_xlfn.XLOOKUP(Table3[[#This Row],[Month]],Lookups!$N$2:$N$13,Lookups!$P$2:$P$13),"CHECK MONTH") -> Q1 | AH3: =Table3[[#This Row],[Gross Sales (EUR)]]-Table3[[#This Row],[Total Sales (EUR)]] -> 6825 | AI3: =DATE(Lookups!$O$15,Table3[[#This Row],[Month No]],1) -> 45658
A4: 3 | B4: Sanya | C4: Joshi | D4: =TRIM(Table3[[#This Row],[Rep Last Name]])&", "&TRIM(Table3[[#This Row],[Rep First Name]]) -> Joshi, Sanya | E4: January | F4: Electric Skateboard | G4: 18 mph | H4: =IF(Table3[[#This Row],[Min Speed (original, incomplete)]]="",_xlfn.IFNA(_xlfn.XLOOKUP(Table3[[#This Row],[Product Type]],Lookups!$G$2:$G$4,Lookups!$H$2:$H$4),"CHECK PRODUCT"),Table3[[#This Row],[Min Speed (original, incomplete)]]) -> 18 mph | I4: 28 mph | J4: 25 miles | K4: =ROUND(VALUE(SUBSTITUTE(Table3[[#This Row],[Min Speed (mph)]]," mph",""))*Lookups!$L$2,0) -> 29 | L4: =ROUND(VALUE(SUBSTITUTE(Table3[[#This Row],[Speed]]," mph",""))*Lookups!$L$2,0) -> 45 | M4: =Table3[[#This Row],[Min Speed (km/h)]]&" – "&Table3[[#This Row],[Max Speed (km/h)]]&" km/h" -> 29 – 45 km/h | N4: =IF(ISNUMBER(SEARCH("mile",Table3[[#This Row],[Distance]])),ROUND(VALUE(SUBSTITUTE(Table3[[#This Row],[Distance]]," miles",""))*Lookups!$L$3,0),ROUND(VALUE(SUBSTITUTE(Table3[[#This Row],[Distance]]," meters",""))*Lookups!$L$4,0)) -> 40 | O4: 458 Brigade Road, Bengaluru, 560001 | P4: =TRIM(LEFT(Table3[[#This Row],[Shipping Address]],FIND(",",Table3[[#This Row],[Shipping Address]])-1)) -> 458 Brigade Road | Q4: =TRIM(MID(Table3[[#This Row],[Shipping Address]],FIND(",",Table3[[#This Row],[Shipping Address]])+1,FIND(",",Table3[[#This Row],[Shipping Address]],FIND(",",Table3[[#This Row],[Shipping Address]])+1)-FIND(",",Table3[[#This Row],[Shipping Address]])-1)) -> Bengaluru | R4: =TRIM(MID(Table3[[#This Row],[Shipping Address]],FIND(",",Table3[[#This Row],[Shipping Address]],FIND(",",Table3[[#This Row],[Shipping Address]])+1)+1,20)) -> 560001 | S4: IN | T4: =_xlfn.IFNA(_xlfn.XLOOKUP(Table3[[#This Row],[Country Code]],Lookups!$A$2:$A$5,Lookups!$B$2:$B$5),"CHECK CODE") -> India | U4: =_xlfn.IFNA(_xlfn.XLOOKUP(Table3[[#This Row],[Country Code]],Lookups!$A$2:$A$5,Lookups!$C$2:$C$5),"CHECK CODE") -> Asia | V4: ₹22,000 | W4: =_xlfn.IFNA(_xlfn.XLOOKUP(Table3[[#This Row],[Country Code]],Lookups!$A$2:$A$5,Lookups!$D$2:$D$5),"CHECK CODE") -> INR | X4: =VALUE(MID(Table3[[#This Row],[Unit Price]],2,50)) -> 22000 | Y4: =_xlfn.IFNA(_xlfn.XLOOKUP(Table3[[#This Row],[Country Code]],Lookups!$A$2:$A$5,Lookups!$E$2:$E$5),"") -> 109.882 | Z4: =Table3[[#This Row],[Unit Price (local)]]/Table3[[#This Row],[FX Rate (per EUR)]] -> 200.21478 | AA4: 200 | AB4: 10 | AC4: =ROUND(Table3[[#This Row],[Unit Price (EUR)]]*Table3[[#This Row],[Units Sold]],0) -> 40043 | AD4: =ROUND(Table3[[#This Row],[Gross Sales (EUR)]]*(1-Table3[[#This Row],[Discount (%)]]/100),0) -> 36039 | AE4: =_xlfn.IFNA(_xlfn.XLOOKUP(Table3[[#This Row],[Month]],Lookups!$N$2:$N$13,Lookups!$O$2:$O$13),"CHECK MONTH") -> 1 | AF4: =TEXT(Table3[[#This Row],[Month No]],"00")&" - "&Table3[[#This Row],[Month]] -> 01 - January | AG4: =_xlfn.IFNA(_xlfn.XLOOKUP(Table3[[#This Row],[Month]],Lookups!$N$2:$N$13,Lookups!$P$2:$P$13),"CHECK MONTH") -> Q1 | AH4: =Table3[[#This Row],[Gross Sales (EUR)]]-Table3[[#This Row],[Total Sales (EUR)]] -> 4004 | AI4: =DATE(Lookups!$O$15,Table3[[#This Row],[Month No]],1) -> 45658
A5: 4 | B5: Fang | C5: Liu | D5: =TRIM(Table3[[#This Row],[Rep Last Name]])&", "&TRIM(Table3[[#This Row],[Rep First Name]]) -> Liu, Fang | E5: January | F5: Electric Unicycle | G5: 15 mph | H5: =IF(Table3[[#This Row],[Min Speed (original, incomplete)]]="",_xlfn.IFNA(_xlfn.XLOOKUP(Table3[[#This Row],[Product Type]],Lookups!$G$2:$G$4,Lookups!$H$2:$H$4),"CHECK PRODUCT"),Table3[[#This Row],[Min Speed (original, incomplete)]]) -> 15 mph | I5: 30 mph | J5: 30 miles | K5: =ROUND(VALUE(SUBSTITUTE(Table3[[#This Row],[Min Speed (mph)]]," mph",""))*Lookups!$L$2,0) -> 24 | L5: =ROUND(VALUE(SUBSTITUTE(Table3[[#This Row],[Speed]]," mph",""))*Lookups!$L$2,0) -> 48 | M5: =Table3[[#This Row],[Min Speed (km/h)]]&" – "&Table3[[#This Row],[Max Speed (km/h)]]&" km/h" -> 24 – 48 km/h | N5: =IF(ISNUMBER(SEARCH("mile",Table3[[#This Row],[Distance]])),ROUND(VALUE(SUBSTITUTE(Table3[[#This Row],[Distance]]," miles",""))*Lookups!$L$3,0),ROUND(VALUE(SUBSTITUTE(Table3[[#This Row],[Distance]]," meters",""))*Lookups!$L$4,0)) -> 48 | O5: 99 Nanjing Road, Shanghai, 200001 | P5: =TRIM(LEFT(Table3[[#This Row],[Shipping Address]],FIND(",",Table3[[#This Row],[Shipping Address]])-1)) -> 99 Nanjing Road | Q5: =TRIM(MID(Table3[[#This Row],[Shipping Address]],FIND(",",Table3[[#This Row],[Shipping Address]])+1,FIND(",",Table3[[#This Row],[Shipping Address]],FIND(",",Table3[[#This Row],[Shipping Address]])+1)-FIND(",",Table3[[#This Row],[Shipping Address]])-1)) -> Shanghai | R5: =TRIM(MID(Table3[[#This Row],[Shipping Address]],FIND(",",Table3[[#This Row],[Shipping Address]],FIND(",",Table3[[#This Row],[Shipping Address]])+1)+1,20)) -> 200001 | S5: CN | T5: =_xlfn.IFNA(_xlfn.XLOOKUP(Table3[[#This Row],[Country Code]],Lookups!$A$2:$A$5,Lookups!$B$2:$B$5),"CHECK CODE") -> China | U5: =_xlfn.IFNA(_xlfn.XLOOKUP(Table3[[#This Row],[Country Code]],Lookups!$A$2:$A$5,Lookups!$C$2:$C$5),"CHECK CODE") -> Asia | V5: ¥5,000 | W5: =_xlfn.IFNA(_xlfn.XLOOKUP(Table3[[#This Row],[Country Code]],Lookups!$A$2:$A$5,Lookups!$D$2:$D$5),"CHECK CODE") -> CNY | X5: =VALUE(MID(Table3[[#This Row],[Unit Price]],2,50)) -> 5000 | Y5: =_xlfn.IFNA(_xlfn.XLOOKUP(Table3[[#This Row],[Country Code]],Lookups!$A$2:$A$5,Lookups!$E$2:$E$5),"") -> 7.7255 | Z5: =Table3[[#This Row],[Unit Price (local)]]/Table3[[#This Row],[FX Rate (per EUR)]] -> 647.2073 | AA5: 500 | AB5: 10 | AC5: =ROUND(Table3[[#This Row],[Unit Price (EUR)]]*Table3[[#This Row],[Units Sold]],0) -> 323604 | AD5: =ROUND(Table3[[#This Row],[Gross Sales (EUR)]]*(1-Table3[[#This Row],[Discount (%)]]/100),0) -> 291244 | AE5: =_xlfn.IFNA(_xlfn.XLOOKUP(Table3[[#This Row],[Month]],Lookups!$N$2:$N$13,Lookups!$O$2:$O$13),"CHECK MONTH") -> 1 | AF5: =TEXT(Table3[[#This Row],[Month No]],"00")&" - "&Table3[[#This Row],[Month]] -> 01 - January | AG5: =_xlfn.IFNA(_xlfn.XLOOKUP(Table3[[#This Row],[Month]],Lookups!$N$2:$N$13,Lookups!$P$2:$P$13),"CHECK MONTH") -> Q1 | AH5: =Table3[[#This Row],[Gross Sales (EUR)]]-Table3[[#This Row],[Total Sales (EUR)]] -> 32360 | AI5: =DATE(Lookups!$O$15,Table3[[#This Row],[Month No]],1) -> 45658
A6: 5 | B6: Fang | C6: Liu | D6: =TRIM(Table3[[#This Row],[Rep Last Name]])&", "&TRIM(Table3[[#This Row],[Rep First Name]]) -> Liu, Fang | E6: January | F6: Electric Scooter | G6: 20 mph | H6: =IF(Table3[[#This Row],[Min Speed (original, incomplete)]]="",_xlfn.IFNA(_xlfn.XLOOKUP(Table3[[#This Row],[Product Type]],Lookups!$G$2:$G$4,Lookups!$H$2:$H$4),"CHECK PRODUCT"),Table3[[#This Row],[Min Speed (original, incomplete)]]) -> 20 mph | I6: 35 mph | J6: 40 miles | K6: =ROUND(VALUE(SUBSTITUTE(Table3[[#This Row],[Min Speed (mph)]]," mph",""))*Lookups!$L$2,0) -> 32 | L6: =ROUND(VALUE(SUBSTITUTE(Table3[[#This Row],[Speed]]," mph",""))*Lookups!$L$2,0) -> 56 | M6: =Table3[[#This Row],[Min Speed (km/h)]]&" – "&Table3[[#This Row],[Max Speed (km/h)]]&" km/h" -> 32 – 56 km/h | N6: =IF(ISNUMBER(SEARCH("mile",Table3[[#This Row],[Distance]])),ROUND(VALUE(SUBSTITUTE(Table3[[#This Row],[Distance]]," miles",""))*Lookups!$L$3,0),ROUND(VALUE(SUBSTITUTE(Table3[[#This Row],[Distance]]," meters",""))*Lookups!$L$4,0)) -> 64 | O6: 100 Nanjing Road, Shanghai, 200001 | P6: =TRIM(LEFT(Table3[[#This Row],[Shipping Address]],FIND(",",Table3[[#This Row],[Shipping Address]])-1)) -> 100 Nanjing Road | Q6: =TRIM(MID(Table3[[#This Row],[Shipping Address]],FIND(",",Table3[[#This Row],[Shipping Address]])+1,FIND(",",Table3[[#This Row],[Shipping Address]],FIND(",",Table3[[#This Row],[Shipping Address]])+1)-FIND(",",Table3[[#This Row],[Shipping Address]])-1)) -> Shanghai | R6: =TRIM(MID(Table3[[#This Row],[Shipping Address]],FIND(",",Table3[[#This Row],[Shipping Address]],FIND(",",Table3[[#This Row],[Shipping Address]])+1)+1,20)) -> 200001 | S6: CN | T6: =_xlfn.IFNA(_xlfn.XLOOKUP(Table3[[#This Row],[Country Code]],Lookups!$A$2:$A$5,Lookups!$B$2:$B$5),"CHECK CODE") -> China | U6: =_xlfn.IFNA(_xlfn.XLOOKUP(Table3[[#This Row],[Country Code]],Lookups!$A$2:$A$5,Lookups!$C$2:$C$5),"CHECK CODE") -> Asia | V6: ¥3,500 | W6: =_xlfn.IFNA(_xlfn.XLOOKUP(Table3[[#This Row],[Country Code]],Lookups!$A$2:$A$5,Lookups!$D$2:$D$5),"CHECK CODE") -> CNY | X6: =VALUE(MID(Table3[[#This Row],[Unit Price]],2,50)) -> 3500 | Y6: =_xlfn.IFNA(_xlfn.XLOOKUP(Table3[[#This Row],[Country Code]],Lookups!$A$2:$A$5,Lookups!$E$2:$E$5),"") -> 7.7255 | Z6: =Table3[[#This Row],[Unit Price (local)]]/Table3[[#This Row],[FX Rate (per EUR)]] -> 453.04511 | AA6: 1000 | AB6: 10 | AC6: =ROUND(Table3[[#This Row],[Unit Price (EUR)]]*Table3[[#This Row],[Units Sold]],0) -> 453045 | AD6: =ROUND(Table3[[#This Row],[Gross Sales (EUR)]]*(1-Table3[[#This Row],[Discount (%)]]/100),0) -> 407741 | AE6: =_xlfn.IFNA(_xlfn.XLOOKUP(Table3[[#This Row],[Month]],Lookups!$N$2:$N$13,Lookups!$O$2:$O$13),"CHECK MONTH") -> 1 | AF6: =TEXT(Table3[[#This Row],[Month No]],"00")&" - "&Table3[[#This Row],[Month]] -> 01 - January | AG6: =_xlfn.IFNA(_xlfn.XLOOKUP(Table3[[#This Row],[Month]],Lookups!$N$2:$N$13,Lookups!$P$2:$P$13),"CHECK MONTH") -> Q1 | AH6: =Table3[[#This Row],[Gross Sales (EUR)]]-Table3[[#This Row],[Total Sales (EUR)]] -> 45304 | AI6: =DATE(Lookups!$O$15,Table3[[#This Row],[Month No]],1) -> 45658
A7: 6 | B7: Fang | C7: Liu | D7: =TRIM(Table3[[#This Row],[Rep Last Name]])&", "&TRIM(Table3[[#This Row],[Rep First Name]]) -> Liu, Fang | E7: January | F7: Electric Skateboard | H7: =IF(Table3[[#This Row],[Min Speed (original, incomplete)]]="",_xlfn.IFNA(_xlfn.XLOOKUP(Table3[[#This Row],[Product Type]],Lookups!$G$2:$G$4,Lookups!$H$2:$H$4),"CHECK PRODUCT"),Table3[[#This Row],[Min Speed (original, incomplete)]]) -> 18 mph | I7: 28 mph | J7: 40,230 meters | K7: =ROUND(VALUE(SUBSTITUTE(Table3[[#This Row],[Min Speed (mph)]]," mph",""))*Lookups!$L$2,0) -> 29 | L7: =ROUND(VALUE(SUBSTITUTE(Table3[[#This Row],[Speed]]," mph",""))*Lookups!$L$2,0) -> 45 | M7: =Table3[[#This Row],[Min Speed (km/h)]]&" – "&Table3[[#This Row],[Max Speed (km/h)]]&" km/h" -> 29 – 45 km/h | N7: =IF(ISNUMBER(SEARCH("mile",Table3[[#This Row],[Distance]])),ROUND(VALUE(SUBSTITUTE(Table3[[#This Row],[Distance]]," miles",""))*Lookups!$L$3,0),ROUND(VALUE(SUBSTITUTE(Table3[[#This Row],[Distance]]," meters",""))*Lookups!$L$4,0)) -> 40 | O7: 101 Nanjing Road, Shanghai, 200001 | P7: =TRIM(LEFT(Table3[[#This Row],[Shipping Address]],FIND(",",Table3[[#This Row],[Shipping Address]])-1)) -> 101 Nanjing Road | Q7: =TRIM(MID(Table3[[#This Row],[Shipping Address]],FIND(",",Table3[[#This Row],[Shipping Address]])+1,FIND(",",Table3[[#This Row],[Shipping Address]],FIND(",",Table3[[#This Row],[Shipping Address]])+1)-FIND(",",Table3[[#This Row],[Shipping Address]])-1)) -> Shanghai | R7: =TRIM(MID(Table3[[#This Row],[Shipping Address]],FIND(",",Table3[[#This Row],[Shipping Address]],FIND(",",Table3[[#This Row],[Shipping Address]])+1)+1,20)) -> 200001 | S7: CN | T7: =_xlfn.IFNA(_xlfn.XLOOKUP(Table3[[#This Row],[Country Code]],Lookups!$A$2:$A$5,Lookups!$B$2:$B$5),"CHECK CODE") -> China | U7: =_xlfn.IFNA(_xlfn.XLOOKUP(Table3[[#This Row],[Country Code]],Lookups!$A$2:$A$5,Lookups!$C$2:$C$5),"CHECK CODE") -> Asia | V7: ¥4,200 | W7: =_xlfn.IFNA(_xlfn.XLOOKUP(Table3[[#This Row],[Country Code]],Lookups!$A$2:$A$5,Lookups!$D$2:$D$5),"CHECK CODE") -> CNY | X7: =VALUE(MID(Table3[[#This Row],[Unit Price]],2,50)) -> 4200 | Y7: =_xlfn.IFNA(_xlfn.XLOOKUP(Table3[[#This Row],[Country Code]],Lookups!$A$2:$A$5,Lookups!$E$2:$E$5),"") -> 7.7255 | Z7: =Table3[[#This Row],[Unit Price (local)]]/Table3[[#This Row],[FX Rate (per EUR)]] -> 543.65413 | AA7: 800 | AB7: 10 | AC7: =ROUND(Table3[[#This Row],[Unit Price (EUR)]]*Table3[[#This Row],[Units Sold]],0) -> 434923 | AD7: =ROUND(Table3[[#This Row],[Gross Sales (EUR)]]*(1-Table3[[#This Row],[Discount (%)]]/100),0) -> 391431 | AE7: =_xlfn.IFNA(_xlfn.XLOOKUP(Table3[[#This Row],[Month]],Lookups!$N$2:$N$13,Lookups!$O$2:$O$13),"CHECK MONTH") -> 1 | AF7: =TEXT(Table3[[#This Row],[Month No]],"00")&" - "&Table3[[#This Row],[Month]] -> 01 - January | AG7: =_xlfn.IFNA(_xlfn.XLOOKUP(Table3[[#This Row],[Month]],Lookups!$N$2:$N$13,Lookups!$P$2:$P$13),"CHECK MONTH") -> Q1 | AH7: =Table3[[#This Row],[Gross Sales (EUR)]]-Table3[[#This Row],[Total Sales (EUR)]] -> 43492 | AI7: =DATE(Lookups!$O$15,Table3[[#This Row],[Month No]],1) -> 45658
A8: 7 | B8: Jonas | C8: Fischer | D8: =TRIM(Table3[[#This Row],[Rep Last Name]])&", "&TRIM(Table3[[#This Row],[Rep First Name]]) -> Fischer, Jonas | E8: January | F8: Electric Unicycle | G8: 15 mph | H8: =IF(Table3[[#This Row],[Min Speed (original, incomplete)]]="",_xlfn.IFNA(_xlfn.XLOOKUP(Table3[[#This Row],[Product Type]],Lookups!$G$2:$G$4,Lookups!$H$2:$H$4),"CHECK PRODUCT"),Table3[[#This Row],[Min Speed (original, incomplete)]]) -> 15 mph | I8: 30 mph | J8: 48,280 meters | K8: =ROUND(VALUE(SUBSTITUTE(Table3[[#This Row],[Min Speed (mph)]]," mph",""))*Lookups!$L$2,0) -> 24 | L8: =ROUND(VALUE(SUBSTITUTE(Table3[[#This Row],[Speed]]," mph",""))*Lookups!$L$2,0) -> 48 | M8: =Table3[[#This Row],[Min Speed (km/h)]]&" – "&Table3[[#This Row],[Max Speed (km/h)]]&" km/h" -> 24 – 48 km/h | N8: =IF(ISNUMBER(SEARCH("mile",Table3[[#This Row],[Distance]])),ROUND(VALUE(SUBSTITUTE(Table3[[#This Row],[Distance]]," miles",""))*Lookups!$L$3,0),ROUND(VALUE(SUBSTITUTE(Table3[[#This Row],[Distance]]," meters",""))*Lookups!$L$4,0)) -> 48 | O8: 303 Ringstraße, Hamburg, 20095 | P8: =TRIM(LEFT(Table3[[#This Row],[Shipping Address]],FIND(",",Table3[[#This Row],[Shipping Address]])-1)) -> 303 Ringstraße | Q8: =TRIM(MID(Table3[[#This Row],[Shipping Address]],FIND(",",Table3[[#This Row],[Shipping Address]])+1,FIND(",",Table3[[#This Row],[Shipping Address]],FIND(",",Table3[[#This Row],[Shipping Address]])+1)-FIND(",",Table3[[#This Row],[Shipping Address]])-1)) -> Hamburg | R8: =TRIM(MID(Table3[[#This Row],[Shipping Address]],FIND(",",Table3[[#This Row],[Shipping Address]],FIND(",",Table3[[#This Row],[Shipping Address]])+1)+1,20)) -> 20095 | S8: DE | T8: =_xlfn.IFNA(_xlfn.XLOOKUP(Table3[[#This Row],[Country Code]],Lookups!$A$2:$A$5,Lookups!$B$2:$B$5),"CHECK CODE") -> Germany | U8: =_xlfn.IFNA(_xlfn.XLOOKUP(Table3[[#This Row],[Country Code]],Lookups!$A$2:$A$5,Lookups!$C$2:$C$5),"CHECK CODE") -> Europe | V8: €1000 | W8: =_xlfn.IFNA(_xlfn.XLOOKUP(Table3[[#This Row],[Country Code]],Lookups!$A$2:$A$5,Lookups!$D$2:$D$5),"CHECK CODE") -> EUR | X8: =VALUE(MID(Table3[[#This Row],[Unit Price]],2,50)) -> 1000 | Y8: =_xlfn.IFNA(_xlfn.XLOOKUP(Table3[[#This Row],[Country Code]],Lookups!$A$2:$A$5,Lookups!$E$2:$E$5),"") -> 1 | Z8: =Table3[[#This Row],[Unit Price (local)]]/Table3[[#This Row],[FX Rate (per EUR)]] -> 1000 | AA8: 120 | AB8: 10 | AC8: =ROUND(Table3[[#This Row],[Unit Price (EUR)]]*Table3[[#This Row],[Units Sold]],0) -> 120000 | AD8: =ROUND(Table3[[#This Row],[Gross Sales (EUR)]]*(1-Table3[[#This Row],[Discount (%)]]/100),0) -> 108000 | AE8: =_xlfn.IFNA(_xlfn.XLOOKUP(Table3[[#This Row],[Month]],Lookups!$N$2:$N$13,Lookups!$O$2:$O$13),"CHECK MONTH") -> 1 | AF8: =TEXT(Table3[[#This Row],[Month No]],"00")&" - "&Table3[[#This Row],[Month]] -> 01 - January | AG8: =_xlfn.IFNA(_xlfn.XLOOKUP(Table3[[#This Row],[Month]],Lookups!$N$2:$N$13,Lookups!$P$2:$P$13),"CHECK MONTH") -> Q1 | AH8: =Table3[[#This Row],[Gross Sales (EUR)]]-Table3[[#This Row],[Total Sales (EUR)]] -> 12000 | AI8: =DATE(Lookups!$O$15,Table3[[#This Row],[Month No]],1) -> 45658
A9: 8 | B9: Jonas | C9: Fischer | D9: =TRIM(Table3[[#This Row],[Rep Last Name]])&", "&TRIM(Table3[[#This Row],[Rep First Name]]) -> Fischer, Jonas | E9: January | F9: Electric Scooter | G9: 20 mph | H9: =IF(Table3[[#This Row],[Min Speed (original, incomplete)]]="",_xlfn.IFNA(_xlfn.XLOOKUP(Table3[[#This Row],[Product Type]],Lookups!$G$2:$G$4,Lookups!$H$2:$H$4),"CHECK PRODUCT"),Table3[[#This Row],[Min Speed (original, incomplete)]]) -> 20 mph | I9: 35 mph | J9: 40 miles | K9: =ROUND(VALUE(SUBSTITUTE(Table3[[#This Row],[Min Speed (mph)]]," mph",""))*Lookups!$L$2,0) -> 32 | L9: =ROUND(VALUE(SUBSTITUTE(Table3[[#This Row],[Speed]]," mph",""))*Lookups!$L$2,0) -> 56 | M9: =Table3[[#This Row],[Min Speed (km/h)]]&" – "&Table3[[#This Row],[Max Speed (km/h)]]&" km/h" -> 32 – 56 km/h | N9: =IF(ISNUMBER(SEARCH("mile",Table3[[#This Row],[Distance]])),ROUND(VALUE(SUBSTITUTE(Table3[[#This Row],[Distance]]," miles",""))*Lookups!$L$3,0),ROUND(VALUE(SUBSTITUTE(Table3[[#This Row],[Distance]]," meters",""))*Lookups!$L$4,0)) -> 64 | O9: 304 Ringstraße, Hamburg, 20095 | P9: =TRIM(LEFT(Table3[[#This Row],[Shipping Address]],FIND(",",Table3[[#This Row],[Shipping Address]])-1)) -> 304 Ringstraße | Q9: =TRIM(MID(Table3[[#This Row],[Shipping Address]],FIND(",",Table3[[#This Row],[Shipping Address]])+1,FIND(",",Table3[[#This Row],[Shipping Address]],FIND(",",Table3[[#This Row],[Shipping Address]])+1)-FIND(",",Table3[[#This Row],[Shipping Address]])-1)) -> Hamburg | R9: =TRIM(MID(Table3[[#This Row],[Shipping Address]],FIND(",",Table3[[#This Row],[Shipping Address]],FIND(",",Table3[[#This Row],[Shipping Address]])+1)+1,20)) -> 20095 | S9: DE | T9: =_xlfn.IFNA(_xlfn.XLOOKUP(Table3[[#This Row],[Country Code]],Lookups!$A$2:$A$5,Lookups!$B$2:$B$5),"CHECK CODE") -> Germany | U9: =_xlfn.IFNA(_xlfn.XLOOKUP(Table3[[#This Row],[Country Code]],Lookups!$A$2:$A$5,Lookups!$C$2:$C$5),"CHECK CODE") -> Europe | V9: €800 | W9: =_xlfn.IFNA(_xlfn.XLOOKUP(Table3[[#This Row],[Country Code]],Lookups!$A$2:$A$5,Lookups!$D$2:$D$5),"CHECK CODE") -> EUR | X9: =VALUE(MID(Table3[[#This Row],[Unit Price]],2,50)) -> 800 | Y9: =_xlfn.IFNA(_xlfn.XLOOKUP(Table3[[#This Row],[Country Code]],Lookups!$A$2:$A$5,Lookups!$E$2:$E$5),"") -> 1 | Z9: =Table3[[#This Row],[Unit Price (local)]]/Table3[[#This Row],[FX Rate (per EUR)]] -> 800 | AA9: 200 | AB9: 10 | AC9: =ROUND(Table3[[#This Row],[Unit Price (EUR)]]*Table3[[#This Row],[Units Sold]],0) -> 160000 | AD9: =ROUND(Table3[[#This Row],[Gross Sales (EUR)]]*(1-Table3[[#This Row],[Discount (%)]]/100),0) -> 144000 | AE9: =_xlfn.IFNA(_xlfn.XLOOKUP(Table3[[#This Row],[Month]],Lookups!$N$2:$N$13,Lookups!$O$2:$O$13),"CHECK MONTH") -> 1 | AF9: =TEXT(Table3[[#This Row],[Month No]],"00")&" - "&Table3[[#This Row],[Month]] -> 01 - January | AG9: =_xlfn.IFNA(_xlfn.XLOOKUP(Table3[[#This Row],[Month]],Lookups!$N$2:$N$13,Lookups!$P$2:$P$13),"CHECK MONTH") -> Q1 | AH9: =Table3[[#This Row],[Gross Sales (EUR)]]-Table3[[#This Row],[Total Sales (EUR)]] -> 16000 | AI9: =DATE(Lookups!$O$15,Table3[[#This Row],[Month No]],1) -> 45658
A10: 9 | B10: Jonas | C10: Fischer | D10: =TRIM(Table3[[#This Row],[Rep Last Name]])&", "&TRIM(Table3[[#This Row],[Rep First Name]]) -> Fischer, Jonas | E10: January | F10: Electric Skateboard | G10: 18 mph | H10: =IF(Table3[[#This Row],[Min Speed (original, incomplete)]]="",_xlfn.IFNA(_xlfn.XLOOKUP(Table3[[#This Row],[Product Type]],Lookups!$G$2:$G$4,Lookups!$H$2:$H$4),"CHECK PRODUCT"),Table3[[#This Row],[Min Speed (original, incomplete)]]) -> 18 mph | I10: 28 mph | J10: 25 miles | K10: =ROUND(VALUE(SUBSTITUTE(Table3[[#This Row],[Min Speed (mph)]]," mph",""))*Lookups!$L$2,0) -> 29 | L10: =ROUND(VALUE(SUBSTITUTE(Table3[[#This Row],[Speed]]," mph",""))*Lookups!$L$2,0) -> 45 | M10: =Table3[[#This Row],[Min Speed (km/h)]]&" – "&Table3[[#This Row],[Max Speed (km/h)]]&" km/h" -> 29 – 45 km/h | N10: =IF(ISNUMBER(SEARCH("mile",Table3[[#This Row],[Distance]])),ROUND(VALUE(SUBSTITUTE(Table3[[#This Row],[Distance]]," miles",""))*Lookups!$L$3,0),ROUND(VALUE(SUBSTITUTE(Table3[[#This Row],[Distance]]," meters",""))*Lookups!$L$4,0)) -> 40 | O10: 305 Ringstraße, Hamburg, 20095 | P10: =TRIM(LEFT(Table3[[#This Row],[Shipping Address]],FIND(",",Table3[[#This Row],[Shipping Address]])-1)) -> 305 Ringstraße | Q10: =TRIM(MID(Table3[[#This Row],[Shipping Address]],FIND(",",Table3[[#This Row],[Shipping Address]])+1,FIND(",",Table3[[#This Row],[Shipping Address]],FIND(",",Table3[[#This Row],[Shipping Address]])+1)-FIND(",",Table3[[#This Row],[Shipping Address]])-1)) -> Hamburg | R10: =TRIM(MID(Table3[[#This Row],[Shipping Address]],FIND(",",Table3[[#This Row],[Shipping Address]],FIND(",",Table3[[#This Row],[Shipping Address]])+1)+1,20)) -> 20095 | S10: DE | T10: =_xlfn.IFNA(_xlfn.XLOOKUP(Table3[[#This Row],[Country Code]],Lookups!$A$2:$A$5,Lookups!$B$2:$B$5),"CHECK CODE") -> Germany | U10: =_xlfn.IFNA(_xlfn.XLOOKUP(Table3[[#This Row],[Country Code]],Lookups!$A$2:$A$5,Lookups!$C$2:$C$5),"CHECK CODE") -> Europe | V10: €950 | W10: =_xlfn.IFNA(_xlfn.XLOOKUP(Table3[[#This Row],[Country Code]],Lookups!$A$2:$A$5,Lookups!$D$2:$D$5),"CHECK CODE") -> EUR | X10: =VALUE(MID(Table3[[#This Row],[Unit Price]],2,50)) -> 950 | Y10: =_xlfn.IFNA(_xlfn.XLOOKUP(Table3[[#This Row],[Country Code]],Lookups!$A$2:$A$5,Lookups!$E$2:$E$5),"") -> 1 | Z10: =Table3[[#This Row],[Unit Price (local)]]/Table3[[#This Row],[FX Rate (per EUR)]] -> 950 | AA10: 150 | AB10: 10 | AC10: =ROUND(Table3[[#This Row],[Unit Price (EUR)]]*Table3[[#This Row],[Units Sold]],0) -> 142500 | AD10: =ROUND(Table3[[#This Row],[Gross Sales (EUR)]]*(1-Table3[[#This Row],[Discount (%)]]/100),0) -> 128250 | AE10: =_xlfn.IFNA(_xlfn.XLOOKUP(Table3[[#This Row],[Month]],Lookups!$N$2:$N$13,Lookups!$O$2:$O$13),"CHECK MONTH") -> 1 | AF10: =TEXT(Table3[[#This Row],[Month No]],"00")&" - "&Table3[[#This Row],[Month]] -> 01 - January | AG10: =_xlfn.IFNA(_xlfn.XLOOKUP(Table3[[#This Row],[Month]],Lookups!$N$2:$N$13,Lookups!$P$2:$P$13),"CHECK MONTH") -> Q1 | AH10: =Table3[[#This Row],[Gross Sales (EUR)]]-Table3[[#This Row],[Total Sales (EUR)]] -> 14250 | AI10: =DATE(Lookups!$O$15,Table3[[#This Row],[Month No]],1) -> 45658
A11: 10 | B11: Théo | C11: Bernard | D11: =TRIM(Table3[[#This Row],[Rep Last Name]])&", "&TRIM(Table3[[#This Row],[Rep First Name]]) -> Bernard, Théo | E11: January | F11: Electric Unicycle | G11: 15 mph | H11: =IF(Table3[[#This Row],[Min Speed (original, incomplete)]]="",_xlfn.IFNA(_xlfn.XLOOKUP(Table3[[#This Row],[Product Type]],Lookups!$G$2:$G$4,Lookups!$H$2:$H$4),"CHECK PRODUCT"),Table3[[#This Row],[Min Speed (original, incomplete)]]) -> 15 mph | I11: 30 mph | J11: 30 miles | K11: =ROUND(VALUE(SUBSTITUTE(Table3[[#This Row],[Min Speed (mph)]]," mph",""))*Lookups!$L$2,0) -> 24 | L11: =ROUND(VALUE(SUBSTITUTE(Table3[[#This Row],[Speed]]," mph",""))*Lookups!$L$2,0) -> 48 | M11: =Table3[[#This Row],[Min Speed (km/h)]]&" – "&Table3[[#This Row],[Max Speed (km/h)]]&" km/h" -> 24 – 48 km/h | N11: =IF(ISNUMBER(SEARCH("mile",Table3[[#This Row],[Distance]])),ROUND(VALUE(SUBSTITUTE(Table3[[#This Row],[Distance]]," miles",""))*Lookups!$L$3,0),ROUND(VALUE(SUBSTITUTE(Table3[[#This Row],[Distance]]," meters",""))*Lookups!$L$4,0)) -> 48 | O11: 56 Boulevard Saint-Germain, Paris, 75005 | P11: =TRIM(LEFT(Table3[[#This Row],[Shipping Address]],FIND(",",Table3[[#This Row],[Shipping Address]])-1)) -> 56 Boulevard Saint-Germain | Q11: =TRIM(MID(Table3[[#This Row],[Shipping Address]],FIND(",",Table3[[#This Row],[Shipping Address]])+1,FIND(",",Table3[[#This Row],[Shipping Address]],FIND(",",Table3[[#This Row],[Shipping Address]])+1)-FIND(",",Table3[[#This Row],[Shipping Address]])-1)) -> Paris | R11: =TRIM(MID(Table3[[#This Row],[Shipping Address]],FIND(",",Table3[[#This Row],[Shipping Address]],FIND(",",Table3[[#This Row],[Shipping Address]])+1)+1,20)) -> 75005 | S11: FR | T11: =_xlfn.IFNA(_xlfn.XLOOKUP(Table3[[#This Row],[Country Code]],Lookups!$A$2:$A$5,Lookups!$B$2:$B$5),"CHECK CODE") -> France | U11: =_xlfn.IFNA(_xlfn.XLOOKUP(Table3[[#This Row],[Country Code]],Lookups!$A$2:$A$5,Lookups!$C$2:$C$5),"CHECK CODE") -> Europe | V11: €1100 | W11: =_xlfn.IFNA(_xlfn.XLOOKUP(Table3[[#This Row],[Country Code]],Lookups!$A$2:$A$5,Lookups!$D$2:$D$5),"CHECK CODE") -> EUR | X11: =VALUE(MID(Table3[[#This Row],[Unit Price]],2,50)) -> 1100 | Y11: =_xlfn.IFNA(_xlfn.XLOOKUP(Table3[[#This Row],[Country Code]],Lookups!$A$2:$A$5,Lookups!$E$2:$E$5),"") -> 1 | Z11: =Table3[[#This Row],[Unit Price (local)]]/Table3[[#This Row],[FX Rate (per EUR)]] -> 1100 | AA11: 100 | AB11: 10 | AC11: =ROUND(Table3[[#This Row],[Unit Price (EUR)]]*Table3[[#This Row],[Units Sold]],0) -> 110000 | AD11: =ROUND(Table3[[#This Row],[Gross Sales (EUR)]]*(1-Table3[[#This Row],[Discount (%)]]/100),0) -> 99000 | AE11: =_xlfn.IFNA(_xlfn.XLOOKUP(Table3[[#This Row],[Month]],Lookups!$N$2:$N$13,Lookups!$O$2:$O$13),"CHECK MONTH") -> 1 | AF11: =TEXT(Table3[[#This Row],[Month No]],"00")&" - "&Table3[[#This Row],[Month]] -> 01 - January | AG11: =_xlfn.IFNA(_xlfn.XLOOKUP(Table3[[#This Row],[Month]],Lookups!$N$2:$N$13,Lookups!$P$2:$P$13),"CHECK MONTH") -> Q1 | AH11: =Table3[[#This Row],[Gross Sales (EUR)]]-Table3[[#This Row],[Total Sales (EUR)]] -> 11000 | AI11: =DATE(Lookups!$O$15,Table3[[#This Row],[Month No]],1) -> 45658
A12: 11 | B12: Théo | C12: Bernard | D12: =TRIM(Table3[[#This Row],[Rep Last Name]])&", "&TRIM(Table3[[#This Row],[Rep First Name]]) -> Bernard, Théo | E12: January | F12: Electric Scooter | G12: 20 mph | H12: =IF(Table3[[#This Row],[Min Speed (original, incomplete)]]="",_xlfn.IFNA(_xlfn.XLOOKUP(Table3[[#This Row],[Product Type]],Lookups!$G$2:$G$4,Lookups!$H$2:$H$4),"CHECK PRODUCT"),Table3[[#This Row],[Min Speed (original, incomplete)]]) -> 20 mph | I12: 35 mph | J12: 64,370 meters | K12: =ROUND(VALUE(SUBSTITUTE(Table3[[#This Row],[Min Speed (mph)]]," mph",""))*Lookups!$L$2,0) -> 32 | L12: =ROUND(VALUE(SUBSTITUTE(Table3[[#This Row],[Speed]]," mph",""))*Lookups!$L$2,0) -> 56 | M12: =Table3[[#This Row],[Min Speed (km/h)]]&" – "&Table3[[#This Row],[Max Speed (km/h)]]&" km/h" -> 32 – 56 km/h | N12: =IF(ISNUMBER(SEARCH("mile",Table3[[#This Row],[Distance]])),ROUND(VALUE(SUBSTITUTE(Table3[[#This Row],[Distance]]," miles",""))*Lookups!$L$3,0),ROUND(VALUE(SUBSTITUTE(Table3[[#This Row],[Distance]]," meters",""))*Lookups!$L$4,0)) -> 64 | O12: 57 Boulevard Saint-Germain, Paris, 75005 | P12: =TRIM(LEFT(Table3[[#This Row],[Shipping Address]],FIND(",",Table3[[#This Row],[Shipping Address]])-1)) -> 57 Boulevard Saint-Germain | Q12: =TRIM(MID(Table3[[#This Row],[Shipping Address]],FIND(",",Table3[[#This Row],[Shipping Address]])+1,FIND(",",Table3[[#This Row],[Shipping Address]],FIND(",",Table3[[#This Row],[Shipping Address]])+1)-FIND(",",Table3[[#This Row],[Shipping Address]])-1)) -> Paris | R12: =TRIM(MID(Table3[[#This Row],[Shipping Address]],FIND(",",Table3[[#This Row],[Shipping Address]],FIND(",",Table3[[#This Row],[Shipping Address]])+1)+1,20)) -> 75005 | S12: FR | T12: =_xlfn.IFNA(_xlfn.XLOOKUP(Table3[[#This Row],[Country Code]],Lookups!$A$2:$A$5,Lookups!$B$2:$B$5),"CHECK CODE") -> France | U12: =_xlfn.IFNA(_xlfn.XLOOKUP(Table3[[#This Row],[Country Code]],Lookups!$A$2:$A$5,Lookups!$C$2:$C$5),"CHECK CODE") -> Europe | V12: €900 | W12: =_xlfn.IFNA(_xlfn.XLOOKUP(Table3[[#This Row],[Country Code]],Lookups!$A$2:$A$5,Lookups!$D$2:$D$5),"CHECK CODE") -> EUR | X12: =VALUE(MID(Table3[[#This Row],[Unit Price]],2,50)) -> 900 | Y12: =_xlfn.IFNA(_xlfn.XLOOKUP(Table3[[#This Row],[Country Code]],Lookups!$A$2:$A$5,Lookups!$E$2:$E$5),"") -> 1 | Z12: =Table3[[#This Row],[Unit Price (local)]]/Table3[[#This Row],[FX Rate (per EUR)]] -> 900 | AA12: 250 | AB12: 10 | AC12: =ROUND(Table3[[#This Row],[Unit Price (EUR)]]*Table3[[#This Row],[Units Sold]],0) -> 225000 | AD12: =ROUND(Table3[[#This Row],[Gross Sales (EUR)]]*(1-Table3[[#This Row],[Discount (%)]]/100),0) -> 202500 | AE12: =_xlfn.IFNA(_xlfn.XLOOKUP(Table3[[#This Row],[Month]],Lookups!$N$2:$N$13,Lookups!$O$2:$O$13),"CHECK MONTH") -> 1 | AF12: =TEXT(Table3[[#This Row],[Month No]],"00")&" - "&Table3[[#This Row],[Month]] -> 01 - January | AG12: =_xlfn.IFNA(_xlfn.XLOOKUP(Table3[[#This Row],[Month]],Lookups!$N$2:$N$13,Lookups!$P$2:$P$13),"CHECK MONTH") -> Q1 | AH12: =Table3[[#This Row],[Gross Sales (EUR)]]-Table3[[#This Row],[Total Sales (EUR)]] -> 22500 | AI12: =DATE(Lookups!$O$15,Table3[[#This Row],[Month No]],1) -> 45658
A13: 12 | B13: Théo | C13: Bernard | D13: =TRIM(Table3[[#This Row],[Rep Last Name]])&", "&TRIM(Table3[[#This Row],[Rep First Name]]) -> Bernard, Théo | E13: January | F13: Electric Skateboard | G13: 18 mph | H13: =IF(Table3[[#This Row],[Min Speed (original, incomplete)]]="",_xlfn.IFNA(_xlfn.XLOOKUP(Table3[[#This Row],[Product Type]],Lookups!$G$2:$G$4,Lookups!$H$2:$H$4),"CHECK PRODUCT"),Table3[[#This Row],[Min Speed (original, incomplete)]]) -> 18 mph | I13: 28 mph | J13: 25 miles | K13: =ROUND(VALUE(SUBSTITUTE(Table3[[#This Row],[Min Speed (mph)]]," mph",""))*Lookups!$L$2,0) -> 29 | L13: =ROUND(VALUE(SUBSTITUTE(Table3[[#This Row],[Speed]]," mph",""))*Lookups!$L$2,0) -> 45 | M13: =Table3[[#This Row],[Min Speed (km/h)]]&" – "&Table3[[#This Row],[Max Speed (km/h)]]&" km/h" -> 29 – 45 km/h | N13: =IF(ISNUMBER(SEARCH("mile",Table3[[#This Row],[Distance]])),ROUND(VALUE(SUBSTITUTE(Table3[[#This Row],[Distance]]," miles",""))*Lookups!$L$3,0),ROUND(VALUE(SUBSTITUTE(Table3[[#This Row],[Distance]]," meters",""))*Lookups!$L$4,0)) -> 40 | O13: 58 Boulevard Saint-Germain, Paris, 75005 | P13: =TRIM(LEFT(Table3[[#This Row],[Shipping Address]],FIND(",",Table3[[#This Row],[Shipping Address]])-1)) -> 58 Boulevard Saint-Germain | Q13: =TRIM(MID(Table3[[#This Row],[Shipping Address]],FIND(",",Table3[[#This Row],[Shipping Address]])+1,FIND(",",Table3[[#This Row],[Shipping Address]],FIND(",",Table3[[#This Row],[Shipping Address]])+1)-FIND(",",Table3[[#This Row],[Shipping Address]])-1)) -> Paris | R13: =TRIM(MID(Table3[[#This Row],[Shipping Address]],FIND(",",Table3[[#This Row],[Shipping Address]],FIND(",",Table3[[#This Row],[Shipping Address]])+1)+1,20)) -> 75005 | S13: FR | T13: =_xlfn.IFNA(_xlfn.XLOOKUP(Table3[[#This Row],[Country Code]],Lookups!$A$2:$A$5,Lookups!$B$2:$B$5),"CHECK CODE") -> France | U13: =_xlfn.IFNA(_xlfn.XLOOKUP(Table3[[#This Row],[Country Code]],Lookups!$A$2:$A$5,Lookups!$C$2:$C$5),"CHECK CODE") -> Europe | V13: €1050 | W13: =_xlfn.IFNA(_xlfn.XLOOKUP(Table3[[#This Row],[Country Code]],Lookups!$A$2:$A$5,Lookups!$D$2:$D$5),"CHECK CODE") -> EUR | X13: =VALUE(MID(Table3[[#This Row],[Unit Price]],2,50)) -> 1050 | Y13: =_xlfn.IFNA(_xlfn.XLOOKUP(Table3[[#This Row],[Country Code]],Lookups!$A$2:$A$5,Lookups!$E$2:$E$5),"") -> 1 | Z13: =Table3[[#This Row],[Unit Price (local)]]/Table3[[#This Row],[FX Rate (per EUR)]] -> 1050 | AA13: 180 | AB13: 10 | AC13: =ROUND(Table3[[#This Row],[Unit Price (EUR)]]*Table3[[#This Row],[Units Sold]],0) -> 189000 | AD13: =ROUND(Table3[[#This Row],[Gross Sales (EUR)]]*(1-Table3[[#This Row],[Discount (%)]]/100),0) -> 170100 | AE13: =_xlfn.IFNA(_xlfn.XLOOKUP(Table3[[#This Row],[Month]],Lookups!$N$2:$N$13,Lookups!$O$2:$O$13),"CHECK MONTH") -> 1 | AF13: =TEXT(Table3[[#This Row],[Month No]],"00")&" - "&Table3[[#This Row],[Month]] -> 01 - January | AG13: =_xlfn.IFNA(_xlfn.XLOOKUP(Table3[[#This Row],[Month]],Lookups!$N$2:$N$13,Lookups!$P$2:$P$13),"CHECK MONTH") -> Q1 | AH13: =Table3[[#This Row],[Gross Sales (EUR)]]-Table3[[#This Row],[Total Sales (EUR)]] -> 18900 | AI13: =DATE(Lookups!$O$15,Table3[[#This Row],[Month No]],1) -> 45658
A14: 13 | B14: Sanya | C14: Joshi | D14: =TRIM(Table3[[#This Row],[Rep Last Name]])&", "&TRIM(Table3[[#This Row],[Rep First Name]]) -> Joshi, Sanya | E14: February | F14: Electric Unicycle | G14: 15 mph | H14: =IF(Table3[[#This Row],[Min Speed (original, incomplete)]]="",_xlfn.IFNA(_xlfn.XLOOKUP(Table3[[#This Row],[Product Type]],Lookups!$G$2:$G$4,Lookups!$H$2:$H$4),"CHECK PRODUCT"),Table3[[#This Row],[Min Speed (original, incomplete)]]) -> 15 mph | I14: 30 mph | J14: 30 miles | K14: =ROUND(VALUE(SUBSTITUTE(Table3[[#This Row],[Min Speed (mph)]]," mph",""))*Lookups!$L$2,0) -> 24 | L14: =ROUND(VALUE(SUBSTITUTE(Table3[[#This Row],[Speed]]," mph",""))*Lookups!$L$2,0) -> 48 | M14: =Table3[[#This Row],[Min Speed (km/h)]]&" – "&Table3[[#This Row],[Max Speed (km/h)]]&" km/h" -> 24 – 48 km/h | N14: =IF(ISNUMBER(SEARCH("mile",Table3[[#This Row],[Distance]])),ROUND(VALUE(SUBSTITUTE(Table3[[#This Row],[Distance]]," miles",""))*Lookups!$L$3,0),ROUND(VALUE(SUBSTITUTE(Table3[[#This Row],[Distance]]," meters",""))*Lookups!$L$4,0)) -> 48 | O14: 456 Brigade Road, Bengaluru, 560001 | P14: =TRIM(LEFT(Table3[[#This Row],[Shipping Address]],FIND(",",Table3[[#This Row],[Shipping Address]])-1)) -> 456 Brigade Road | Q14: =TRIM(MID(Table3[[#This Row],[Shipping Address]],FIND(",",Table3[[#This Row],[Shipping Address]])+1,FIND(",",Table3[[#This Row],[Shipping Address]],FIND(",",Table3[[#This Row],[Shipping Address]])+1)-FIND(",",Table3[[#This Row],[Shipping Address]])-1)) -> Bengaluru | R14: =TRIM(MID(Table3[[#This Row],[Shipping Address]],FIND(",",Table3[[#This Row],[Shipping Address]],FIND(",",Table3[[#This Row],[Shipping Address]])+1)+1,20)) -> 560001 | S14: IN | T14: =_xlfn.IFNA(_xlfn.XLOOKUP(Table3[[#This Row],[Country Code]],Lookups!$A$2:$A$5,Lookups!$B$2:$B$5),"CHECK CODE") -> India | U14: =_xlfn.IFNA(_xlfn.XLOOKUP(Table3[[#This Row],[Country Code]],Lookups!$A$2:$A$5,Lookups!$C$2:$C$5),"CHECK CODE") -> Asia | V14: ₹30,000 | W14: =_xlfn.IFNA(_xlfn.XLOOKUP(Table3[[#This Row],[Country Code]],Lookups!$A$2:$A$5,Lookups!$D$2:$D$5),"CHECK CODE") -> INR | X14: =VALUE(MID(Table3[[#This Row],[Unit Price]],2,50)) -> 30000 | Y14: =_xlfn.IFNA(_xlfn.XLOOKUP(Table3[[#This Row],[Country Code]],Lookups!$A$2:$A$5,Lookups!$E$2:$E$5),"") -> 109.882 | Z14: =Table3[[#This Row],[Unit Price (local)]]/Table3[[#This Row],[FX Rate (per EUR)]] -> 273.02015 | AA14: 160 | AB14: 0 | AC14: =ROUND(Table3[[#This Row],[Unit Price (EUR)]]*Table3[[#This Row],[Units Sold]],0) -> 43683 | AD14: =ROUND(Table3[[#This Row],[Gross Sales (EUR)]]*(1-Table3[[#This Row],[Discount (%)]]/100),0) -> 43683 | AE14: =_xlfn.IFNA(_xlfn.XLOOKUP(Table3[[#This Row],[Month]],Lookups!$N$2:$N$13,Lookups!$O$2:$O$13),"CHECK MONTH") -> 2 | AF14: =TEXT(Table3[[#This Row],[Month No]],"00")&" - "&Table3[[#This Row],[Month]] -> 02 - February | AG14: =_xlfn.IFNA(_xlfn.XLOOKUP(Table3[[#This Row],[Month]],Lookups!$N$2:$N$13,Lookups!$P$2:$P$13),"CHECK MONTH") -> Q1 | AH14: =Table3[[#This Row],[Gross Sales (EUR)]]-Table3[[#This Row],[Total Sales (EUR)]] -> 0 | AI14: =DATE(Lookups!$O$15,Table3[[#This Row],[Month No]],1) -> 45689
A15: 14 | B15: Sanya | C15: Joshi | D15: =TRIM(Table3[[#This Row],[Rep Last Name]])&", "&TRIM(Table3[[#This Row],[Rep First Name]]) -> Joshi, Sanya | E15: February | F15: Electric Scooter | H15: =IF(Table3[[#This Row],[Min Speed (original, incomplete)]]="",_xlfn.IFNA(_xlfn.XLOOKUP(Table3[[#This Row],[Product Type]],Lookups!$G$2:$G$4,Lookups!$H$2:$H$4),"CHECK PRODUCT"),Table3[[#This Row],[Min Speed (original, incomplete)]]) -> 20 mph | I15: 35 mph | J15: 40 miles | K15: =ROUND(VALUE(SUBSTITUTE(Table3[[#This Row],[Min Speed (mph)]]," mph",""))*Lookups!$L$2,0) -> 32 | L15: =ROUND(VALUE(SUBSTITUTE(Table3[[#This Row],[Speed]]," mph",""))*Lookups!$L$2,0) -> 56 | M15: =Table3[[#This Row],[Min Speed (km/h)]]&" – "&Table3[[#This Row],[Max Speed (km/h)]]&" km/h" -> 32 – 56 km/h | N15: =IF(ISNUMBER(SEARCH("mile",Table3[[#This Row],[Distance]])),ROUND(VALUE(SUBSTITUTE(Table3[[#This Row],[Distance]]," miles",""))*Lookups!$L$3,0),ROUND(VALUE(SUBSTITUTE(Table3[[#This Row],[Distance]]," meters",""))*Lookups!$L$4,0)) -> 64 | O15: 457 Brigade Road, Bengaluru, 560001 | P15: =TRIM(LEFT(Table3[[#This Row],[Shipping Address]],FIND(",",Table3[[#This Row],[Shipping Address]])-1)) -> 457 Brigade Road | Q15: =TRIM(MID(Table3[[#This Row],[Shipping Address]],FIND(",",Table3[[#This Row],[Shipping Address]])+1,FIND(",",Table3[[#This Row],[Shipping Address]],FIND(",",Table3[[#This Row],[Shipping Address]])+1)-FIND(",",Table3[[#This Row],[Shipping Address]])-1)) -> Bengaluru | R15: =TRIM(MID(Table3[[#This Row],[Shipping Address]],FIND(",",Table3[[#This Row],[Shipping Address]],FIND(",",Table3[[#This Row],[Shipping Address]])+1)+1,20)) -> 560001 | S15: IN | T15: =_xlfn.IFNA(_xlfn.XLOOKUP(Table3[[#This Row],[Country Code]],Lookups!$A$2:$A$5,Lookups!$B$2:$B$5),"CHECK CODE") -> India | U15: =_xlfn.IFNA(_xlfn.XLOOKUP(Table3[[#This Row],[Country Code]],Lookups!$A$2:$A$5,Lookups!$C$2:$C$5),"CHECK CODE") -> Asia | V15: ₹25,000 | W15: =_xlfn.IFNA(_xlfn.XLOOKUP(Table3[[#This Row],[Country Code]],Lookups!$A$2:$A$5,Lookups!$D$2:$D$5),"CHECK CODE") -> INR | X15: =VALUE(MID(Table3[[#This Row],[Unit Price]],2,50)) -> 25000 | Y15: =_xlfn.IFNA(_xlfn.XLOOKUP(Table3[[#This Row],[Country Code]],Lookups!$A$2:$A$5,Lookups!$E$2:$E$5),"") -> 109.882 | Z15: =Table3[[#This Row],[Unit Price (local)]]/Table3[[#This Row],[FX Rate (per EUR)]] -> 227.51679 | AA15: 350 | AB15: 0 | AC15: =ROUND(Table3[[#This Row],[Unit Price (EUR)]]*Table3[[#This Row],[Units Sold]],0) -> 79631 | AD15: =ROUND(Table3[[#This Row],[Gross Sales (EUR)]]*(1-Table3[[#This Row],[Discount (%)]]/100),0) -> 79631 | AE15: =_xlfn.IFNA(_xlfn.XLOOKUP(Table3[[#This Row],[Month]],Lookups!$N$2:$N$13,Lookups!$O$2:$O$13),"CHECK MONTH") -> 2 | AF15: =TEXT(Table3[[#This Row],[Month No]],"00")&" - "&Table3[[#This Row],[Month]] -> 02 - February | AG15: =_xlfn.IFNA(_xlfn.XLOOKUP(Table3[[#This Row],[Month]],Lookups!$N$2:$N$13,Lookups!$P$2:$P$13),"CHECK MONTH") -> Q1 | AH15: =Table3[[#This Row],[Gross Sales (EUR)]]-Table3[[#This Row],[Total Sales (EUR)]] -> 0 | AI15: =DATE(Lookups!$O$15,Table3[[#This Row],[Month No]],1) -> 45689
A16: 15 | B16: Sanya | C16: Joshi | D16: =TRIM(Table3[[#This Row],[Rep Last Name]])&", "&TRIM(Table3[[#This Row],[Rep First Name]]) -> Joshi, Sanya | E16: February | F16: Electric Skateboard | G16: 18 mph | H16: =IF(Table3[[#This Row],[Min Speed (original, incomplete)]]="",_xlfn.IFNA(_xlfn.XLOOKUP(Table3[[#This Row],[Product Type]],Lookups!$G$2:$G$4,Lookups!$H$2:$H$4),"CHECK PRODUCT"),Table3[[#This Row],[Min Speed (original, incomplete)]]) -> 18 mph | I16: 28 mph | J16: 25 miles | K16: =ROUND(VALUE(SUBSTITUTE(Table3[[#This Row],[Min Speed (mph)]]," mph",""))*Lookups!$L$2,0) -> 29 | L16: =ROUND(VALUE(SUBSTITUTE(Table3[[#This Row],[Speed]]," mph",""))*Lookups!$L$2,0) -> 45 | M16: =Table3[[#This Row],[Min Speed (km/h)]]&" – "&Table3[[#This Row],[Max Speed (km/h)]]&" km/h" -> 29 – 45 km/h | N16: =IF(ISNUMBER(SEARCH("mile",Table3[[#This Row],[Distance]])),ROUND(VALUE(SUBSTITUTE(Table3[[#This Row],[Distance]]," miles",""))*Lookups!$L$3,0),ROUND(VALUE(SUBSTITUTE(Table3[[#This Row],[Distance]]," meters",""))*Lookups!$L$4,0)) -> 40 | O16: 458 Brigade Road, Bengaluru, 560001 | P16: =TRIM(LEFT(Table3[[#This Row],[Shipping Address]],FIND(",",Table3[[#This Row],[Shipping Address]])-1)) -> 458 Brigade Road | Q16: =TRIM(MID(Table3[[#This Row],[Shipping Address]],FIND(",",Table3[[#This Row],[Shipping Address]])+1,FIND(",",Table3[[#This Row],[Shipping Address]],FIND(",",Table3[[#This Row],[Shipping Address]])+1)-FIND(",",Table3[[#This Row],[Shipping Address]])-1)) -> Bengaluru | R16: =TRIM(MID(Table3[[#This Row],[Shipping Address]],FIND(",",Table3[[#This Row],[Shipping Address]],FIND(",",Table3[[#This Row],[Shipping Address]])+1)+1,20)) -> 560001 | S16: IN | T16: =_xlfn.IFNA(_xlfn.XLOOKUP(Table3[[#This Row],[Country Code]],Lookups!$A$2:$A$5,Lookups!$B$2:$B$5),"CHECK CODE") -> India | U16: =_xlfn.IFNA(_xlfn.XLOOKUP(Table3[[#This Row],[Country Code]],Lookups!$A$2:$A$5,Lookups!$C$2:$C$5),"CHECK CODE") -> Asia | V16: ₹22,000 | W16: =_xlfn.IFNA(_xlfn.XLOOKUP(Table3[[#This Row],[Country Code]],Lookups!$A$2:$A$5,Lookups!$D$2:$D$5),"CHECK CODE") -> INR | X16: =VALUE(MID(Table3[[#This Row],[Unit Price]],2,50)) -> 22000 | Y16: =_xlfn.IFNA(_xlfn.XLOOKUP(Table3[[#This Row],[Country Code]],Lookups!$A$2:$A$5,Lookups!$E$2:$E$5),"") -> 109.882 | Z16: =Table3[[#This Row],[Unit Price (local)]]/Table3[[#This Row],[FX Rate (per EUR)]] -> 200.21478 | AA16: 220 | AB16: 0 | AC16: =ROUND(Table3[[#This Row],[Unit Price (EUR)]]*Table3[[#This Row],[Units Sold]],0) -> 44047 | AD16: =ROUND(Table3[[#This Row],[Gross Sales (EUR)]]*(1-Table3[[#This Row],[Discount (%)]]/100),0) -> 44047 | AE16: =_xlfn.IFNA(_xlfn.XLOOKUP(Table3[[#This Row],[Month]],Lookups!$N$2:$N$13,Lookups!$O$2:$O$13),"CHECK MONTH") -> 2 | AF16: =TEXT(Table3[[#This Row],[Month No]],"00")&" - "&Table3[[#This Row],[Month]] -> 02 - February | AG16: =_xlfn.IFNA(_xlfn.XLOOKUP(Table3[[#This Row],[Month]],Lookups!$N$2:$N$13,Lookups!$P$2:$P$13),"CHECK MONTH") -> Q1 | AH16: =Table3[[#This Row],[Gross Sales (EUR)]]-Table3[[#This Row],[Total Sales (EUR)]] -> 0 | AI16: =DATE(Lookups!$O$15,Table3[[#This Row],[Month No]],1) -> 45689
A17: 16 | B17: Fang | C17: Liu | D17: =TRIM(Table3[[#This Row],[Rep Last Name]])&", "&TRIM(Table3[[#This Row],[Rep First Name]]) -> Liu, Fang | E17: February | F17: Electric Unicycle | G17: 15 mph | H17: =IF(Table3[[#This Row],[Min Speed (original, incomplete)]]="",_xlfn.IFNA(_xlfn.XLOOKUP(Table3[[#This Row],[Product Type]],Lookups!$G$2:$G$4,Lookups!$H$2:$H$4),"CHECK PRODUCT"),Table3[[#This Row],[Min Speed (original, incomplete)]]) -> 15 mph | I17: 30 mph | J17: 48,280 meters | K17: =ROUND(VALUE(SUBSTITUTE(Table3[[#This Row],[Min Speed (mph)]]," mph",""))*Lookups!$L$2,0) -> 24 | L17: =ROUND(VALUE(SUBSTITUTE(Table3[[#This Row],[Speed]]," mph",""))*Lookups!$L$2,0) -> 48 | M17: =Table3[[#This Row],[Min Speed (km/h)]]&" – "&Table3[[#This Row],[Max Speed (km/h)]]&" km/h" -> 24 – 48 km/h | N17: =IF(ISNUMBER(SEARCH("mile",Table3[[#This Row],[Distance]])),ROUND(VALUE(SUBSTITUTE(Table3[[#This Row],[Distance]]," miles",""))*Lookups!$L$3,0),ROUND(VALUE(SUBSTITUTE(Table3[[#This Row],[Distance]]," meters",""))*Lookups!$L$4,0)) -> 48 | O17: 99 Nanjing Road, Shanghai, 200001 | P17: =TRIM(LEFT(Table3[[#This Row],[Shipping Address]],FIND(",",Table3[[#This Row],[Shipping Address]])-1)) -> 99 Nanjing Road | Q17: =TRIM(MID(Table3[[#This Row],[Shipping Address]],FIND(",",Table3[[#This Row],[Shipping Address]])+1,FIND(",",Table3[[#This Row],[Shipping Address]],FIND(",",Table3[[#This Row],[Shipping Address]])+1)-FIND(",",Table3[[#This Row],[Shipping Address]])-1)) -> Shanghai | R17: =TRIM(MID(Table3[[#This Row],[Shipping Address]],FIND(",",Table3[[#This Row],[Shipping Address]],FIND(",",Table3[[#This Row],[Shipping Address]])+1)+1,20)) -> 200001 | S17: CN | T17: =_xlfn.IFNA(_xlfn.XLOOKUP(Table3[[#This Row],[Country Code]],Lookups!$A$2:$A$5,Lookups!$B$2:$B$5),"CHECK CODE") -> China | U17: =_xlfn.IFNA(_xlfn.XLOOKUP(Table3[[#This Row],[Country Code]],Lookups!$A$2:$A$5,Lookups!$C$2:$C$5),"CHECK CODE") -> Asia | V17: ¥5,000 | W17: =_xlfn.IFNA(_xlfn.XLOOKUP(Table3[[#This Row],[Country Code]],Lookups!$A$2:$A$5,Lookups!$D$2:$D$5),"CHECK CODE") -> CNY | X17: =VALUE(MID(Table3[[#This Row],[Unit Price]],2,50)) -> 5000 | Y17: =_xlfn.IFNA(_xlfn.XLOOKUP(Table3[[#This Row],[Country Code]],Lookups!$A$2:$A$5,Lookups!$E$2:$E$5),"") -> 7.7255 | Z17: =Table3[[#This Row],[Unit Price (local)]]/Table3[[#This Row],[FX Rate (per EUR)]] -> 647.2073 | AA17: 550 | AB17: 0 | AC17: =ROUND(Table3[[#This Row],[Unit Price (EUR)]]*Table3[[#This Row],[Units Sold]],0) -> 355964 | AD17: =ROUND(Table3[[#This Row],[Gross Sales (EUR)]]*(1-Table3[[#This Row],[Discount (%)]]/100),0) -> 355964 | AE17: =_xlfn.IFNA(_xlfn.XLOOKUP(Table3[[#This Row],[Month]],Lookups!$N$2:$N$13,Lookups!$O$2:$O$13),"CHECK MONTH") -> 2 | AF17: =TEXT(Table3[[#This Row],[Month No]],"00")&" - "&Table3[[#This Row],[Month]] -> 02 - February | AG17: =_xlfn.IFNA(_xlfn.XLOOKUP(Table3[[#This Row],[Month]],Lookups!$N$2:$N$13,Lookups!$P$2:$P$13),"CHECK MONTH") -> Q1 | AH17: =Table3[[#This Row],[Gross Sales (EUR)]]-Table3[[#This Row],[Total Sales (EUR)]] -> 0 | AI17: =DATE(Lookups!$O$15,Table3[[#This Row],[Month No]],1) -> 45689
A18: 17 | B18: Fang | C18: Liu | D18: =TRIM(Table3[[#This Row],[Rep Last Name]])&", "&TRIM(Table3[[#This Row],[Rep First Name]]) -> Liu, Fang | E18: February | F18: Electric Scooter | G18: 20 mph | H18: =IF(Table3[[#This Row],[Min Speed (original, incomplete)]]="",_xlfn.IFNA(_xlfn.XLOOKUP(Table3[[#This Row],[Product Type]],Lookups!$G$2:$G$4,Lookups!$H$2:$H$4),"CHECK PRODUCT"),Table3[[#This Row],[Min Speed (original, incomplete)]]) -> 20 mph | I18: 35 mph | J18: 40 miles | K18: =ROUND(VALUE(SUBSTITUTE(Table3[[#This Row],[Min Speed (mph)]]," mph",""))*Lookups!$L$2,0) -> 32 | L18: =ROUND(VALUE(SUBSTITUTE(Table3[[#This Row],[Speed]]," mph",""))*Lookups!$L$2,0) -> 56 | M18: =Table3[[#This Row],[Min Speed (km/h)]]&" – "&Table3[[#This Row],[Max Speed (km/h)]]&" km/h" -> 32 – 56 km/h | N18: =IF(ISNUMBER(SEARCH("mile",Table3[[#This Row],[Distance]])),ROUND(VALUE(SUBSTITUTE(Table3[[#This Row],[Distance]]," miles",""))*Lookups!$L$3,0),ROUND(VALUE(SUBSTITUTE(Table3[[#This Row],[Distance]]," meters",""))*Lookups!$L$4,0)) -> 64 | O18: 100 Nanjing Road, Shanghai, 200001 | P18: =TRIM(LEFT(Table3[[#This Row],[Shipping Address]],FIND(",",Table3[[#This Row],[Shipping Address]])-1)) -> 100 Nanjing Road | Q18: =TRIM(MID(Table3[[#This Row],[Shipping Address]],FIND(",",Table3[[#This Row],[Shipping Address]])+1,FIND(",",Table3[[#This Row],[Shipping Address]],FIND(",",Table3[[#This Row],[Shipping Address]])+1)-FIND(",",Table3[[#This Row],[Shipping Address]])-1)) -> Shanghai | R18: =TRIM(MID(Table3[[#This Row],[Shipping Address]],FIND(",",Table3[[#This Row],[Shipping Address]],FIND(",",Table3[[#This Row],[Shipping Address]])+1)+1,20)) -> 200001 | S18: CN | T18: =_xlfn.IFNA(_xlfn.XLOOKUP(Table3[[#This Row],[Country Code]],Lookups!$A$2:$A$5,Lookups!$B$2:$B$5),"CHECK CODE") -> China | U18: =_xlfn.IFNA(_xlfn.XLOOKUP(Table3[[#This Row],[Country Code]],Lookups!$A$2:$A$5,Lookups!$C$2:$C$5),"CHECK CODE") -> Asia | V18: ¥3,500 | W18: =_xlfn.IFNA(_xlfn.XLOOKUP(Table3[[#This Row],[Country Code]],Lookups!$A$2:$A$5,Lookups!$D$2:$D$5),"CHECK CODE") -> CNY | X18: =VALUE(MID(Table3[[#This Row],[Unit Price]],2,50)) -> 3500 | Y18: =_xlfn.IFNA(_xlfn.XLOOKUP(Table3[[#This Row],[Country Code]],Lookups!$A$2:$A$5,Lookups!$E$2:$E$5),"") -> 7.7255 | Z18: =Table3[[#This Row],[Unit Price (local)]]/Table3[[#This Row],[FX Rate (per EUR)]] -> 453.04511 | AA18: 1200 | AB18: 0 | AC18: =ROUND(Table3[[#This Row],[Unit Price (EUR)]]*Table3[[#This Row],[Units Sold]],0) -> 543654 | AD18: =ROUND(Table3[[#This Row],[Gross Sales (EUR)]]*(1-Table3[[#This Row],[Discount (%)]]/100),0) -> 543654 | AE18: =_xlfn.IFNA(_xlfn.XLOOKUP(Table3[[#This Row],[Month]],Lookups!$N$2:$N$13,Lookups!$O$2:$O$13),"CHECK MONTH") -> 2 | AF18: =TEXT(Table3[[#This Row],[Month No]],"00")&" - "&Table3[[#This Row],[Month]] -> 02 - February | AG18: =_xlfn.IFNA(_xlfn.XLOOKUP(Table3[[#This Row],[Month]],Lookups!$N$2:$N$13,Lookups!$P$2:$P$13),"CHECK MONTH") -> Q1 | AH18: =Table3[[#This Row],[Gross Sales (EUR)]]-Table3[[#This Row],[Total Sales (EUR)]] -> 0 | AI18: =DATE(Lookups!$O$15,Table3[[#This Row],[Month No]],1) -> 45689
A19: 18 | B19: Fang | C19: Liu | D19: =TRIM(Table3[[#This Row],[Rep Last Name]])&", "&TRIM(Table3[[#This Row],[Rep First Name]]) -> Liu, Fang | E19: February | F19: Electric Skateboard | G19: 18 mph | H19: =IF(Table3[[#This Row],[Min Speed (original, incomplete)]]="",_xlfn.IFNA(_xlfn.XLOOKUP(Table3[[#This Row],[Product Type]],Lookups!$G$2:$G$4,Lookups!$H$2:$H$4),"CHECK PRODUCT"),Table3[[#This Row],[Min Speed (original, incomplete)]]) -> 18 mph | I19: 28 mph | J19: 25 miles | K19: =ROUND(VALUE(SUBSTITUTE(Table3[[#This Row],[Min Speed (mph)]]," mph",""))*Lookups!$L$2,0) -> 29 | L19: =ROUND(VALUE(SUBSTITUTE(Table3[[#This Row],[Speed]]," mph",""))*Lookups!$L$2,0) -> 45 | M19: =Table3[[#This Row],[Min Speed (km/h)]]&" – "&Table3[[#This Row],[Max Speed (km/h)]]&" km/h" -> 29 – 45 km/h | N19: =IF(ISNUMBER(SEARCH("mile",Table3[[#This Row],[Distance]])),ROUND(VALUE(SUBSTITUTE(Table3[[#This Row],[Distance]]," miles",""))*Lookups!$L$3,0),ROUND(VALUE(SUBSTITUTE(Table3[[#This Row],[Distance]]," meters",""))*Lookups!$L$4,0)) -> 40 | O19: 101 Nanjing Road, Shanghai, 200001 | P19: =TRIM(LEFT(Table3[[#This Row],[Shipping Address]],FIND(",",Table3[[#This Row],[Shipping Address]])-1)) -> 101 Nanjing Road | Q19: =TRIM(MID(Table3[[#This Row],[Shipping Address]],FIND(",",Table3[[#This Row],[Shipping Address]])+1,FIND(",",Table3[[#This Row],[Shipping Address]],FIND(",",Table3[[#This Row],[Shipping Address]])+1)-FIND(",",Table3[[#This Row],[Shipping Address]])-1)) -> Shanghai | R19: =TRIM(MID(Table3[[#This Row],[Shipping Address]],FIND(",",Table3[[#This Row],[Shipping Address]],FIND(",",Table3[[#This Row],[Shipping Address]])+1)+1,20)) -> 200001 | S19: CN | T19: =_xlfn.IFNA(_xlfn.XLOOKUP(Table3[[#This Row],[Country Code]],Lookups!$A$2:$A$5,Lookups!$B$2:$B$5),"CHECK CODE") -> China | U19: =_xlfn.IFNA(_xlfn.XLOOKUP(Table3[[#This Row],[Country Code]],Lookups!$A$2:$A$5,Lookups!$C$2:$C$5),"CHECK CODE") -> Asia | V19: ¥4,200 | W19: =_xlfn.IFNA(_xlfn.XLOOKUP(Table3[[#This Row],[Country Code]],Lookups!$A$2:$A$5,Lookups!$D$2:$D$5),"CHECK CODE") -> CNY | X19: =VALUE(MID(Table3[[#This Row],[Unit Price]],2,50)) -> 4200 | Y19: =_xlfn.IFNA(_xlfn.XLOOKUP(Table3[[#This Row],[Country Code]],Lookups!$A$2:$A$5,Lookups!$E$2:$E$5),"") -> 7.7255 | Z19: =Table3[[#This Row],[Unit Price (local)]]/Table3[[#This Row],[FX Rate (per EUR)]] -> 543.65413 | AA19: 850 | AB19: 0 | AC19: =ROUND(Table3[[#This Row],[Unit Price (EUR)]]*Table3[[#This Row],[Units Sold]],0) -> 462106 | AD19: =ROUND(Table3[[#This Row],[Gross Sales (EUR)]]*(1-Table3[[#This Row],[Discount (%)]]/100),0) -> 462106 | AE19: =_xlfn.IFNA(_xlfn.XLOOKUP(Table3[[#This Row],[Month]],Lookups!$N$2:$N$13,Lookups!$O$2:$O$13),"CHECK MONTH") -> 2 | AF19: =TEXT(Table3[[#This Row],[Month No]],"00")&" - "&Table3[[#This Row],[Month]] -> 02 - February | AG19: =_xlfn.IFNA(_xlfn.XLOOKUP(Table3[[#This Row],[Month]],Lookups!$N$2:$N$13,Lookups!$P$2:$P$13),"CHECK MONTH") -> Q1 | AH19: =Table3[[#This Row],[Gross Sales (EUR)]]-Table3[[#This Row],[Total Sales (EUR)]] -> 0 | AI19: =DATE(Lookups!$O$15,Table3[[#This Row],[Month No]],1) -> 45689
A20: 19 | B20: Jonas | C20: Fischer | D20: =TRIM(Table3[[#This Row],[Rep Last Name]])&", "&TRIM(Table3[[#This Row],[Rep First Name]]) -> Fischer, Jonas | E20: February | F20: Electric Unicycle | G20: 15 mph | H20: =IF(Table3[[#This Row],[Min Speed (original, incomplete)]]="",_xlfn.IFNA(_xlfn.XLOOKUP(Table3[[#This Row],[Product Type]],Lookups!$G$2:$G$4,Lookups!$H$2:$H$4),"CHECK PRODUCT"),Table3[[#This Row],[Min Speed (original, incomplete)]]) -> 15 mph | I20: 30 mph | J20: 30 miles | K20: =ROUND(VALUE(SUBSTITUTE(Table3[[#This Row],[Min Speed (mph)]]," mph",""))*Lookups!$L$2,0) -> 24 | L20: =ROUND(VALUE(SUBSTITUTE(Table3[[#This Row],[Speed]]," mph",""))*Lookups!$L$2,0) -> 48 | M20: =Table3[[#This Row],[Min Speed (km/h)]]&" – "&Table3[[#This Row],[Max Speed (km/h)]]&" km/h" -> 24 – 48 km/h | N20: =IF(ISNUMBER(SEARCH("mile",Table3[[#This Row],[Distance]])),ROUND(VALUE(SUBSTITUTE(Table3[[#This Row],[Distance]]," miles",""))*Lookups!$L$3,0),ROUND(VALUE(SUBSTITUTE(Table3[[#This Row],[Distance]]," meters",""))*Lookups!$L$4,0)) -> 48 | O20: 303 Ringstraße, Hamburg, 20095 | P20: =TRIM(LEFT(Table3[[#This Row],[Shipping Address]],FIND(",",Table3[[#This Row],[Shipping Address]])-1)) -> 303 Ringstraße | Q20: =TRIM(MID(Table3[[#This Row],[Shipping Address]],FIND(",",Table3[[#This Row],[Shipping Address]])+1,FIND(",",Table3[[#This Row],[Shipping Address]],FIND(",",Table3[[#This Row],[Shipping Address]])+1)-FIND(",",Table3[[#This Row],[Shipping Address]])-1)) -> Hamburg | R20: =TRIM(MID(Table3[[#This Row],[Shipping Address]],FIND(",",Table3[[#This Row],[Shipping Address]],FIND(",",Table3[[#This Row],[Shipping Address]])+1)+1,20)) -> 20095 | S20: DE | T20: =_xlfn.IFNA(_xlfn.XLOOKUP(Table3[[#This Row],[Country Code]],Lookups!$A$2:$A$5,Lookups!$B$2:$B$5),"CHECK CODE") -> Germany | U20: =_xlfn.IFNA(_xlfn.XLOOKUP(Table3[[#This Row],[Country Code]],Lookups!$A$2:$A$5,Lookups!$C$2:$C$5),"CHECK CODE") -> Europe | V20: €1000 | W20: =_xlfn.IFNA(_xlfn.XLOOKUP(Table3[[#This Row],[Country Code]],Lookups!$A$2:$A$5,Lookups!$D$2:$D$5),"CHECK CODE") -> EUR | X20: =VALUE(MID(Table3[[#This Row],[Unit Price]],2,50)) -> 1000 | Y20: =_xlfn.IFNA(_xlfn.XLOOKUP(Table3[[#This Row],[Country Code]],Lookups!$A$2:$A$5,Lookups!$E$2:$E$5),"") -> 1 | Z20: =Table3[[#This Row],[Unit Price (local)]]/Table3[[#This Row],[FX Rate (per EUR)]] -> 1000 | AA20: 130 | AB20: 0 | AC20: =ROUND(Table3[[#This Row],[Unit Price (EUR)]]*Table3[[#This Row],[Units Sold]],0) -> 130000 | AD20: =ROUND(Table3[[#This Row],[Gross Sales (EUR)]]*(1-Table3[[#This Row],[Discount (%)]]/100),0) -> 130000 | AE20: =_xlfn.IFNA(_xlfn.XLOOKUP(Table3[[#This Row],[Month]],Lookups!$N$2:$N$13,Lookups!$O$2:$O$13),"CHECK MONTH") -> 2 | AF20: =TEXT(Table3[[#This Row],[Month No]],"00")&" - "&Table3[[#This Row],[Month]] -> 02 - February | AG20: =_xlfn.IFNA(_xlfn.XLOOKUP(Table3[[#This Row],[Month]],Lookups!$N$2:$N$13,Lookups!$P$2:$P$13),"CHECK MONTH") -> Q1 | AH20: =Table3[[#This Row],[Gross Sales (EUR)]]-Table3[[#This Row],[Total Sales (EUR)]] -> 0 | AI20: =DATE(Lookups!$O$15,Table3[[#This Row],[Month No]],1) -> 45689
A21: 20 | B21: Jonas | C21: Fischer | D21: =TRIM(Table3[[#This Row],[Rep Last Name]])&", "&TRIM(Table3[[#This Row],[Rep First Name]]) -> Fischer, Jonas | E21: February | F21: Electric Scooter | G21: 20 mph | H21: =IF(Table3[[#This Row],[Min Speed (original, incomplete)]]="",_xlfn.IFNA(_xlfn.XLOOKUP(Table3[[#This Row],[Product Type]],Lookups!$G$2:$G$4,Lookups!$H$2:$H$4),"CHECK PRODUCT"),Table3[[#This Row],[Min Speed (original, incomplete)]]) -> 20 mph | I21: 35 mph | J21: 40 miles | K21: =ROUND(VALUE(SUBSTITUTE(Table3[[#This Row],[Min Speed (mph)]]," mph",""))*Lookups!$L$2,0) -> 32 | L21: =ROUND(VALUE(SUBSTITUTE(Table3[[#This Row],[Speed]]," mph",""))*Lookups!$L$2,0) -> 56 | M21: =Table3[[#This Row],[Min Speed (km/h)]]&" – "&Table3[[#This Row],[Max Speed (km/h)]]&" km/h" -> 32 – 56 km/h | N21: =IF(ISNUMBER(SEARCH("mile",Table3[[#This Row],[Distance]])),ROUND(VALUE(SUBSTITUTE(Table3[[#This Row],[Distance]]," miles",""))*Lookups!$L$3,0),ROUND(VALUE(SUBSTITUTE(Table3[[#This Row],[Distance]]," meters",""))*Lookups!$L$4,0)) -> 64 | O21: 304 Ringstraße, Hamburg, 20095 | P21: =TRIM(LEFT(Table3[[#This Row],[Shipping Address]],FIND(",",Table3[[#This Row],[Shipping Address]])-1)) -> 304 Ringstraße | Q21: =TRIM(MID(Table3[[#This Row],[Shipping Address]],FIND(",",Table3[[#This Row],[Shipping Address]])+1,FIND(",",Table3[[#This Row],[Shipping Address]],FIND(",",Table3[[#This Row],[Shipping Address]])+1)-FIND(",",Table3[[#This Row],[Shipping Address]])-1)) -> Hamburg | R21: =TRIM(MID(Table3[[#This Row],[Shipping Address]],FIND(",",Table3[[#This Row],[Shipping Address]],FIND(",",Table3[[#This Row],[Shipping Address]])+1)+1,20)) -> 20095 | S21: DE | T21: =_xlfn.IFNA(_xlfn.XLOOKUP(Table3[[#This Row],[Country Code]],Lookups!$A$2:$A$5,Lookups!$B$2:$B$5),"CHECK CODE") -> Germany | U21: =_xlfn.IFNA(_xlfn.XLOOKUP(Table3[[#This Row],[Country Code]],Lookups!$A$2:$A$5,Lookups!$C$2:$C$5),"CHECK CODE") -> Europe | V21: €800 | W21: =_xlfn.IFNA(_xlfn.XLOOKUP(Table3[[#This Row],[Country Code]],Lookups!$A$2:$A$5,Lookups!$D$2:$D$5),"CHECK CODE") -> EUR | X21: =VALUE(MID(Table3[[#This Row],[Unit Price]],2,50)) -> 800 | Y21: =_xlfn.IFNA(_xlfn.XLOOKUP(Table3[[#This Row],[Country Code]],Lookups!$A$2:$A$5,Lookups!$E$2:$E$5),"") -> 1 | Z21: =Table3[[#This Row],[Unit Price (local)]]/Table3[[#This Row],[FX Rate (per EUR)]] -> 800 | AA21: 220 | AB21: 0 | AC21: =ROUND(Table3[[#This Row],[Unit Price (EUR)]]*Table3[[#This Row],[Units Sold]],0) -> 176000 | AD21: =ROUND(Table3[[#This Row],[Gross Sales (EUR)]]*(1-Table3[[#This Row],[Discount (%)]]/100),0) -> 176000 | AE21: =_xlfn.IFNA(_xlfn.XLOOKUP(Table3[[#This Row],[Month]],Lookups!$N$2:$N$13,Lookups!$O$2:$O$13),"CHECK MONTH") -> 2 | AF21: =TEXT(Table3[[#This Row],[Month No]],"00")&" - "&Table3[[#This Row],[Month]] -> 02 - February | AG21: =_xlfn.IFNA(_xlfn.XLOOKUP(Table3[[#This Row],[Month]],Lookups!$N$2:$N$13,Lookups!$P$2:$P$13),"CHECK MONTH") -> Q1 | AH21: =Table3[[#This Row],[Gross Sales (EUR)]]-Table3[[#This Row],[Total Sales (EUR)]] -> 0 | AI21: =DATE(Lookups!$O$15,Table3[[#This Row],[Month No]],1) -> 45689
A22: 21 | B22: Jonas | C22: Fischer | D22: =TRIM(Table3[[#This Row],[Rep Last Name]])&", "&TRIM(Table3[[#This Row],[Rep First Name]]) -> Fischer, Jonas | E22: February | F22: Electric Skateboard | G22: 18 mph | H22: =IF(Table3[[#This Row],[Min Speed (original, incomplete)]]="",_xlfn.IFNA(_xlfn.XLOOKUP(Table3[[#This Row],[Product Type]],Lookups!$G$2:$G$4,Lookups!$H$2:$H$4),"CHECK PRODUCT"),Table3[[#This Row],[Min Speed (original, incomplete)]]) -> 18 mph | I22: 28 mph | J22: 25 miles | K22: =ROUND(VALUE(SUBSTITUTE(Table3[[#This Row],[Min Speed (mph)]]," mph",""))*Lookups!$L$2,0) -> 29 | L22: =ROUND(VALUE(SUBSTITUTE(Table3[[#This Row],[Speed]]," mph",""))*Lookups!$L$2,0) -> 45 | M22: =Table3[[#This Row],[Min Speed (km/h)]]&" – "&Table3[[#This Row],[Max Speed (km/h)]]&" km/h" -> 29 – 45 km/h | N22: =IF(ISNUMBER(SEARCH("mile",Table3[[#This Row],[Distance]])),ROUND(VALUE(SUBSTITUTE(Table3[[#This Row],[Distance]]," miles",""))*Lookups!$L$3,0),ROUND(VALUE(SUBSTITUTE(Table3[[#This Row],[Distance]]," meters",""))*Lookups!$L$4,0)) -> 40 | O22: 305 Ringstraße, Hamburg, 20095 | P22: =TRIM(LEFT(Table3[[#This Row],[Shipping Address]],FIND(",",Table3[[#This Row],[Shipping Address]])-1)) -> 305 Ringstraße | Q22: =TRIM(MID(Table3[[#This Row],[Shipping Address]],FIND(",",Table3[[#This Row],[Shipping Address]])+1,FIND(",",Table3[[#This Row],[Shipping Address]],FIND(",",Table3[[#This Row],[Shipping Address]])+1)-FIND(",",Table3[[#This Row],[Shipping Address]])-1)) -> Hamburg | R22: =TRIM(MID(Table3[[#This Row],[Shipping Address]],FIND(",",Table3[[#This Row],[Shipping Address]],FIND(",",Table3[[#This Row],[Shipping Address]])+1)+1,20)) -> 20095 | S22: DE | T22: =_xlfn.IFNA(_xlfn.XLOOKUP(Table3[[#This Row],[Country Code]],Lookups!$A$2:$A$5,Lookups!$B$2:$B$5),"CHECK CODE") -> Germany | U22: =_xlfn.IFNA(_xlfn.XLOOKUP(Table3[[#This Row],[Country Code]],Lookups!$A$2:$A$5,Lookups!$C$2:$C$5),"CHECK CODE") -> Europe | V22: €950 | W22: =_xlfn.IFNA(_xlfn.XLOOKUP(Table3[[#This Row],[Country Code]],Lookups!$A$2:$A$5,Lookups!$D$2:$D$5),"CHECK CODE") -> EUR | X22: =VALUE(MID(Table3[[#This Row],[Unit Price]],2,50)) -> 950 | Y22: =_xlfn.IFNA(_xlfn.XLOOKUP(Table3[[#This Row],[Country Code]],Lookups!$A$2:$A$5,Lookups!$E$2:$E$5),"") -> 1 | Z22: =Table3[[#This Row],[Unit Price (local)]]/Table3[[#This Row],[FX Rate (per EUR)]] -> 950 | AA22: 160 | AB22: 0 | AC22: =ROUND(Table3[[#This Row],[Unit Price (EUR)]]*Table3[[#This Row],[Units Sold]],0) -> 152000 | AD22: =ROUND(Table3[[#This Row],[Gross Sales (EUR)]]*(1-Table3[[#This Row],[Discount (%)]]/100),0) -> 152000 | AE22: =_xlfn.IFNA(_xlfn.XLOOKUP(Table3[[#This Row],[Month]],Lookups!$N$2:$N$13,Lookups!$O$2:$O$13),"CHECK MONTH") -> 2 | AF22: =TEXT(Table3[[#This Row],[Month No]],"00")&" - "&Table3[[#This Row],[Month]] -> 02 - February | AG22: =_xlfn.IFNA(_xlfn.XLOOKUP(Table3[[#This Row],[Month]],Lookups!$N$2:$N$13,Lookups!$P$2:$P$13),"CHECK MONTH") -> Q1 | AH22: =Table3[[#This Row],[Gross Sales (EUR)]]-Table3[[#This Row],[Total Sales (EUR)]] -> 0 | AI22: =DATE(Lookups!$O$15,Table3[[#This Row],[Month No]],1) -> 45689
A23: 22 | B23: Théo | C23: Bernard | D23: =TRIM(Table3[[#This Row],[Rep Last Name]])&", "&TRIM(Table3[[#This Row],[Rep First Name]]) -> Bernard, Théo | E23: February | F23: Electric Unicycle | G23: 15 mph | H23: =IF(Table3[[#This Row],[Min Speed (original, incomplete)]]="",_xlfn.IFNA(_xlfn.XLOOKUP(Table3[[#This Row],[Product Type]],Lookups!$G$2:$G$4,Lookups!$H$2:$H$4),"CHECK PRODUCT"),Table3[[#This Row],[Min Speed (original, incomplete)]]) -> 15 mph | I23: 30 mph | J23: 30 miles | K23: =ROUND(VALUE(SUBSTITUTE(Table3[[#This Row],[Min Speed (mph)]]," mph",""))*Lookups!$L$2,0) -> 24 | L23: =ROUND(VALUE(SUBSTITUTE(Table3[[#This Row],[Speed]]," mph",""))*Lookups!$L$2,0) -> 48 | M23: =Table3[[#This Row],[Min Speed (km/h)]]&" – "&Table3[[#This Row],[Max Speed (km/h)]]&" km/h" -> 24 – 48 km/h | N23: =IF(ISNUMBER(SEARCH("mile",Table3[[#This Row],[Distance]])),ROUND(VALUE(SUBSTITUTE(Table3[[#This Row],[Distance]]," miles",""))*Lookups!$L$3,0),ROUND(VALUE(SUBSTITUTE(Table3[[#This Row],[Distance]]," meters",""))*Lookups!$L$4,0)) -> 48 | O23: 56 Boulevard Saint-Germain, Paris, 75005 | P23: =TRIM(LEFT(Table3[[#This Row],[Shipping Address]],FIND(",",Table3[[#This Row],[Shipping Address]])-1)) -> 56 Boulevard Saint-Germain | Q23: =TRIM(MID(Table3[[#This Row],[Shipping Address]],FIND(",",Table3[[#This Row],[Shipping Address]])+1,FIND(",",Table3[[#This Row],[Shipping Address]],FIND(",",Table3[[#This Row],[Shipping Address]])+1)-FIND(",",Table3[[#This Row],[Shipping Address]])-1)) -> Paris | R23: =TRIM(MID(Table3[[#This Row],[Shipping Address]],FIND(",",Table3[[#This Row],[Shipping Address]],FIND(",",Table3[[#This Row],[Shipping Address]])+1)+1,20)) -> 75005 | S23: FR | T23: =_xlfn.IFNA(_xlfn.XLOOKUP(Table3[[#This Row],[Country Code]],Lookups!$A$2:$A$5,Lookups!$B$2:$B$5),"CHECK CODE") -> France | U23: =_xlfn.IFNA(_xlfn.XLOOKUP(Table3[[#This Row],[Country Code]],Lookups!$A$2:$A$5,Lookups!$C$2:$C$5),"CHECK CODE") -> Europe | V23: €1100 | W23: =_xlfn.IFNA(_xlfn.XLOOKUP(Table3[[#This Row],[Country Code]],Lookups!$A$2:$A$5,Lookups!$D$2:$D$5),"CHECK CODE") -> EUR | X23: =VALUE(MID(Table3[[#This Row],[Unit Price]],2,50)) -> 1100 | Y23: =_xlfn.IFNA(_xlfn.XLOOKUP(Table3[[#This Row],[Country Code]],Lookups!$A$2:$A$5,Lookups!$E$2:$E$5),"") -> 1 | Z23: =Table3[[#This Row],[Unit Price (local)]]/Table3[[#This Row],[FX Rate (per EUR)]] -> 1100 | AA23: 110 | AB23: 0 | AC23: =ROUND(Table3[[#This Row],[Unit Price (EUR)]]*Table3[[#This Row],[Units Sold]],0) -> 121000 | AD23: =ROUND(Table3[[#This Row],[Gross Sales (EUR)]]*(1-Table3[[#This Row],[Discount (%)]]/100),0) -> 121000 | AE23: =_xlfn.IFNA(_xlfn.XLOOKUP(Table3[[#This Row],[Month]],Lookups!$N$2:$N$13,Lookups!$O$2:$O$13),"CHECK MONTH") -> 2 | AF23: =TEXT(Table3[[#This Row],[Month No]],"00")&" - "&Table3[[#This Row],[Month]] -> 02 - February | AG23: =_xlfn.IFNA(_xlfn.XLOOKUP(Table3[[#This Row],[Month]],Lookups!$N$2:$N$13,Lookups!$P$2:$P$13),"CHECK MONTH") -> Q1 | AH23: =Table3[[#This Row],[Gross Sales (EUR)]]-Table3[[#This Row],[Total Sales (EUR)]] -> 0 | AI23: =DATE(Lookups!$O$15,Table3[[#This Row],[Month No]],1) -> 45689
A24: 23 | B24: Théo | C24: Bernard | D24: =TRIM(Table3[[#This Row],[Rep Last Name]])&", "&TRIM(Table3[[#This Row],[Rep First Name]]) -> Bernard, Théo | E24: February | F24: Electric Scooter | G24: 20 mph | H24: =IF(Table3[[#This Row],[Min Speed (original, incomplete)]]="",_xlfn.IFNA(_xlfn.XLOOKUP(Table3[[#This Row],[Product Type]],Lookups!$G$2:$G$4,Lookups!$H$2:$H$4),"CHECK PRODUCT"),Table3[[#This Row],[Min Speed (original, incomplete)]]) -> 20 mph | I24: 35 mph | J24: 40 miles | K24: =ROUND(VALUE(SUBSTITUTE(Table3[[#This Row],[Min Speed (mph)]]," mph",""))*Lookups!$L$2,0) -> 32 | L24: =ROUND(VALUE(SUBSTITUTE(Table3[[#This Row],[Speed]]," mph",""))*Lookups!$L$2,0) -> 56 | M24: =Table3[[#This Row],[Min Speed (km/h)]]&" – "&Table3[[#This Row],[Max Speed (km/h)]]&" km/h" -> 32 – 56 km/h | N24: =IF(ISNUMBER(SEARCH("mile",Table3[[#This Row],[Distance]])),ROUND(VALUE(SUBSTITUTE(Table3[[#This Row],[Distance]]," miles",""))*Lookups!$L$3,0),ROUND(VALUE(SUBSTITUTE(Table3[[#This Row],[Distance]]," meters",""))*Lookups!$L$4,0)) -> 64 | O24: 57 Boulevard Saint-Germain, Paris, 75005 | P24: =TRIM(LEFT(Table3[[#This Row],[Shipping Address]],FIND(",",Table3[[#This Row],[Shipping Address]])-1)) -> 57 Boulevard Saint-Germain | Q24: =TRIM(MID(Table3[[#This Row],[Shipping Address]],FIND(",",Table3[[#This Row],[Shipping Address]])+1,FIND(",",Table3[[#This Row],[Shipping Address]],FIND(",",Table3[[#This Row],[Shipping Address]])+1)-FIND(",",Table3[[#This Row],[Shipping Address]])-1)) -> Paris | R24: =TRIM(MID(Table3[[#This Row],[Shipping Address]],FIND(",",Table3[[#This Row],[Shipping Address]],FIND(",",Table3[[#This Row],[Shipping Address]])+1)+1,20)) -> 75005 | S24: FR | T24: =_xlfn.IFNA(_xlfn.XLOOKUP(Table3[[#This Row],[Country Code]],Lookups!$A$2:$A$5,Lookups!$B$2:$B$5),"CHECK CODE") -> France | U24: =_xlfn.IFNA(_xlfn.XLOOKUP(Table3[[#This Row],[Country Code]],Lookups!$A$2:$A$5,Lookups!$C$2:$C$5),"CHECK CODE") -> Europe | V24: €900 | W24: =_xlfn.IFNA(_xlfn.XLOOKUP(Table3[[#This Row],[Country Code]],Lookups!$A$2:$A$5,Lookups!$D$2:$D$5),"CHECK CODE") -> EUR | X24: =VALUE(MID(Table3[[#This Row],[Unit Price]],2,50)) -> 900 | Y24: =_xlfn.IFNA(_xlfn.XLOOKUP(Table3[[#This Row],[Country Code]],Lookups!$A$2:$A$5,Lookups!$E$2:$E$5),"") -> 1 | Z24: =Table3[[#This Row],[Unit Price (local)]]/Table3[[#This Row],[FX Rate (per EUR)]] -> 900 | AA24: 260 | AB24: 0 | AC24: =ROUND(Table3[[#This Row],[Unit Price (EUR)]]*Table3[[#This Row],[Units Sold]],0) -> 234000 | AD24: =ROUND(Table3[[#This Row],[Gross Sales (EUR)]]*(1-Table3[[#This Row],[Discount (%)]]/100),0) -> 234000 | AE24: =_xlfn.IFNA(_xlfn.XLOOKUP(Table3[[#This Row],[Month]],Lookups!$N$2:$N$13,Lookups!$O$2:$O$13),"CHECK MONTH") -> 2 | AF24: =TEXT(Table3[[#This Row],[Month No]],"00")&" - "&Table3[[#This Row],[Month]] -> 02 - February | AG24: =_xlfn.IFNA(_xlfn.XLOOKUP(Table3[[#This Row],[Month]],Lookups!$N$2:$N$13,Lookups!$P$2:$P$13),"CHECK MONTH") -> Q1 | AH24: =Table3[[#This Row],[Gross Sales (EUR)]]-Table3[[#This Row],[Total Sales (EUR)]] -> 0 | AI24: =DATE(Lookups!$O$15,Table3[[#This Row],[Month No]],1) -> 45689
A25: 24 | B25: Théo | C25: Bernard | D25: =TRIM(Table3[[#This Row],[Rep Last Name]])&", "&TRIM(Table3[[#This Row],[Rep First Name]]) -> Bernard, Théo | E25: February | F25: Electric Skateboard | G25: 18 mph | H25: =IF(Table3[[#This Row],[Min Speed (original, incomplete)]]="",_xlfn.IFNA(_xlfn.XLOOKUP(Table3[[#This Row],[Product Type]],Lookups!$G$2:$G$4,Lookups!$H$2:$H$4),"CHECK PRODUCT"),Table3[[#This Row],[Min Speed (original, incomplete)]]) -> 18 mph | I25: 28 mph | J25: 40,230 meters | K25: =ROUND(VALUE(SUBSTITUTE(Table3[[#This Row],[Min Speed (mph)]]," mph",""))*Lookups!$L$2,0) -> 29 | L25: =ROUND(VALUE(SUBSTITUTE(Table3[[#This Row],[Speed]]," mph",""))*Lookups!$L$2,0) -> 45 | M25: =Table3[[#This Row],[Min Speed (km/h)]]&" – "&Table3[[#This Row],[Max Speed (km/h)]]&" km/h" -> 29 – 45 km/h | N25: =IF(ISNUMBER(SEARCH("mile",Table3[[#This Row],[Distance]])),ROUND(VALUE(SUBSTITUTE(Table3[[#This Row],[Distance]]," miles",""))*Lookups!$L$3,0),ROUND(VALUE(SUBSTITUTE(Table3[[#This Row],[Distance]]," meters",""))*Lookups!$L$4,0)) -> 40 | O25: 58 Boulevard Saint-Germain, Paris, 75005 | P25: =TRIM(LEFT(Table3[[#This Row],[Shipping Address]],FIND(",",Table3[[#This Row],[Shipping Address]])-1)) -> 58 Boulevard Saint-Germain | Q25: =TRIM(MID(Table3[[#This Row],[Shipping Address]],FIND(",",Table3[[#This Row],[Shipping Address]])+1,FIND(",",Table3[[#This Row],[Shipping Address]],FIND(",",Table3[[#This Row],[Shipping Address]])+1)-FIND(",",Table3[[#This Row],[Shipping Address]])-1)) -> Paris | R25: =TRIM(MID(Table3[[#This Row],[Shipping Address]],FIND(",",Table3[[#This Row],[Shipping Address]],FIND(",",Table3[[#This Row],[Shipping Address]])+1)+1,20)) -> 75005 | S25: FR | T25: =_xlfn.IFNA(_xlfn.XLOOKUP(Table3[[#This Row],[Country Code]],Lookups!$A$2:$A$5,Lookups!$B$2:$B$5),"CHECK CODE") -> France | U25: =_xlfn.IFNA(_xlfn.XLOOKUP(Table3[[#This Row],[Country Code]],Lookups!$A$2:$A$5,Lookups!$C$2:$C$5),"CHECK CODE") -> Europe | V25: €1050 | W25: =_xlfn.IFNA(_xlfn.XLOOKUP(Table3[[#This Row],[Country Code]],Lookups!$A$2:$A$5,Lookups!$D$2:$D$5),"CHECK CODE") -> EUR | X25: =VALUE(MID(Table3[[#This Row],[Unit Price]],2,50)) -> 1050 | Y25: =_xlfn.IFNA(_xlfn.XLOOKUP(Table3[[#This Row],[Country Code]],Lookups!$A$2:$A$5,Lookups!$E$2:$E$5),"") -> 1 | Z25: =Table3[[#This Row],[Unit Price (local)]]/Table3[[#This Row],[FX Rate (per EUR)]] -> 1050 | AA25: 200 | AB25: 0 | AC25: =ROUND(Table3[[#This Row],[Unit Price (EUR)]]*Table3[[#This Row],[Units Sold]],0) -> 210000 | AD25: =ROUND(Table3[[#This Row],[Gross Sales (EUR)]]*(1-Table3[[#This Row],[Discount (%)]]/100),0) -> 210000 | AE25: =_xlfn.IFNA(_xlfn.XLOOKUP(Table3[[#This Row],[Month]],Lookups!$N$2:$N$13,Lookups!$O$2:$O$13),"CHECK MONTH") -> 2 | AF25: =TEXT(Table3[[#This Row],[Month No]],"00")&" - "&Table3[[#This Row],[Month]] -> 02 - February | AG25: =_xlfn.IFNA(_xlfn.XLOOKUP(Table3[[#This Row],[Month]],Lookups!$N$2:$N$13,Lookups!$P$2:$P$13),"CHECK MONTH") -> Q1 | AH25: =Table3[[#This Row],[Gross Sales (EUR)]]-Table3[[#This Row],[Total Sales (EUR)]] -> 0 | AI25: =DATE(Lookups!$O$15,Table3[[#This Row],[Month No]],1) -> 45689
A26: 25 | B26: Sanya | C26: Joshi | D26: =TRIM(Table3[[#This Row],[Rep Last Name]])&", "&TRIM(Table3[[#This Row],[Rep First Name]]) -> Joshi, Sanya | E26: March | F26: Electric Unicycle | G26: 15 mph | H26: =IF(Table3[[#This Row],[Min Speed (original, incomplete)]]="",_xlfn.IFNA(_xlfn.XLOOKUP(Table3[[#This Row],[Product Type]],Lookups!$G$2:$G$4,Lookups!$H$2:$H$4),"CHECK PRODUCT"),Table3[[#This Row],[Min Speed (original, incomplete)]]) -> 15 mph | I26: 30 mph | J26: 30 miles | K26: =ROUND(VALUE(SUBSTITUTE(Table3[[#This Row],[Min Speed (mph)]]," mph",""))*Lookups!$L$2,0) -> 24 | L26: =ROUND(VALUE(SUBSTITUTE(Table3[[#This Row],[Speed]]," mph",""))*Lookups!$L$2,0) -> 48 | M26: =Table3[[#This Row],[Min Speed (km/h)]]&" – "&Table3[[#This Row],[Max Speed (km/h)]]&" km/h" -> 24 – 48 km/h | N26: =IF(ISNUMBER(SEARCH("mile",Table3[[#This Row],[Distance]])),ROUND(VALUE(SUBSTITUTE(Table3[[#This Row],[Distance]]," miles",""))*Lookups!$L$3,0),ROUND(VALUE(SUBSTITUTE(Table3[[#This Row],[Distance]]," meters",""))*Lookups!$L$4,0)) -> 48 | O26: 456 Brigade Road, Bengaluru, 560001 | P26: =TRIM(LEFT(Table3[[#This Row],[Shipping Address]],FIND(",",Table3[[#This Row],[Shipping Address]])-1)) -> 456 Brigade Road | Q26: =TRIM(MID(Table3[[#This Row],[Shipping Address]],FIND(",",Table3[[#This Row],[Shipping Address]])+1,FIND(",",Table3[[#This Row],[Shipping Address]],FIND(",",Table3[[#This Row],[Shipping Address]])+1)-FIND(",",Table3[[#This Row],[Shipping Address]])-1)) -> Bengaluru | R26: =TRIM(MID(Table3[[#This Row],[Shipping Address]],FIND(",",Table3[[#This Row],[Shipping Address]],FIND(",",Table3[[#This Row],[Shipping Address]])+1)+1,20)) -> 560001 | S26: IN | T26: =_xlfn.IFNA(_xlfn.XLOOKUP(Table3[[#This Row],[Country Code]],Lookups!$A$2:$A$5,Lookups!$B$2:$B$5),"CHECK CODE") -> India | U26: =_xlfn.IFNA(_xlfn.XLOOKUP(Table3[[#This Row],[Country Code]],Lookups!$A$2:$A$5,Lookups!$C$2:$C$5),"CHECK CODE") -> Asia | V26: ₹30,000 | W26: =_xlfn.IFNA(_xlfn.XLOOKUP(Table3[[#This Row],[Country Code]],Lookups!$A$2:$A$5,Lookups!$D$2:$D$5),"CHECK CODE") -> INR | X26: =VALUE(MID(Table3[[#This Row],[Unit Price]],2,50)) -> 30000 | Y26: =_xlfn.IFNA(_xlfn.XLOOKUP(Table3[[#This Row],[Country Code]],Lookups!$A$2:$A$5,Lookups!$E$2:$E$5),"") -> 109.882 | Z26: =Table3[[#This Row],[Unit Price (local)]]/Table3[[#This Row],[FX Rate (per EUR)]] -> 273.02015 | AA26: 160 | AB26: 0 | AC26: =ROUND(Table3[[#This Row],[Unit Price (EUR)]]*Table3[[#This Row],[Units Sold]],0) -> 43683 | AD26: =ROUND(Table3[[#This Row],[Gross Sales (EUR)]]*(1-Table3[[#This Row],[Discount (%)]]/100),0) -> 43683 | AE26: =_xlfn.IFNA(_xlfn.XLOOKUP(Table3[[#This Row],[Month]],Lookups!$N$2:$N$13,Lookups!$O$2:$O$13),"CHECK MONTH") -> 3 | AF26: =TEXT(Table3[[#This Row],[Month No]],"00")&" - "&Table3[[#This Row],[Month]] -> 03 - March | AG26: =_xlfn.IFNA(_xlfn.XLOOKUP(Table3[[#This Row],[Month]],Lookups!$N$2:$N$13,Lookups!$P$2:$P$13),"CHECK MONTH") -> Q1 | AH26: =Table3[[#This Row],[Gross Sales (EUR)]]-Table3[[#This Row],[Total Sales (EUR)]] -> 0 | AI26: =DATE(Lookups!$O$15,Table3[[#This Row],[Month No]],1) -> 45717
A27: 26 | B27: Sanya | C27: Joshi | D27: =TRIM(Table3[[#This Row],[Rep Last Name]])&", "&TRIM(Table3[[#This Row],[Rep First Name]]) -> Joshi, Sanya | E27: March | F27: Electric Scooter | H27: =IF(Table3[[#This Row],[Min Speed (original, incomplete)]]="",_xlfn.IFNA(_xlfn.XLOOKUP(Table3[[#This Row],[Product Type]],Lookups!$G$2:$G$4,Lookups!$H$2:$H$4),"CHECK PRODUCT"),Table3[[#This Row],[Min Speed (original, incomplete)]]) -> 20 mph | I27: 35 mph | J27: 40 miles | K27: =ROUND(VALUE(SUBSTITUTE(Table3[[#This Row],[Min Speed (mph)]]," mph",""))*Lookups!$L$2,0) -> 32 | L27: =ROUND(VALUE(SUBSTITUTE(Table3[[#This Row],[Speed]]," mph",""))*Lookups!$L$2,0) -> 56 | M27: =Table3[[#This Row],[Min Speed (km/h)]]&" – "&Table3[[#This Row],[Max Speed (km/h)]]&" km/h" -> 32 – 56 km/h | N27: =IF(ISNUMBER(SEARCH("mile",Table3[[#This Row],[Distance]])),ROUND(VALUE(SUBSTITUTE(Table3[[#This Row],[Distance]]," miles",""))*Lookups!$L$3,0),ROUND(VALUE(SUBSTITUTE(Table3[[#This Row],[Distance]]," meters",""))*Lookups!$L$4,0)) -> 64 | O27: 457 Brigade Road, Bengaluru, 560001 | P27: =TRIM(LEFT(Table3[[#This Row],[Shipping Address]],FIND(",",Table3[[#This Row],[Shipping Address]])-1)) -> 457 Brigade Road | Q27: =TRIM(MID(Table3[[#This Row],[Shipping Address]],FIND(",",Table3[[#This Row],[Shipping Address]])+1,FIND(",",Table3[[#This Row],[Shipping Address]],FIND(",",Table3[[#This Row],[Shipping Address]])+1)-FIND(",",Table3[[#This Row],[Shipping Address]])-1)) -> Bengaluru | R27: =TRIM(MID(Table3[[#This Row],[Shipping Address]],FIND(",",Table3[[#This Row],[Shipping Address]],FIND(",",Table3[[#This Row],[Shipping Address]])+1)+1,20)) -> 560001 | S27: IN | T27: =_xlfn.IFNA(_xlfn.XLOOKUP(Table3[[#This Row],[Country Code]],Lookups!$A$2:$A$5,Lookups!$B$2:$B$5),"CHECK CODE") -> India | U27: =_xlfn.IFNA(_xlfn.XLOOKUP(Table3[[#This Row],[Country Code]],Lookups!$A$2:$A$5,Lookups!$C$2:$C$5),"CHECK CODE") -> Asia | V27: ₹25,000 | W27: =_xlfn.IFNA(_xlfn.XLOOKUP(Table3[[#This Row],[Country Code]],Lookups!$A$2:$A$5,Lookups!$D$2:$D$5),"CHECK CODE") -> INR | X27: =VALUE(MID(Table3[[#This Row],[Unit Price]],2,50)) -> 25000 | Y27: =_xlfn.IFNA(_xlfn.XLOOKUP(Table3[[#This Row],[Country Code]],Lookups!$A$2:$A$5,Lookups!$E$2:$E$5),"") -> 109.882 | Z27: =Table3[[#This Row],[Unit Price (local)]]/Table3[[#This Row],[FX Rate (per EUR)]] -> 227.51679 | AA27: 350 | AB27: 0 | AC27: =ROUND(Table3[[#This Row],[Unit Price (EUR)]]*Table3[[#This Row],[Units Sold]],0) -> 79631 | AD27: =ROUND(Table3[[#This Row],[Gross Sales (EUR)]]*(1-Table3[[#This Row],[Discount (%)]]/100),0) -> 79631 | AE27: =_xlfn.IFNA(_xlfn.XLOOKUP(Table3[[#This Row],[Month]],Lookups!$N$2:$N$13,Lookups!$O$2:$O$13),"CHECK MONTH") -> 3 | AF27: =TEXT(Table3[[#This Row],[Month No]],"00")&" - "&Table3[[#This Row],[Month]] -> 03 - March | AG27: =_xlfn.IFNA(_xlfn.XLOOKUP(Table3[[#This Row],[Month]],Lookups!$N$2:$N$13,Lookups!$P$2:$P$13),"CHECK MONTH") -> Q1 | AH27: =Table3[[#This Row],[Gross Sales (EUR)]]-Table3[[#This Row],[Total Sales (EUR)]] -> 0 | AI27: =DATE(Lookups!$O$15,Table3[[#This Row],[Month No]],1) -> 45717
A28: 27 | B28: Sanya | C28: Joshi | D28: =TRIM(Table3[[#This Row],[Rep Last Name]])&", "&TRIM(Table3[[#This Row],[Rep First Name]]) -> Joshi, Sanya | E28: March | F28: Electric Skateboard | G28: 18 mph | H28: =IF(Table3[[#This Row],[Min Speed (original, incomplete)]]="",_xlfn.IFNA(_xlfn.XLOOKUP(Table3[[#This Row],[Product Type]],Lookups!$G$2:$G$4,Lookups!$H$2:$H$4),"CHECK PRODUCT"),Table3[[#This Row],[Min Speed (original, incomplete)]]) -> 18 mph | I28: 28 mph | J28: 25 miles | K28: =ROUND(VALUE(SUBSTITUTE(Table3[[#This Row],[Min Speed (mph)]]," mph",""))*Lookups!$L$2,0) -> 29 | L28: =ROUND(VALUE(SUBSTITUTE(Table3[[#This Row],[Speed]]," mph",""))*Lookups!$L$2,0) -> 45 | M28: =Table3[[#This Row],[Min Speed (km/h)]]&" – "&Table3[[#This Row],[Max Speed (km/h)]]&" km/h" -> 29 – 45 km/h | N28: =IF(ISNUMBER(SEARCH("mile",Table3[[#This Row],[Distance]])),ROUND(VALUE(SUBSTITUTE(Table3[[#This Row],[Distance]]," miles",""))*Lookups!$L$3,0),ROUND(VALUE(SUBSTITUTE(Table3[[#This Row],[Distance]]," meters",""))*Lookups!$L$4,0)) -> 40 | O28: 458 Brigade Road, Bengaluru, 560001 | P28: =TRIM(LEFT(Table3[[#This Row],[Shipping Address]],FIND(",",Table3[[#This Row],[Shipping Address]])-1)) -> 458 Brigade Road | Q28: =TRIM(MID(Table3[[#This Row],[Shipping Address]],FIND(",",Table3[[#This Row],[Shipping Address]])+1,FIND(",",Table3[[#This Row],[Shipping Address]],FIND(",",Table3[[#This Row],[Shipping Address]])+1)-FIND(",",Table3[[#This Row],[Shipping Address]])-1)) -> Bengaluru | R28: =TRIM(MID(Table3[[#This Row],[Shipping Address]],FIND(",",Table3[[#This Row],[Shipping Address]],FIND(",",Table3[[#This Row],[Shipping Address]])+1)+1,20)) -> 560001 | S28: IN | T28: =_xlfn.IFNA(_xlfn.XLOOKUP(Table3[[#This Row],[Country Code]],Lookups!$A$2:$A$5,Lookups!$B$2:$B$5),"CHECK CODE") -> India | U28: =_xlfn.IFNA(_xlfn.XLOOKUP(Table3[[#This Row],[Country Code]],Lookups!$A$2:$A$5,Lookups!$C$2:$C$5),"CHECK CODE") -> Asia | V28: ₹22,000 | W28: =_xlfn.IFNA(_xlfn.XLOOKUP(Table3[[#This Row],[Country Code]],Lookups!$A$2:$A$5,Lookups!$D$2:$D$5),"CHECK CODE") -> INR | X28: =VALUE(MID(Table3[[#This Row],[Unit Price]],2,50)) -> 22000 | Y28: =_xlfn.IFNA(_xlfn.XLOOKUP(Table3[[#This Row],[Country Code]],Lookups!$A$2:$A$5,Lookups!$E$2:$E$5),"") -> 109.882 | Z28: =Table3[[#This Row],[Unit Price (local)]]/Table3[[#This Row],[FX Rate (per EUR)]] -> 200.21478 | AA28: 220 | AB28: 0 | AC28: =ROUND(Table3[[#This Row],[Unit Price (EUR)]]*Table3[[#This Row],[Units Sold]],0) -> 44047 | AD28: =ROUND(Table3[[#This Row],[Gross Sales (EUR)]]*(1-Table3[[#This Row],[Discount (%)]]/100),0) -> 44047 | AE28: =_xlfn.IFNA(_xlfn.XLOOKUP(Table3[[#This Row],[Month]],Lookups!$N$2:$N$13,Lookups!$O$2:$O$13),"CHECK MONTH") -> 3 | AF28: =TEXT(Table3[[#This Row],[Month No]],"00")&" - "&Table3[[#This Row],[Month]] -> 03 - March | AG28: =_xlfn.IFNA(_xlfn.XLOOKUP(Table3[[#This Row],[Month]],Lookups!$N$2:$N$13,Lookups!$P$2:$P$13),"CHECK MONTH") -> Q1 | AH28: =Table3[[#This Row],[Gross Sales (EUR)]]-Table3[[#This Row],[Total Sales (EUR)]] -> 0 | AI28: =DATE(Lookups!$O$15,Table3[[#This Row],[Month No]],1) -> 45717
A29: 28 | B29: Fang | C29: Liu | D29: =TRIM(Table3[[#This Row],[Rep Last Name]])&", "&TRIM(Table3[[#This Row],[Rep First Name]]) -> Liu, Fang | E29: March | F29: Electric Unicycle | G29: 15 mph | H29: =IF(Table3[[#This Row],[Min Speed (original, incomplete)]]="",_xlfn.IFNA(_xlfn.XLOOKUP(Table3[[#This Row],[Product Type]],Lookups!$G$2:$G$4,Lookups!$H$2:$H$4),"CHECK PRODUCT"),Table3[[#This Row],[Min Speed (original, incomplete)]]) -> 15 mph | I29: 30 mph | J29: 30 miles | K29: =ROUND(VALUE(SUBSTITUTE(Table3[[#This Row],[Min Speed (mph)]]," mph",""))*Lookups!$L$2,0) -> 24 | L29: =ROUND(VALUE(SUBSTITUTE(Table3[[#This Row],[Speed]]," mph",""))*Lookups!$L$2,0) -> 48 | M29: =Table3[[#This Row],[Min Speed (km/h)]]&" – "&Table3[[#This Row],[Max Speed (km/h)]]&" km/h" -> 24 – 48 km/h | N29: =IF(ISNUMBER(SEARCH("mile",Table3[[#This Row],[Distance]])),ROUND(VALUE(SUBSTITUTE(Table3[[#This Row],[Distance]]," miles",""))*Lookups!$L$3,0),ROUND(VALUE(SUBSTITUTE(Table3[[#This Row],[Distance]]," meters",""))*Lookups!$L$4,0)) -> 48 | O29: 99 Nanjing Road, Shanghai, 200001 | P29: =TRIM(LEFT(Table3[[#This Row],[Shipping Address]],FIND(",",Table3[[#This Row],[Shipping Address]])-1)) -> 99 Nanjing Road | Q29: =TRIM(MID(Table3[[#This Row],[Shipping Address]],FIND(",",Table3[[#This Row],[Shipping Address]])+1,FIND(",",Table3[[#This Row],[Shipping Address]],FIND(",",Table3[[#This Row],[Shipping Address]])+1)-FIND(",",Table3[[#This Row],[Shipping Address]])-1)) -> Shanghai | R29: =TRIM(MID(Table3[[#This Row],[Shipping Address]],FIND(",",Table3[[#This Row],[Shipping Address]],FIND(",",Table3[[#This Row],[Shipping Address]])+1)+1,20)) -> 200001 | S29: CN | T29: =_xlfn.IFNA(_xlfn.XLOOKUP(Table3[[#This Row],[Country Code]],Lookups!$A$2:$A$5,Lookups!$B$2:$B$5),"CHECK CODE") -> China | U29: =_xlfn.IFNA(_xlfn.XLOOKUP(Table3[[#This Row],[Country Code]],Lookups!$A$2:$A$5,Lookups!$C$2:$C$5),"CHECK CODE") -> Asia | V29: ¥5,000 | W29: =_xlfn.IFNA(_xlfn.XLOOKUP(Table3[[#This Row],[Country Code]],Lookups!$A$2:$A$5,Lookups!$D$2:$D$5),"CHECK CODE") -> CNY | X29: =VALUE(MID(Table3[[#This Row],[Unit Price]],2,50)) -> 5000 | Y29: =_xlfn.IFNA(_xlfn.XLOOKUP(Table3[[#This Row],[Country Code]],Lookups!$A$2:$A$5,Lookups!$E$2:$E$5),"") -> 7.7255 | Z29: =Table3[[#This Row],[Unit Price (local)]]/Table3[[#This Row],[FX Rate (per EUR)]] -> 647.2073 | AA29: 550 | AB29: 0 | AC29: =ROUND(Table3[[#This Row],[Unit Price (EUR)]]*Table3[[#This Row],[Units Sold]],0) -> 355964 | AD29: =ROUND(Table3[[#This Row],[Gross Sales (EUR)]]*(1-Table3[[#This Row],[Discount (%)]]/100),0) -> 355964 | AE29: =_xlfn.IFNA(_xlfn.XLOOKUP(Table3[[#This Row],[Month]],Lookups!$N$2:$N$13,Lookups!$O$2:$O$13),"CHECK MONTH") -> 3 | AF29: =TEXT(Table3[[#This Row],[Month No]],"00")&" - "&Table3[[#This Row],[Month]] -> 03 - March | AG29: =_xlfn.IFNA(_xlfn.XLOOKUP(Table3[[#This Row],[Month]],Lookups!$N$2:$N$13,Lookups!$P$2:$P$13),"CHECK MONTH") -> Q1 | AH29: =Table3[[#This Row],[Gross Sales (EUR)]]-Table3[[#This Row],[Total Sales (EUR)]] -> 0 | AI29: =DATE(Lookups!$O$15,Table3[[#This Row],[Month No]],1) -> 45717
A30: 29 | B30: Fang | C30: Liu | D30: =TRIM(Table3[[#This Row],[Rep Last Name]])&", "&TRIM(Table3[[#This Row],[Rep First Name]]) -> Liu, Fang | E30: March | F30: Electric Scooter | G30: 20 mph | H30: =IF(Table3[[#This Row],[Min Speed (original, incomplete)]]="",_xlfn.IFNA(_xlfn.XLOOKUP(Table3[[#This Row],[Product Type]],Lookups!$G$2:$G$4,Lookups!$H$2:$H$4),"CHECK PRODUCT"),Table3[[#This Row],[Min Speed (original, incomplete)]]) -> 20 mph | I30: 35 mph | J30: 64,370 meters | K30: =ROUND(VALUE(SUBSTITUTE(Table3[[#This Row],[Min Speed (mph)]]," mph",""))*Lookups!$L$2,0) -> 32 | L30: =ROUND(VALUE(SUBSTITUTE(Table3[[#This Row],[Speed]]," mph",""))*Lookups!$L$2,0) -> 56 | M30: =Table3[[#This Row],[Min Speed (km/h)]]&" – "&Table3[[#This Row],[Max Speed (km/h)]]&" km/h" -> 32 – 56 km/h | N30: =IF(ISNUMBER(SEARCH("mile",Table3[[#This Row],[Distance]])),ROUND(VALUE(SUBSTITUTE(Table3[[#This Row],[Distance]]," miles",""))*Lookups!$L$3,0),ROUND(VALUE(SUBSTITUTE(Table3[[#This Row],[Distance]]," meters",""))*Lookups!$L$4,0)) -> 64 | O30: 100 Nanjing Road, Shanghai, 200001 | P30: =TRIM(LEFT(Table3[[#This Row],[Shipping Address]],FIND(",",Table3[[#This Row],[Shipping Address]])-1)) -> 100 Nanjing Road | Q30: =TRIM(MID(Table3[[#This Row],[Shipping Address]],FIND(",",Table3[[#This Row],[Shipping Address]])+1,FIND(",",Table3[[#This Row],[Shipping Address]],FIND(",",Table3[[#This Row],[Shipping Address]])+1)-FIND(",",Table3[[#This Row],[Shipping Address]])-1)) -> Shanghai | R30: =TRIM(MID(Table3[[#This Row],[Shipping Address]],FIND(",",Table3[[#This Row],[Shipping Address]],FIND(",",Table3[[#This Row],[Shipping Address]])+1)+1,20)) -> 200001 | S30: CN | T30: =_xlfn.IFNA(_xlfn.XLOOKUP(Table3[[#This Row],[Country Code]],Lookups!$A$2:$A$5,Lookups!$B$2:$B$5),"CHECK CODE") -> China | U30: =_xlfn.IFNA(_xlfn.XLOOKUP(Table3[[#This Row],[Country Code]],Lookups!$A$2:$A$5,Lookups!$C$2:$C$5),"CHECK CODE") -> Asia | V30: ¥3,500 | W30: =_xlfn.IFNA(_xlfn.XLOOKUP(Table3[[#This Row],[Country Code]],Lookups!$A$2:$A$5,Lookups!$D$2:$D$5),"CHECK CODE") -> CNY | X30: =VALUE(MID(Table3[[#This Row],[Unit Price]],2,50)) -> 3500 | Y30: =_xlfn.IFNA(_xlfn.XLOOKUP(Table3[[#This Row],[Country Code]],Lookups!$A$2:$A$5,Lookups!$E$2:$E$5),"") -> 7.7255 | Z30: =Table3[[#This Row],[Unit Price (local)]]/Table3[[#This Row],[FX Rate (per EUR)]] -> 453.04511 | AA30: 1200 | AB30: 0 | AC30: =ROUND(Table3[[#This Row],[Unit Price (EUR)]]*Table3[[#This Row],[Units Sold]],0) -> 543654 | AD30: =ROUND(Table3[[#This Row],[Gross Sales (EUR)]]*(1-Table3[[#This Row],[Discount (%)]]/100),0) -> 543654 | AE30: =_xlfn.IFNA(_xlfn.XLOOKUP(Table3[[#This Row],[Month]],Lookups!$N$2:$N$13,Lookups!$O$2:$O$13),"CHECK MONTH") -> 3 | AF30: =TEXT(Table3[[#This Row],[Month No]],"00")&" - "&Table3[[#This Row],[Month]] -> 03 - March | AG30: =_xlfn.IFNA(_xlfn.XLOOKUP(Table3[[#This Row],[Month]],Lookups!$N$2:$N$13,Lookups!$P$2:$P$13),"CHECK MONTH") -> Q1 | AH30: =Table3[[#This Row],[Gross Sales (EUR)]]-Table3[[#This Row],[Total Sales (EUR)]] -> 0 | AI30: =DATE(Lookups!$O$15,Table3[[#This Row],[Month No]],1) -> 45717
A31: 30 | B31: Fang | C31: Liu | D31: =TRIM(Table3[[#This Row],[Rep Last Name]])&", "&TRIM(Table3[[#This Row],[Rep First Name]]) -> Liu, Fang | E31: March | F31: Electric Skateboard | G31: 18 mph | H31: =IF(Table3[[#This Row],[Min Speed (original, incomplete)]]="",_xlfn.IFNA(_xlfn.XLOOKUP(Table3[[#This Row],[Product Type]],Lookups!$G$2:$G$4,Lookups!$H$2:$H$4),"CHECK PRODUCT"),Table3[[#This Row],[Min Speed (original, incomplete)]]) -> 18 mph | I31: 28 mph | J31: 25 miles | K31: =ROUND(VALUE(SUBSTITUTE(Table3[[#This Row],[Min Speed (mph)]]," mph",""))*Lookups!$L$2,0) -> 29 | L31: =ROUND(VALUE(SUBSTITUTE(Table3[[#This Row],[Speed]]," mph",""))*Lookups!$L$2,0) -> 45 | M31: =Table3[[#This Row],[Min Speed (km/h)]]&" – "&Table3[[#This Row],[Max Speed (km/h)]]&" km/h" -> 29 – 45 km/h | N31: =IF(ISNUMBER(SEARCH("mile",Table3[[#This Row],[Distance]])),ROUND(VALUE(SUBSTITUTE(Table3[[#This Row],[Distance]]," miles",""))*Lookups!$L$3,0),ROUND(VALUE(SUBSTITUTE(Table3[[#This Row],[Distance]]," meters",""))*Lookups!$L$4,0)) -> 40 | O31: 101 Nanjing Road, Shanghai, 200001 | P31: =TRIM(LEFT(Table3[[#This Row],[Shipping Address]],FIND(",",Table3[[#This Row],[Shipping Address]])-1)) -> 101 Nanjing Road | Q31: =TRIM(MID(Table3[[#This Row],[Shipping Address]],FIND(",",Table3[[#This Row],[Shipping Address]])+1,FIND(",",Table3[[#This Row],[Shipping Address]],FIND(",",Table3[[#This Row],[Shipping Address]])+1)-FIND(",",Table3[[#This Row],[Shipping Address]])-1)) -> Shanghai | R31: =TRIM(MID(Table3[[#This Row],[Shipping Address]],FIND(",",Table3[[#This Row],[Shipping Address]],FIND(",",Table3[[#This Row],[Shipping Address]])+1)+1,20)) -> 200001 | S31: CN | T31: =_xlfn.IFNA(_xlfn.XLOOKUP(Table3[[#This Row],[Country Code]],Lookups!$A$2:$A$5,Lookups!$B$2:$B$5),"CHECK CODE") -> China | U31: =_xlfn.IFNA(_xlfn.XLOOKUP(Table3[[#This Row],[Country Code]],Lookups!$A$2:$A$5,Lookups!$C$2:$C$5),"CHECK CODE") -> Asia | V31: ¥4,200 | W31: =_xlfn.IFNA(_xlfn.XLOOKUP(Table3[[#This Row],[Country Code]],Lookups!$A$2:$A$5,Lookups!$D$2:$D$5),"CHECK CODE") -> CNY | X31: =VALUE(MID(Table3[[#This Row],[Unit Price]],2,50)) -> 4200 | Y31: =_xlfn.IFNA(_xlfn.XLOOKUP(Table3[[#This Row],[Country Code]],Lookups!$A$2:$A$5,Lookups!$E$2:$E$5),"") -> 7.7255 | Z31: =Table3[[#This Row],[Unit Price (local)]]/Table3[[#This Row],[FX Rate (per EUR)]] -> 543.65413 | AA31: 850 | AB31: 0 | AC31: =ROUND(Table3[[#This Row],[Unit Price (EUR)]]*Table3[[#This Row],[Units Sold]],0) -> 462106 | AD31: =ROUND(Table3[[#This Row],[Gross Sales (EUR)]]*(1-Table3[[#This Row],[Discount (%)]]/100),0) -> 462106 | AE31: =_xlfn.IFNA(_xlfn.XLOOKUP(Table3[[#This Row],[Month]],Lookups!$N$2:$N$13,Lookups!$O$2:$O$13),"CHECK MONTH") -> 3 | AF31: =TEXT(Table3[[#This Row],[Month No]],"00")&" - "&Table3[[#This Row],[Month]] -> 03 - March | AG31: =_xlfn.IFNA(_xlfn.XLOOKUP(Table3[[#This Row],[Month]],Lookups!$N$2:$N$13,Lookups!$P$2:$P$13),"CHECK MONTH") -> Q1 | AH31: =Table3[[#This Row],[Gross Sales (EUR)]]-Table3[[#This Row],[Total Sales (EUR)]] -> 0 | AI31: =DATE(Lookups!$O$15,Table3[[#This Row],[Month No]],1) -> 45717
A32: 31 | B32: Jonas | C32: Fischer | D32: =TRIM(Table3[[#This Row],[Rep Last Name]])&", "&TRIM(Table3[[#This Row],[Rep First Name]]) -> Fischer, Jonas | E32: March | F32: Electric Unicycle | G32: 15 mph | H32: =IF(Table3[[#This Row],[Min Speed (original, incomplete)]]="",_xlfn.IFNA(_xlfn.XLOOKUP(Table3[[#This Row],[Product Type]],Lookups!$G$2:$G$4,Lookups!$H$2:$H$4),"CHECK PRODUCT"),Table3[[#This Row],[Min Speed (original, incomplete)]]) -> 15 mph | I32: 30 mph | J32: 30 miles | K32: =ROUND(VALUE(SUBSTITUTE(Table3[[#This Row],[Min Speed (mph)]]," mph",""))*Lookups!$L$2,0) -> 24 | L32: =ROUND(VALUE(SUBSTITUTE(Table3[[#This Row],[Speed]]," mph",""))*Lookups!$L$2,0) -> 48 | M32: =Table3[[#This Row],[Min Speed (km/h)]]&" – "&Table3[[#This Row],[Max Speed (km/h)]]&" km/h" -> 24 – 48 km/h | N32: =IF(ISNUMBER(SEARCH("mile",Table3[[#This Row],[Distance]])),ROUND(VALUE(SUBSTITUTE(Table3[[#This Row],[Distance]]," miles",""))*Lookups!$L$3,0),ROUND(VALUE(SUBSTITUTE(Table3[[#This Row],[Distance]]," meters",""))*Lookups!$L$4,0)) -> 48 | O32: 303 Ringstraße, Hamburg, 20095 | P32: =TRIM(LEFT(Table3[[#This Row],[Shipping Address]],FIND(",",Table3[[#This Row],[Shipping Address]])-1)) -> 303 Ringstraße | Q32: =TRIM(MID(Table3[[#This Row],[Shipping Address]],FIND(",",Table3[[#This Row],[Shipping Address]])+1,FIND(",",Table3[[#This Row],[Shipping Address]],FIND(",",Table3[[#This Row],[Shipping Address]])+1)-FIND(",",Table3[[#This Row],[Shipping Address]])-1)) -> Hamburg | R32: =TRIM(MID(Table3[[#This Row],[Shipping Address]],FIND(",",Table3[[#This Row],[Shipping Address]],FIND(",",Table3[[#This Row],[Shipping Address]])+1)+1,20)) -> 20095 | S32: DE | T32: =_xlfn.IFNA(_xlfn.XLOOKUP(Table3[[#This Row],[Country Code]],Lookups!$A$2:$A$5,Lookups!$B$2:$B$5),"CHECK CODE") -> Germany | U32: =_xlfn.IFNA(_xlfn.XLOOKUP(Table3[[#This Row],[Country Code]],Lookups!$A$2:$A$5,Lookups!$C$2:$C$5),"CHECK CODE") -> Europe | V32: €1000 | W32: =_xlfn.IFNA(_xlfn.XLOOKUP(Table3[[#This Row],[Country Code]],Lookups!$A$2:$A$5,Lookups!$D$2:$D$5),"CHECK CODE") -> EUR | X32: =VALUE(MID(Table3[[#This Row],[Unit Price]],2,50)) -> 1000 | Y32: =_xlfn.IFNA(_xlfn.XLOOKUP(Table3[[#This Row],[Country Code]],Lookups!$A$2:$A$5,Lookups!$E$2:$E$5),"") -> 1 | Z32: =Table3[[#This Row],[Unit Price (local)]]/Table3[[#This Row],[FX Rate (per EUR)]] -> 1000 | AA32: 130 | AB32: 0 | AC32: =ROUND(Table3[[#This Row],[Unit Price (EUR)]]*Table3[[#This Row],[Units Sold]],0) -> 130000 | AD32: =ROUND(Table3[[#This Row],[Gross Sales (EUR)]]*(1-Table3[[#This Row],[Discount (%)]]/100),0) -> 130000 | AE32: =_xlfn.IFNA(_xlfn.XLOOKUP(Table3[[#This Row],[Month]],Lookups!$N$2:$N$13,Lookups!$O$2:$O$13),"CHECK MONTH") -> 3 | AF32: =TEXT(Table3[[#This Row],[Month No]],"00")&" - "&Table3[[#This Row],[Month]] -> 03 - March | AG32: =_xlfn.IFNA(_xlfn.XLOOKUP(Table3[[#This Row],[Month]],Lookups!$N$2:$N$13,Lookups!$P$2:$P$13),"CHECK MONTH") -> Q1 | AH32: =Table3[[#This Row],[Gross Sales (EUR)]]-Table3[[#This Row],[Total Sales (EUR)]] -> 0 | AI32: =DATE(Lookups!$O$15,Table3[[#This Row],[Month No]],1) -> 45717
A33: 32 | B33: Jonas | C33: Fischer | D33: =TRIM(Table3[[#This Row],[Rep Last Name]])&", "&TRIM(Table3[[#This Row],[Rep First Name]]) -> Fischer, Jonas | E33: March | F33: Electric Scooter | G33: 20 mph | H33: =IF(Table3[[#This Row],[Min Speed (original, incomplete)]]="",_xlfn.IFNA(_xlfn.XLOOKUP(Table3[[#This Row],[Product Type]],Lookups!$G$2:$G$4,Lookups!$H$2:$H$4),"CHECK PRODUCT"),Table3[[#This Row],[Min Speed (original, incomplete)]]) -> 20 mph | I33: 35 mph | J33: 40 miles | K33: =ROUND(VALUE(SUBSTITUTE(Table3[[#This Row],[Min Speed (mph)]]," mph",""))*Lookups!$L$2,0) -> 32 | L33: =ROUND(VALUE(SUBSTITUTE(Table3[[#This Row],[Speed]]," mph",""))*Lookups!$L$2,0) -> 56 | M33: =Table3[[#This Row],[Min Speed (km/h)]]&" – "&Table3[[#This Row],[Max Speed (km/h)]]&" km/h" -> 32 – 56 km/h | N33: =IF(ISNUMBER(SEARCH("mile",Table3[[#This Row],[Distance]])),ROUND(VALUE(SUBSTITUTE(Table3[[#This Row],[Distance]]," miles",""))*Lookups!$L$3,0),ROUND(VALUE(SUBSTITUTE(Table3[[#This Row],[Distance]]," meters",""))*Lookups!$L$4,0)) -> 64 | O33: 304 Ringstraße, Hamburg, 20095 | P33: =TRIM(LEFT(Table3[[#This Row],[Shipping Address]],FIND(",",Table3[[#This Row],[Shipping Address]])-1)) -> 304 Ringstraße | Q33: =TRIM(MID(Table3[[#This Row],[Shipping Address]],FIND(",",Table3[[#This Row],[Shipping Address]])+1,FIND(",",Table3[[#This Row],[Shipping Address]],FIND(",",Table3[[#This Row],[Shipping Address]])+1)-FIND(",",Table3[[#This Row],[Shipping Address]])-1)) -> Hamburg | R33: =TRIM(MID(Table3[[#This Row],[Shipping Address]],FIND(",",Table3[[#This Row],[Shipping Address]],FIND(",",Table3[[#This Row],[Shipping Address]])+1)+1,20)) -> 20095 | S33: DE | T33: =_xlfn.IFNA(_xlfn.XLOOKUP(Table3[[#This Row],[Country Code]],Lookups!$A$2:$A$5,Lookups!$B$2:$B$5),"CHECK CODE") -> Germany | U33: =_xlfn.IFNA(_xlfn.XLOOKUP(Table3[[#This Row],[Country Code]],Lookups!$A$2:$A$5,Lookups!$C$2:$C$5),"CHECK CODE") -> Europe | V33: €800 | W33: =_xlfn.IFNA(_xlfn.XLOOKUP(Table3[[#This Row],[Country Code]],Lookups!$A$2:$A$5,Lookups!$D$2:$D$5),"CHECK CODE") -> EUR | X33: =VALUE(MID(Table3[[#This Row],[Unit Price]],2,50)) -> 800 | Y33: =_xlfn.IFNA(_xlfn.XLOOKUP(Table3[[#This Row],[Country Code]],Lookups!$A$2:$A$5,Lookups!$E$2:$E$5),"") -> 1 | Z33: =Table3[[#This Row],[Unit Price (local)]]/Table3[[#This Row],[FX Rate (per EUR)]] -> 800 | AA33: 220 | AB33: 0 | AC33: =ROUND(Table3[[#This Row],[Unit Price (EUR)]]*Table3[[#This Row],[Units Sold]],0) -> 176000 | AD33: =ROUND(Table3[[#This Row],[Gross Sales (EUR)]]*(1-Table3[[#This Row],[Discount (%)]]/100),0) -> 176000 | AE33: =_xlfn.IFNA(_xlfn.XLOOKUP(Table3[[#This Row],[Month]],Lookups!$N$2:$N$13,Lookups!$O$2:$O$13),"CHECK MONTH") -> 3 | AF33: =TEXT(Table3[[#This Row],[Month No]],"00")&" - "&Table3[[#This Row],[Month]] -> 03 - March | AG33: =_xlfn.IFNA(_xlfn.XLOOKUP(Table3[[#This Row],[Month]],Lookups!$N$2:$N$13,Lookups!$P$2:$P$13),"CHECK MONTH") -> Q1 | AH33: =Table3[[#This Row],[Gross Sales (EUR)]]-Table3[[#This Row],[Total Sales (EUR)]] -> 0 | AI33: =DATE(Lookups!$O$15,Table3[[#This Row],[Month No]],1) -> 45717
A34: 33 | B34: Jonas | C34: Fischer | D34: =TRIM(Table3[[#This Row],[Rep Last Name]])&", "&TRIM(Table3[[#This Row],[Rep First Name]]) -> Fischer, Jonas | E34: March | F34: Electric Skateboard | G34: 18 mph | H34: =IF(Table3[[#This Row],[Min Speed (original, incomplete)]]="",_xlfn.IFNA(_xlfn.XLOOKUP(Table3[[#This Row],[Product Type]],Lookups!$G$2:$G$4,Lookups!$H$2:$H$4),"CHECK PRODUCT"),Table3[[#This Row],[Min Speed (original, incomplete)]]) -> 18 mph | I34: 28 mph | J34: 25 miles | K34: =ROUND(VALUE(SUBSTITUTE(Table3[[#This Row],[Min Speed (mph)]]," mph",""))*Lookups!$L$2,0) -> 29 | L34: =ROUND(VALUE(SUBSTITUTE(Table3[[#This Row],[Speed]]," mph",""))*Lookups!$L$2,0) -> 45 | M34: =Table3[[#This Row],[Min Speed (km/h)]]&" – "&Table3[[#This Row],[Max Speed (km/h)]]&" km/h" -> 29 – 45 km/h | N34: =IF(ISNUMBER(SEARCH("mile",Table3[[#This Row],[Distance]])),ROUND(VALUE(SUBSTITUTE(Table3[[#This Row],[Distance]]," miles",""))*Lookups!$L$3,0),ROUND(VALUE(SUBSTITUTE(Table3[[#This Row],[Distance]]," meters",""))*Lookups!$L$4,0)) -> 40 | O34: 305 Ringstraße, Hamburg, 20095 | P34: =TRIM(LEFT(Table3[[#This Row],[Shipping Address]],FIND(",",Table3[[#This Row],[Shipping Address]])-1)) -> 305 Ringstraße | Q34: =TRIM(MID(Table3[[#This Row],[Shipping Address]],FIND(",",Table3[[#This Row],[Shipping Address]])+1,FIND(",",Table3[[#This Row],[Shipping Address]],FIND(",",Table3[[#This Row],[Shipping Address]])+1)-FIND(",",Table3[[#This Row],[Shipping Address]])-1)) -> Hamburg | R34: =TRIM(MID(Table3[[#This Row],[Shipping Address]],FIND(",",Table3[[#This Row],[Shipping Address]],FIND(",",Table3[[#This Row],[Shipping Address]])+1)+1,20)) -> 20095 | S34: DE | T34: =_xlfn.IFNA(_xlfn.XLOOKUP(Table3[[#This Row],[Country Code]],Lookups!$A$2:$A$5,Lookups!$B$2:$B$5),"CHECK CODE") -> Germany | U34: =_xlfn.IFNA(_xlfn.XLOOKUP(Table3[[#This Row],[Country Code]],Lookups!$A$2:$A$5,Lookups!$C$2:$C$5),"CHECK CODE") -> Europe | V34: €950 | W34: =_xlfn.IFNA(_xlfn.XLOOKUP(Table3[[#This Row],[Country Code]],Lookups!$A$2:$A$5,Lookups!$D$2:$D$5),"CHECK CODE") -> EUR | X34: =VALUE(MID(Table3[[#This Row],[Unit Price]],2,50)) -> 950 | Y34: =_xlfn.IFNA(_xlfn.XLOOKUP(Table3[[#This Row],[Country Code]],Lookups!$A$2:$A$5,Lookups!$E$2:$E$5),"") -> 1 | Z34: =Table3[[#This Row],[Unit Price (local)]]/Table3[[#This Row],[FX Rate (per EUR)]] -> 950 | AA34: 160 | AB34: 0 | AC34: =ROUND(Table3[[#This Row],[Unit Price (EUR)]]*Table3[[#This Row],[Units Sold]],0) -> 152000 | AD34: =ROUND(Table3[[#This Row],[Gross Sales (EUR)]]*(1-Table3[[#This Row],[Discount (%)]]/100),0) -> 152000 | AE34: =_xlfn.IFNA(_xlfn.XLOOKUP(Table3[[#This Row],[Month]],Lookups!$N$2:$N$13,Lookups!$O$2:$O$13),"CHECK MONTH") -> 3 | AF34: =TEXT(Table3[[#This Row],[Month No]],"00")&" - "&Table3[[#This Row],[Month]] -> 03 - March | AG34: =_xlfn.IFNA(_xlfn.XLOOKUP(Table3[[#This Row],[Month]],Lookups!$N$2:$N$13,Lookups!$P$2:$P$13),"CHECK MONTH") -> Q1 | AH34: =Table3[[#This Row],[Gross Sales (EUR)]]-Table3[[#This Row],[Total Sales (EUR)]] -> 0 | AI34: =DATE(Lookups!$O$15,Table3[[#This Row],[Month No]],1) -> 45717
A35: 34 | B35: Théo | C35: Bernard | D35: =TRIM(Table3[[#This Row],[Rep Last Name]])&", "&TRIM(Table3[[#This Row],[Rep First Name]]) -> Bernard, Théo | E35: March | F35: Electric Unicycle | G35: 15 mph | H35: =IF(Table3[[#This Row],[Min Speed (original, incomplete)]]="",_xlfn.IFNA(_xlfn.XLOOKUP(Table3[[#This Row],[Product Type]],Lookups!$G$2:$G$4,Lookups!$H$2:$H$4),"CHECK PRODUCT"),Table3[[#This Row],[Min Speed (original, incomplete)]]) -> 15 mph | I35: 30 mph | J35: 48,280 meters | K35: =ROUND(VALUE(SUBSTITUTE(Table3[[#This Row],[Min Speed (mph)]]," mph",""))*Lookups!$L$2,0) -> 24 | L35: =ROUND(VALUE(SUBSTITUTE(Table3[[#This Row],[Speed]]," mph",""))*Lookups!$L$2,0) -> 48 | M35: =Table3[[#This Row],[Min Speed (km/h)]]&" – "&Table3[[#This Row],[Max Speed (km/h)]]&" km/h" -> 24 – 48 km/h | N35: =IF(ISNUMBER(SEARCH("mile",Table3[[#This Row],[Distance]])),ROUND(VALUE(SUBSTITUTE(Table3[[#This Row],[Distance]]," miles",""))*Lookups!$L$3,0),ROUND(VALUE(SUBSTITUTE(Table3[[#This Row],[Distance]]," meters",""))*Lookups!$L$4,0)) -> 48 | O35: 56 Boulevard Saint-Germain, Paris, 75005 | P35: =TRIM(LEFT(Table3[[#This Row],[Shipping Address]],FIND(",",Table3[[#This Row],[Shipping Address]])-1)) -> 56 Boulevard Saint-Germain | Q35: =TRIM(MID(Table3[[#This Row],[Shipping Address]],FIND(",",Table3[[#This Row],[Shipping Address]])+1,FIND(",",Table3[[#This Row],[Shipping Address]],FIND(",",Table3[[#This Row],[Shipping Address]])+1)-FIND(",",Table3[[#This Row],[Shipping Address]])-1)) -> Paris | R35: =TRIM(MID(Table3[[#This Row],[Shipping Address]],FIND(",",Table3[[#This Row],[Shipping Address]],FIND(",",Table3[[#This Row],[Shipping Address]])+1)+1,20)) -> 75005 | S35: FR | T35: =_xlfn.IFNA(_xlfn.XLOOKUP(Table3[[#This Row],[Country Code]],Lookups!$A$2:$A$5,Lookups!$B$2:$B$5),"CHECK CODE") -> France | U35: =_xlfn.IFNA(_xlfn.XLOOKUP(Table3[[#This Row],[Country Code]],Lookups!$A$2:$A$5,Lookups!$C$2:$C$5),"CHECK CODE") -> Europe | V35: €1100 | W35: =_xlfn.IFNA(_xlfn.XLOOKUP(Table3[[#This Row],[Country Code]],Lookups!$A$2:$A$5,Lookups!$D$2:$D$5),"CHECK CODE") -> EUR | X35: =VALUE(MID(Table3[[#This Row],[Unit Price]],2,50)) -> 1100 | Y35: =_xlfn.IFNA(_xlfn.XLOOKUP(Table3[[#This Row],[Country Code]],Lookups!$A$2:$A$5,Lookups!$E$2:$E$5),"") -> 1 | Z35: =Table3[[#This Row],[Unit Price (local)]]/Table3[[#This Row],[FX Rate (per EUR)]] -> 1100 | AA35: 110 | AB35: 0 | AC35: =ROUND(Table3[[#This Row],[Unit Price (EUR)]]*Table3[[#This Row],[Units Sold]],0) -> 121000 | AD35: =ROUND(Table3[[#This Row],[Gross Sales (EUR)]]*(1-Table3[[#This Row],[Discount (%)]]/100),0) -> 121000 | AE35: =_xlfn.IFNA(_xlfn.XLOOKUP(Table3[[#This Row],[Month]],Lookups!$N$2:$N$13,Lookups!$O$2:$O$13),"CHECK MONTH") -> 3 | AF35: =TEXT(Table3[[#This Row],[Month No]],"00")&" - "&Table3[[#This Row],[Month]] -> 03 - March | AG35: =_xlfn.IFNA(_xlfn.XLOOKUP(Table3[[#This Row],[Month]],Lookups!$N$2:$N$13,Lookups!$P$2:$P$13),"CHECK MONTH") -> Q1 | AH35: =Table3[[#This Row],[Gross Sales (EUR)]]-Table3[[#This Row],[Total Sales (EUR)]] -> 0 | AI35: =DATE(Lookups!$O$15,Table3[[#This Row],[Month No]],1) -> 45717
A36: 35 | B36: Théo | C36: Bernard | D36: =TRIM(Table3[[#This Row],[Rep Last Name]])&", "&TRIM(Table3[[#This Row],[Rep First Name]]) -> Bernard, Théo | E36: March | F36: Electric Scooter | G36: 20 mph | H36: =IF(Table3[[#This Row],[Min Speed (original, incomplete)]]="",_xlfn.IFNA(_xlfn.XLOOKUP(Table3[[#This Row],[Product Type]],Lookups!$G$2:$G$4,Lookups!$H$2:$H$4),"CHECK PRODUCT"),Table3[[#This Row],[Min Speed (original, incomplete)]]) -> 20 mph | I36: 35 mph | J36: 40 miles | K36: =ROUND(VALUE(SUBSTITUTE(Table3[[#This Row],[Min Speed (mph)]]," mph",""))*Lookups!$L$2,0) -> 32 | L36: =ROUND(VALUE(SUBSTITUTE(Table3[[#This Row],[Speed]]," mph",""))*Lookups!$L$2,0) -> 56 | M36: =Table3[[#This Row],[Min Speed (km/h)]]&" – "&Table3[[#This Row],[Max Speed (km/h)]]&" km/h" -> 32 – 56 km/h | N36: =IF(ISNUMBER(SEARCH("mile",Table3[[#This Row],[Distance]])),ROUND(VALUE(SUBSTITUTE(Table3[[#This Row],[Distance]]," miles",""))*Lookups!$L$3,0),ROUND(VALUE(SUBSTITUTE(Table3[[#This Row],[Distance]]," meters",""))*Lookups!$L$4,0)) -> 64 | O36: 57 Boulevard Saint-Germain, Paris, 75005 | P36: =TRIM(LEFT(Table3[[#This Row],[Shipping Address]],FIND(",",Table3[[#This Row],[Shipping Address]])-1)) -> 57 Boulevard Saint-Germain | Q36: =TRIM(MID(Table3[[#This Row],[Shipping Address]],FIND(",",Table3[[#This Row],[Shipping Address]])+1,FIND(",",Table3[[#This Row],[Shipping Address]],FIND(",",Table3[[#This Row],[Shipping Address]])+1)-FIND(",",Table3[[#This Row],[Shipping Address]])-1)) -> Paris | R36: =TRIM(MID(Table3[[#This Row],[Shipping Address]],FIND(",",Table3[[#This Row],[Shipping Address]],FIND(",",Table3[[#This Row],[Shipping Address]])+1)+1,20)) -> 75005 | S36: FR | T36: =_xlfn.IFNA(_xlfn.XLOOKUP(Table3[[#This Row],[Country Code]],Lookups!$A$2:$A$5,Lookups!$B$2:$B$5),"CHECK CODE") -> France | U36: =_xlfn.IFNA(_xlfn.XLOOKUP(Table3[[#This Row],[Country Code]],Lookups!$A$2:$A$5,Lookups!$C$2:$C$5),"CHECK CODE") -> Europe | V36: €900 | W36: =_xlfn.IFNA(_xlfn.XLOOKUP(Table3[[#This Row],[Country Code]],Lookups!$A$2:$A$5,Lookups!$D$2:$D$5),"CHECK CODE") -> EUR | X36: =VALUE(MID(Table3[[#This Row],[Unit Price]],2,50)) -> 900 | Y36: =_xlfn.IFNA(_xlfn.XLOOKUP(Table3[[#This Row],[Country Code]],Lookups!$A$2:$A$5,Lookups!$E$2:$E$5),"") -> 1 | Z36: =Table3[[#This Row],[Unit Price (local)]]/Table3[[#This Row],[FX Rate (per EUR)]] -> 900 | AA36: 260 | AB36: 0 | AC36: =ROUND(Table3[[#This Row],[Unit Price (EUR)]]*Table3[[#This Row],[Units Sold]],0) -> 234000 | AD36: =ROUND(Table3[[#This Row],[Gross Sales (EUR)]]*(1-Table3[[#This Row],[Discount (%)]]/100),0) -> 234000 | AE36: =_xlfn.IFNA(_xlfn.XLOOKUP(Table3[[#This Row],[Month]],Lookups!$N$2:$N$13,Lookups!$O$2:$O$13),"CHECK MONTH") -> 3 | AF36: =TEXT(Table3[[#This Row],[Month No]],"00")&" - "&Table3[[#This Row],[Month]] -> 03 - March | AG36: =_xlfn.IFNA(_xlfn.XLOOKUP(Table3[[#This Row],[Month]],Lookups!$N$2:$N$13,Lookups!$P$2:$P$13),"CHECK MONTH") -> Q1 | AH36: =Table3[[#This Row],[Gross Sales (EUR)]]-Table3[[#This Row],[Total Sales (EUR)]] -> 0 | AI36: =DATE(Lookups!$O$15,Table3[[#This Row],[Month No]],1) -> 45717
A37: 36 | B37: Théo | C37: Bernard | D37: =TRIM(Table3[[#This Row],[Rep Last Name]])&", "&TRIM(Table3[[#This Row],[Rep First Name]]) -> Bernard, Théo | E37: March | F37: Electric Skateboard | G37: 18 mph | H37: =IF(Table3[[#This Row],[Min Speed (original, incomplete)]]="",_xlfn.IFNA(_xlfn.XLOOKUP(Table3[[#This Row],[Product Type]],Lookups!$G$2:$G$4,Lookups!$H$2:$H$4),"CHECK PRODUCT"),Table3[[#This Row],[Min Speed (original, incomplete)]]) -> 18 mph | I37: 28 mph | J37: 25 miles | K37: =ROUND(VALUE(SUBSTITUTE(Table3[[#This Row],[Min Speed (mph)]]," mph",""))*Lookups!$L$2,0) -> 29 | L37: =ROUND(VALUE(SUBSTITUTE(Table3[[#This Row],[Speed]]," mph",""))*Lookups!$L$2,0) -> 45 | M37: =Table3[[#This Row],[Min Speed (km/h)]]&" – "&Table3[[#This Row],[Max Speed (km/h)]]&" km/h" -> 29 – 45 km/h | N37: =IF(ISNUMBER(SEARCH("mile",Table3[[#This Row],[Distance]])),ROUND(VALUE(SUBSTITUTE(Table3[[#This Row],[Distance]]," miles",""))*Lookups!$L$3,0),ROUND(VALUE(SUBSTITUTE(Table3[[#This Row],[Distance]]," meters",""))*Lookups!$L$4,0)) -> 40 | O37: 58 Boulevard Saint-Germain, Paris, 75005 | P37: =TRIM(LEFT(Table3[[#This Row],[Shipping Address]],FIND(",",Table3[[#This Row],[Shipping Address]])-1)) -> 58 Boulevard Saint-Germain | Q37: =TRIM(MID(Table3[[#This Row],[Shipping Address]],FIND(",",Table3[[#This Row],[Shipping Address]])+1,FIND(",",Table3[[#This Row],[Shipping Address]],FIND(",",Table3[[#This Row],[Shipping Address]])+1)-FIND(",",Table3[[#This Row],[Shipping Address]])-1)) -> Paris | R37: =TRIM(MID(Table3[[#This Row],[Shipping Address]],FIND(",",Table3[[#This Row],[Shipping Address]],FIND(",",Table3[[#This Row],[Shipping Address]])+1)+1,20)) -> 75005 | S37: FR | T37: =_xlfn.IFNA(_xlfn.XLOOKUP(Table3[[#This Row],[Country Code]],Lookups!$A$2:$A$5,Lookups!$B$2:$B$5),"CHECK CODE") -> France | U37: =_xlfn.IFNA(_xlfn.XLOOKUP(Table3[[#This Row],[Country Code]],Lookups!$A$2:$A$5,Lookups!$C$2:$C$5),"CHECK CODE") -> Europe | V37: €1050 | W37: =_xlfn.IFNA(_xlfn.XLOOKUP(Table3[[#This Row],[Country Code]],Lookups!$A$2:$A$5,Lookups!$D$2:$D$5),"CHECK CODE") -> EUR | X37: =VALUE(MID(Table3[[#This Row],[Unit Price]],2,50)) -> 1050 | Y37: =_xlfn.IFNA(_xlfn.XLOOKUP(Table3[[#This Row],[Country Code]],Lookups!$A$2:$A$5,Lookups!$E$2:$E$5),"") -> 1 | Z37: =Table3[[#This Row],[Unit Price (local)]]/Table3[[#This Row],[FX Rate (per EUR)]] -> 1050 | AA37: 200 | AB37: 0 | AC37: =ROUND(Table3[[#This Row],[Unit Price (EUR)]]*Table3[[#This Row],[Units Sold]],0) -> 210000 | AD37: =ROUND(Table3[[#This Row],[Gross Sales (EUR)]]*(1-Table3[[#This Row],[Discount (%)]]/100),0) -> 210000 | AE37: =_xlfn.IFNA(_xlfn.XLOOKUP(Table3[[#This Row],[Month]],Lookups!$N$2:$N$13,Lookups!$O$2:$O$13),"CHECK MONTH") -> 3 | AF37: =TEXT(Table3[[#This Row],[Month No]],"00")&" - "&Table3[[#This Row],[Month]] -> 03 - March | AG37: =_xlfn.IFNA(_xlfn.XLOOKUP(Table3[[#This Row],[Month]],Lookups!$N$2:$N$13,Lookups!$P$2:$P$13),"CHECK MONTH") -> Q1 | AH37: =Table3[[#This Row],[Gross Sales (EUR)]]-Table3[[#This Row],[Total Sales (EUR)]] -> 0 | AI37: =DATE(Lookups!$O$15,Table3[[#This Row],[Month No]],1) -> 45717
A38: 37 | B38: Sanya | C38: Joshi | D38: =TRIM(Table3[[#This Row],[Rep Last Name]])&", "&TRIM(Table3[[#This Row],[Rep First Name]]) -> Joshi, Sanya | E38: April | F38: Electric Unicycle | G38: 15 mph | H38: =IF(Table3[[#This Row],[Min Speed (original, incomplete)]]="",_xlfn.IFNA(_xlfn.XLOOKUP(Table3[[#This Row],[Product Type]],Lookups!$G$2:$G$4,Lookups!$H$2:$H$4),"CHECK PRODUCT"),Table3[[#This Row],[Min Speed (original, incomplete)]]) -> 15 mph | I38: 30 mph | J38: 30 miles | K38: =ROUND(VALUE(SUBSTITUTE(Table3[[#This Row],[Min Speed (mph)]]," mph",""))*Lookups!$L$2,0) -> 24 | L38: =ROUND(VALUE(SUBSTITUTE(Table3[[#This Row],[Speed]]," mph",""))*Lookups!$L$2,0) -> 48 | M38: =Table3[[#This Row],[Min Speed (km/h)]]&" – "&Table3[[#This Row],[Max Speed (km/h)]]&" km/h" -> 24 – 48 km/h | N38: =IF(ISNUMBER(SEARCH("mile",Table3[[#This Row],[Distance]])),ROUND(VALUE(SUBSTITUTE(Table3[[#This Row],[Distance]]," miles",""))*Lookups!$L$3,0),ROUND(VALUE(SUBSTITUTE(Table3[[#This Row],[Distance]]," meters",""))*Lookups!$L$4,0)) -> 48 | O38: 456 Brigade Road, Bengaluru, 560001 | P38: =TRIM(LEFT(Table3[[#This Row],[Shipping Address]],FIND(",",Table3[[#This Row],[Shipping Address]])-1)) -> 456 Brigade Road | Q38: =TRIM(MID(Table3[[#This Row],[Shipping Address]],FIND(",",Table3[[#This Row],[Shipping Address]])+1,FIND(",",Table3[[#This Row],[Shipping Address]],FIND(",",Table3[[#This Row],[Shipping Address]])+1)-FIND(",",Table3[[#This Row],[Shipping Address]])-1)) -> Bengaluru | R38: =TRIM(MID(Table3[[#This Row],[Shipping Address]],FIND(",",Table3[[#This Row],[Shipping Address]],FIND(",",Table3[[#This Row],[Shipping Address]])+1)+1,20)) -> 560001 | S38: IN | T38: =_xlfn.IFNA(_xlfn.XLOOKUP(Table3[[#This Row],[Country Code]],Lookups!$A$2:$A$5,Lookups!$B$2:$B$5),"CHECK CODE") -> India | U38: =_xlfn.IFNA(_xlfn.XLOOKUP(Table3[[#This Row],[Country Code]],Lookups!$A$2:$A$5,Lookups!$C$2:$C$5),"CHECK CODE") -> Asia | V38: ₹30,000 | W38: =_xlfn.IFNA(_xlfn.XLOOKUP(Table3[[#This Row],[Country Code]],Lookups!$A$2:$A$5,Lookups!$D$2:$D$5),"CHECK CODE") -> INR | X38: =VALUE(MID(Table3[[#This Row],[Unit Price]],2,50)) -> 30000 | Y38: =_xlfn.IFNA(_xlfn.XLOOKUP(Table3[[#This Row],[Country Code]],Lookups!$A$2:$A$5,Lookups!$E$2:$E$5),"") -> 109.882 | Z38: =Table3[[#This Row],[Unit Price (local)]]/Table3[[#This Row],[FX Rate (per EUR)]] -> 273.02015 | AA38: 200 | AB38: 0 | AC38: =ROUND(Table3[[#This Row],[Unit Price (EUR)]]*Table3[[#This Row],[Units Sold]],0) -> 54604 | AD38: =ROUND(Table3[[#This Row],[Gross Sales (EUR)]]*(1-Table3[[#This Row],[Discount (%)]]/100),0) -> 54604 | AE38: =_xlfn.IFNA(_xlfn.XLOOKUP(Table3[[#This Row],[Month]],Lookups!$N$2:$N$13,Lookups!$O$2:$O$13),"CHECK MONTH") -> 4 | AF38: =TEXT(Table3[[#This Row],[Month No]],"00")&" - "&Table3[[#This Row],[Month]] -> 04 - April | AG38: =_xlfn.IFNA(_xlfn.XLOOKUP(Table3[[#This Row],[Month]],Lookups!$N$2:$N$13,Lookups!$P$2:$P$13),"CHECK MONTH") -> Q2 | AH38: =Table3[[#This Row],[Gross Sales (EUR)]]-Table3[[#This Row],[Total Sales (EUR)]] -> 0 | AI38: =DATE(Lookups!$O$15,Table3[[#This Row],[Month No]],1) -> 45748
A39: 38 | B39: Sanya | C39: Joshi | D39: =TRIM(Table3[[#This Row],[Rep Last Name]])&", "&TRIM(Table3[[#This Row],[Rep First Name]]) -> Joshi, Sanya | E39: April | F39: Electric Scooter | G39: 20 mph | H39: =IF(Table3[[#This Row],[Min Speed (original, incomplete)]]="",_xlfn.IFNA(_xlfn.XLOOKUP(Table3[[#This Row],[Product Type]],Lookups!$G$2:$G$4,Lookups!$H$2:$H$4),"CHECK PRODUCT"),Table3[[#This Row],[Min Speed (original, incomplete)]]) -> 20 mph | I39: 35 mph | J39: 40 miles | K39: =ROUND(VALUE(SUBSTITUTE(Table3[[#This Row],[Min Speed (mph)]]," mph",""))*Lookups!$L$2,0) -> 32 | L39: =ROUND(VALUE(SUBSTITUTE(Table3[[#This Row],[Speed]]," mph",""))*Lookups!$L$2,0) -> 56 | M39: =Table3[[#This Row],[Min Speed (km/h)]]&" – "&Table3[[#This Row],[Max Speed (km/h)]]&" km/h" -> 32 – 56 km/h | N39: =IF(ISNUMBER(SEARCH("mile",Table3[[#This Row],[Distance]])),ROUND(VALUE(SUBSTITUTE(Table3[[#This Row],[Distance]]," miles",""))*Lookups!$L$3,0),ROUND(VALUE(SUBSTITUTE(Table3[[#This Row],[Distance]]," meters",""))*Lookups!$L$4,0)) -> 64 | O39: 457 Brigade Road, Bengaluru, 560001 | P39: =TRIM(LEFT(Table3[[#This Row],[Shipping Address]],FIND(",",Table3[[#This Row],[Shipping Address]])-1)) -> 457 Brigade Road | Q39: =TRIM(MID(Table3[[#This Row],[Shipping Address]],FIND(",",Table3[[#This Row],[Shipping Address]])+1,FIND(",",Table3[[#This Row],[Shipping Address]],FIND(",",Table3[[#This Row],[Shipping Address]])+1)-FIND(",",Table3[[#This Row],[Shipping Address]])-1)) -> Bengaluru | R39: =TRIM(MID(Table3[[#This Row],[Shipping Address]],FIND(",",Table3[[#This Row],[Shipping Address]],FIND(",",Table3[[#This Row],[Shipping Address]])+1)+1,20)) -> 560001 | S39: IN | T39: =_xlfn.IFNA(_xlfn.XLOOKUP(Table3[[#This Row],[Country Code]],Lookups!$A$2:$A$5,Lookups!$B$2:$B$5),"CHECK CODE") -> India | U39: =_xlfn.IFNA(_xlfn.XLOOKUP(Table3[[#This Row],[Country Code]],Lookups!$A$2:$A$5,Lookups!$C$2:$C$5),"CHECK CODE") -> Asia | V39: ₹25,000 | W39: =_xlfn.IFNA(_xlfn.XLOOKUP(Table3[[#This Row],[Country Code]],Lookups!$A$2:$A$5,Lookups!$D$2:$D$5),"CHECK CODE") -> INR | X39: =VALUE(MID(Table3[[#This Row],[Unit Price]],2,50)) -> 25000 | Y39: =_xlfn.IFNA(_xlfn.XLOOKUP(Table3[[#This Row],[Country Code]],Lookups!$A$2:$A$5,Lookups!$E$2:$E$5),"") -> 109.882 | Z39: =Table3[[#This Row],[Unit Price (local)]]/Table3[[#This Row],[FX Rate (per EUR)]] -> 227.51679 | AA39: 450 | AB39: 0 | AC39: =ROUND(Table3[[#This Row],[Unit Price (EUR)]]*Table3[[#This Row],[Units Sold]],0) -> 102383 | AD39: =ROUND(Table3[[#This Row],[Gross Sales (EUR)]]*(1-Table3[[#This Row],[Discount (%)]]/100),0) -> 102383 | AE39: =_xlfn.IFNA(_xlfn.XLOOKUP(Table3[[#This Row],[Month]],Lookups!$N$2:$N$13,Lookups!$O$2:$O$13),"CHECK MONTH") -> 4 | AF39: =TEXT(Table3[[#This Row],[Month No]],"00")&" - "&Table3[[#This Row],[Month]] -> 04 - April | AG39: =_xlfn.IFNA(_xlfn.XLOOKUP(Table3[[#This Row],[Month]],Lookups!$N$2:$N$13,Lookups!$P$2:$P$13),"CHECK MONTH") -> Q2 | AH39: =Table3[[#This Row],[Gross Sales (EUR)]]-Table3[[#This Row],[Total Sales (EUR)]] -> 0 | AI39: =DATE(Lookups!$O$15,Table3[[#This Row],[Month No]],1) -> 45748
A40: 39 | B40: Sanya | C40: Joshi | D40: =TRIM(Table3[[#This Row],[Rep Last Name]])&", "&TRIM(Table3[[#This Row],[Rep First Name]]) -> Joshi, Sanya | E40: April | F40: Electric Skateboard | G40: 18 mph | H40: =IF(Table3[[#This Row],[Min Speed (original, incomplete)]]="",_xlfn.IFNA(_xlfn.XLOOKUP(Table3[[#This Row],[Product Type]],Lookups!$G$2:$G$4,Lookups!$H$2:$H$4),"CHECK PRODUCT"),Table3[[#This Row],[Min Speed (original, incomplete)]]) -> 18 mph | I40: 28 mph | J40: 25 miles | K40: =ROUND(VALUE(SUBSTITUTE(Table3[[#This Row],[Min Speed (mph)]]," mph",""))*Lookups!$L$2,0) -> 29 | L40: =ROUND(VALUE(SUBSTITUTE(Table3[[#This Row],[Speed]]," mph",""))*Lookups!$L$2,0) -> 45 | M40: =Table3[[#This Row],[Min Speed (km/h)]]&" – "&Table3[[#This Row],[Max Speed (km/h)]]&" km/h" -> 29 – 45 km/h | N40: =IF(ISNUMBER(SEARCH("mile",Table3[[#This Row],[Distance]])),ROUND(VALUE(SUBSTITUTE(Table3[[#This Row],[Distance]]," miles",""))*Lookups!$L$3,0),ROUND(VALUE(SUBSTITUTE(Table3[[#This Row],[Distance]]," meters",""))*Lookups!$L$4,0)) -> 40 | O40: 458 Brigade Road, Bengaluru, 560001 | P40: =TRIM(LEFT(Table3[[#This Row],[Shipping Address]],FIND(",",Table3[[#This Row],[Shipping Address]])-1)) -> 458 Brigade Road | Q40: =TRIM(MID(Table3[[#This Row],[Shipping Address]],FIND(",",Table3[[#This Row],[Shipping Address]])+1,FIND(",",Table3[[#This Row],[Shipping Address]],FIND(",",Table3[[#This Row],[Shipping Address]])+1)-FIND(",",Table3[[#This Row],[Shipping Address]])-1)) -> Bengaluru | R40: =TRIM(MID(Table3[[#This Row],[Shipping Address]],FIND(",",Table3[[#This Row],[Shipping Address]],FIND(",",Table3[[#This Row],[Shipping Address]])+1)+1,20)) -> 560001 | S40: IN | T40: =_xlfn.IFNA(_xlfn.XLOOKUP(Table3[[#This Row],[Country Code]],Lookups!$A$2:$A$5,Lookups!$B$2:$B$5),"CHECK CODE") -> India | U40: =_xlfn.IFNA(_xlfn.XLOOKUP(Table3[[#This Row],[Country Code]],Lookups!$A$2:$A$5,Lookups!$C$2:$C$5),"CHECK CODE") -> Asia | V40: ₹22,000 | W40: =_xlfn.IFNA(_xlfn.XLOOKUP(Table3[[#This Row],[Country Code]],Lookups!$A$2:$A$5,Lookups!$D$2:$D$5),"CHECK CODE") -> INR | X40: =VALUE(MID(Table3[[#This Row],[Unit Price]],2,50)) -> 22000 | Y40: =_xlfn.IFNA(_xlfn.XLOOKUP(Table3[[#This Row],[Country Code]],Lookups!$A$2:$A$5,Lookups!$E$2:$E$5),"") -> 109.882 | Z40: =Table3[[#This Row],[Unit Price (local)]]/Table3[[#This Row],[FX Rate (per EUR)]] -> 200.21478 | AA40: 300 | AB40: 0 | AC40: =ROUND(Table3[[#This Row],[Unit Price (EUR)]]*Table3[[#This Row],[Units Sold]],0) -> 60064 | AD40: =ROUND(Table3[[#This Row],[Gross Sales (EUR)]]*(1-Table3[[#This Row],[Discount (%)]]/100),0) -> 60064 | AE40: =_xlfn.IFNA(_xlfn.XLOOKUP(Table3[[#This Row],[Month]],Lookups!$N$2:$N$13,Lookups!$O$2:$O$13),"CHECK MONTH") -> 4 | AF40: =TEXT(Table3[[#This Row],[Month No]],"00")&" - "&Table3[[#This Row],[Month]] -> 04 - April | AG40: =_xlfn.IFNA(_xlfn.XLOOKUP(Table3[[#This Row],[Month]],Lookups!$N$2:$N$13,Lookups!$P$2:$P$13),"CHECK MONTH") -> Q2 | AH40: =Table3[[#This Row],[Gross Sales (EUR)]]-Table3[[#This Row],[Total Sales (EUR)]] -> 0 | AI40: =DATE(Lookups!$O$15,Table3[[#This Row],[Month No]],1) -> 45748
A41: 40 | B41: Fang | C41: Liu | D41: =TRIM(Table3[[#This Row],[Rep Last Name]])&", "&TRIM(Table3[[#This Row],[Rep First Name]]) -> Liu, Fang | E41: April | F41: Electric Unicycle | H41: =IF(Table3[[#This Row],[Min Speed (original, incomplete)]]="",_xlfn.IFNA(_xlfn.XLOOKUP(Table3[[#This Row],[Product Type]],Lookups!$G$2:$G$4,Lookups!$H$2:$H$4),"CHECK PRODUCT"),Table3[[#This Row],[Min Speed (original, incomplete)]]) -> 15 mph | I41: 30 mph | J41: 30 miles | K41: =ROUND(VALUE(SUBSTITUTE(Table3[[#This Row],[Min Speed (mph)]]," mph",""))*Lookups!$L$2,0) -> 24 | L41: =ROUND(VALUE(SUBSTITUTE(Table3[[#This Row],[Speed]]," mph",""))*Lookups!$L$2,0) -> 48 | M41: =Table3[[#This Row],[Min Speed (km/h)]]&" – "&Table3[[#This Row],[Max Speed (km/h)]]&" km/h" -> 24 – 48 km/h | N41: =IF(ISNUMBER(SEARCH("mile",Table3[[#This Row],[Distance]])),ROUND(VALUE(SUBSTITUTE(Table3[[#This Row],[Distance]]," miles",""))*Lookups!$L$3,0),ROUND(VALUE(SUBSTITUTE(Table3[[#This Row],[Distance]]," meters",""))*Lookups!$L$4,0)) -> 48 | O41: 99 Nanjing Road, Shanghai, 200001 | P41: =TRIM(LEFT(Table3[[#This Row],[Shipping Address]],FIND(",",Table3[[#This Row],[Shipping Address]])-1)) -> 99 Nanjing Road | Q41: =TRIM(MID(Table3[[#This Row],[Shipping Address]],FIND(",",Table3[[#This Row],[Shipping Address]])+1,FIND(",",Table3[[#This Row],[Shipping Address]],FIND(",",Table3[[#This Row],[Shipping Address]])+1)-FIND(",",Table3[[#This Row],[Shipping Address]])-1)) -> Shanghai | R41: =TRIM(MID(Table3[[#This Row],[Shipping Address]],FIND(",",Table3[[#This Row],[Shipping Address]],FIND(",",Table3[[#This Row],[Shipping Address]])+1)+1,20)) -> 200001 | S41: CN | T41: =_xlfn.IFNA(_xlfn.XLOOKUP(Table3[[#This Row],[Country Code]],Lookups!$A$2:$A$5,Lookups!$B$2:$B$5),"CHECK CODE") -> China | U41: =_xlfn.IFNA(_xlfn.XLOOKUP(Table3[[#This Row],[Country Code]],Lookups!$A$2:$A$5,Lookups!$C$2:$C$5),"CHECK CODE") -> Asia | V41: ¥5,000 | W41: =_xlfn.IFNA(_xlfn.XLOOKUP(Table3[[#This Row],[Country Code]],Lookups!$A$2:$A$5,Lookups!$D$2:$D$5),"CHECK CODE") -> CNY | X41: =VALUE(MID(Table3[[#This Row],[Unit Price]],2,50)) -> 5000 | Y41: =_xlfn.IFNA(_xlfn.XLOOKUP(Table3[[#This Row],[Country Code]],Lookups!$A$2:$A$5,Lookups!$E$2:$E$5),"") -> 7.7255 | Z41: =Table3[[#This Row],[Unit Price (local)]]/Table3[[#This Row],[FX Rate (per EUR)]] -> 647.2073 | AA41: 700 | AB41: 0 | AC41: =ROUND(Table3[[#This Row],[Unit Price (EUR)]]*Table3[[#This Row],[Units Sold]],0) -> 453045 | AD41: =ROUND(Table3[[#This Row],[Gross Sales (EUR)]]*(1-Table3[[#This Row],[Discount (%)]]/100),0) -> 453045 | AE41: =_xlfn.IFNA(_xlfn.XLOOKUP(Table3[[#This Row],[Month]],Lookups!$N$2:$N$13,Lookups!$O$2:$O$13),"CHECK MONTH") -> 4 | AF41: =TEXT(Table3[[#This Row],[Month No]],"00")&" - "&Table3[[#This Row],[Month]] -> 04 - April | AG41: =_xlfn.IFNA(_xlfn.XLOOKUP(Table3[[#This Row],[Month]],Lookups!$N$2:$N$13,Lookups!$P$2:$P$13),"CHECK MONTH") -> Q2 | AH41: =Table3[[#This Row],[Gross Sales (EUR)]]-Table3[[#This Row],[Total Sales (EUR)]] -> 0 | AI41: =DATE(Lookups!$O$15,Table3[[#This Row],[Month No]],1) -> 45748
A42: 41 | B42: Fang | C42: Liu | D42: =TRIM(Table3[[#This Row],[Rep Last Name]])&", "&TRIM(Table3[[#This Row],[Rep First Name]]) -> Liu, Fang | E42: April | F42: Electric Scooter | G42: 20 mph | H42: =IF(Table3[[#This Row],[Min Speed (original, incomplete)]]="",_xlfn.IFNA(_xlfn.XLOOKUP(Table3[[#This Row],[Product Type]],Lookups!$G$2:$G$4,Lookups!$H$2:$H$4),"CHECK PRODUCT"),Table3[[#This Row],[Min Speed (original, incomplete)]]) -> 20 mph | I42: 35 mph | J42: 40 miles | K42: =ROUND(VALUE(SUBSTITUTE(Table3[[#This Row],[Min Speed (mph)]]," mph",""))*Lookups!$L$2,0) -> 32 | L42: =ROUND(VALUE(SUBSTITUTE(Table3[[#This Row],[Speed]]," mph",""))*Lookups!$L$2,0) -> 56 | M42: =Table3[[#This Row],[Min Speed (km/h)]]&" – "&Table3[[#This Row],[Max Speed (km/h)]]&" km/h" -> 32 – 56 km/h | N42: =IF(ISNUMBER(SEARCH("mile",Table3[[#This Row],[Distance]])),ROUND(VALUE(SUBSTITUTE(Table3[[#This Row],[Distance]]," miles",""))*Lookups!$L$3,0),ROUND(VALUE(SUBSTITUTE(Table3[[#This Row],[Distance]]," meters",""))*Lookups!$L$4,0)) -> 64 | O42: 100 Nanjing Road, Shanghai, 200001 | P42: =TRIM(LEFT(Table3[[#This Row],[Shipping Address]],FIND(",",Table3[[#This Row],[Shipping Address]])-1)) -> 100 Nanjing Road | Q42: =TRIM(MID(Table3[[#This Row],[Shipping Address]],FIND(",",Table3[[#This Row],[Shipping Address]])+1,FIND(",",Table3[[#This Row],[Shipping Address]],FIND(",",Table3[[#This Row],[Shipping Address]])+1)-FIND(",",Table3[[#This Row],[Shipping Address]])-1)) -> Shanghai | R42: =TRIM(MID(Table3[[#This Row],[Shipping Address]],FIND(",",Table3[[#This Row],[Shipping Address]],FIND(",",Table3[[#This Row],[Shipping Address]])+1)+1,20)) -> 200001 | S42: CN | T42: =_xlfn.IFNA(_xlfn.XLOOKUP(Table3[[#This Row],[Country Code]],Lookups!$A$2:$A$5,Lookups!$B$2:$B$5),"CHECK CODE") -> China | U42: =_xlfn.IFNA(_xlfn.XLOOKUP(Table3[[#This Row],[Country Code]],Lookups!$A$2:$A$5,Lookups!$C$2:$C$5),"CHECK CODE") -> Asia | V42: ¥3,500 | W42: =_xlfn.IFNA(_xlfn.XLOOKUP(Table3[[#This Row],[Country Code]],Lookups!$A$2:$A$5,Lookups!$D$2:$D$5),"CHECK CODE") -> CNY | X42: =VALUE(MID(Table3[[#This Row],[Unit Price]],2,50)) -> 3500 | Y42: =_xlfn.IFNA(_xlfn.XLOOKUP(Table3[[#This Row],[Country Code]],Lookups!$A$2:$A$5,Lookups!$E$2:$E$5),"") -> 7.7255 | Z42: =Table3[[#This Row],[Unit Price (local)]]/Table3[[#This Row],[FX Rate (per EUR)]] -> 453.04511 | AA42: 1600 | AB42: 0 | AC42: =ROUND(Table3[[#This Row],[Unit Price (EUR)]]*Table3[[#This Row],[Units Sold]],0) -> 724872 | AD42: =ROUND(Table3[[#This Row],[Gross Sales (EUR)]]*(1-Table3[[#This Row],[Discount (%)]]/100),0) -> 724872 | AE42: =_xlfn.IFNA(_xlfn.XLOOKUP(Table3[[#This Row],[Month]],Lookups!$N$2:$N$13,Lookups!$O$2:$O$13),"CHECK MONTH") -> 4 | AF42: =TEXT(Table3[[#This Row],[Month No]],"00")&" - "&Table3[[#This Row],[Month]] -> 04 - April | AG42: =_xlfn.IFNA(_xlfn.XLOOKUP(Table3[[#This Row],[Month]],Lookups!$N$2:$N$13,Lookups!$P$2:$P$13),"CHECK MONTH") -> Q2 | AH42: =Table3[[#This Row],[Gross Sales (EUR)]]-Table3[[#This Row],[Total Sales (EUR)]] -> 0 | AI42: =DATE(Lookups!$O$15,Table3[[#This Row],[Month No]],1) -> 45748
A43: 42 | B43: Fang | C43: Liu | D43: =TRIM(Table3[[#This Row],[Rep Last Name]])&", "&TRIM(Table3[[#This Row],[Rep First Name]]) -> Liu, Fang | E43: April | F43: Electric Skateboard | G43: 18 mph | H43: =IF(Table3[[#This Row],[Min Speed (original, incomplete)]]="",_xlfn.IFNA(_xlfn.XLOOKUP(Table3[[#This Row],[Product Type]],Lookups!$G$2:$G$4,Lookups!$H$2:$H$4),"CHECK PRODUCT"),Table3[[#This Row],[Min Speed (original, incomplete)]]) -> 18 mph | I43: 28 mph | J43: 25 miles | K43: =ROUND(VALUE(SUBSTITUTE(Table3[[#This Row],[Min Speed (mph)]]," mph",""))*Lookups!$L$2,0) -> 29 | L43: =ROUND(VALUE(SUBSTITUTE(Table3[[#This Row],[Speed]]," mph",""))*Lookups!$L$2,0) -> 45 | M43: =Table3[[#This Row],[Min Speed (km/h)]]&" – "&Table3[[#This Row],[Max Speed (km/h)]]&" km/h" -> 29 – 45 km/h | N43: =IF(ISNUMBER(SEARCH("mile",Table3[[#This Row],[Distance]])),ROUND(VALUE(SUBSTITUTE(Table3[[#This Row],[Distance]]," miles",""))*Lookups!$L$3,0),ROUND(VALUE(SUBSTITUTE(Table3[[#This Row],[Distance]]," meters",""))*Lookups!$L$4,0)) -> 40 | O43: 101 Nanjing Road, Shanghai, 200001 | P43: =TRIM(LEFT(Table3[[#This Row],[Shipping Address]],FIND(",",Table3[[#This Row],[Shipping Address]])-1)) -> 101 Nanjing Road | Q43: =TRIM(MID(Table3[[#This Row],[Shipping Address]],FIND(",",Table3[[#This Row],[Shipping Address]])+1,FIND(",",Table3[[#This Row],[Shipping Address]],FIND(",",Table3[[#This Row],[Shipping Address]])+1)-FIND(",",Table3[[#This Row],[Shipping Address]])-1)) -> Shanghai | R43: =TRIM(MID(Table3[[#This Row],[Shipping Address]],FIND(",",Table3[[#This Row],[Shipping Address]],FIND(",",Table3[[#This Row],[Shipping Address]])+1)+1,20)) -> 200001 | S43: CN | T43: =_xlfn.IFNA(_xlfn.XLOOKUP(Table3[[#This Row],[Country Code]],Lookups!$A$2:$A$5,Lookups!$B$2:$B$5),"CHECK CODE") -> China | U43: =_xlfn.IFNA(_xlfn.XLOOKUP(Table3[[#This Row],[Country Code]],Lookups!$A$2:$A$5,Lookups!$C$2:$C$5),"CHECK CODE") -> Asia | V43: ¥4,200 | W43: =_xlfn.IFNA(_xlfn.XLOOKUP(Table3[[#This Row],[Country Code]],Lookups!$A$2:$A$5,Lookups!$D$2:$D$5),"CHECK CODE") -> CNY | X43: =VALUE(MID(Table3[[#This Row],[Unit Price]],2,50)) -> 4200 | Y43: =_xlfn.IFNA(_xlfn.XLOOKUP(Table3[[#This Row],[Country Code]],Lookups!$A$2:$A$5,Lookups!$E$2:$E$5),"") -> 7.7255 | Z43: =Table3[[#This Row],[Unit Price (local)]]/Table3[[#This Row],[FX Rate (per EUR)]] -> 543.65413 | AA43: 1000 | AB43: 0 | AC43: =ROUND(Table3[[#This Row],[Unit Price (EUR)]]*Table3[[#This Row],[Units Sold]],0) -> 543654 | AD43: =ROUND(Table3[[#This Row],[Gross Sales (EUR)]]*(1-Table3[[#This Row],[Discount (%)]]/100),0) -> 543654 | AE43: =_xlfn.IFNA(_xlfn.XLOOKUP(Table3[[#This Row],[Month]],Lookups!$N$2:$N$13,Lookups!$O$2:$O$13),"CHECK MONTH") -> 4 | AF43: =TEXT(Table3[[#This Row],[Month No]],"00")&" - "&Table3[[#This Row],[Month]] -> 04 - April | AG43: =_xlfn.IFNA(_xlfn.XLOOKUP(Table3[[#This Row],[Month]],Lookups!$N$2:$N$13,Lookups!$P$2:$P$13),"CHECK MONTH") -> Q2 | AH43: =Table3[[#This Row],[Gross Sales (EUR)]]-Table3[[#This Row],[Total Sales (EUR)]] -> 0 | AI43: =DATE(Lookups!$O$15,Table3[[#This Row],[Month No]],1) -> 45748
A44: 43 | B44: Jonas | C44: Fischer | D44: =TRIM(Table3[[#This Row],[Rep Last Name]])&", "&TRIM(Table3[[#This Row],[Rep First Name]]) -> Fischer, Jonas | E44: April | F44: Electric Unicycle | G44: 15 mph | H44: =IF(Table3[[#This Row],[Min Speed (original, incomplete)]]="",_xlfn.IFNA(_xlfn.XLOOKUP(Table3[[#This Row],[Product Type]],Lookups!$G$2:$G$4,Lookups!$H$2:$H$4),"CHECK PRODUCT"),Table3[[#This Row],[Min Speed (original, incomplete)]]) -> 15 mph | I44: 30 mph | J44: 48,280 meters | K44: =ROUND(VALUE(SUBSTITUTE(Table3[[#This Row],[Min Speed (mph)]]," mph",""))*Lookups!$L$2,0) -> 24 | L44: =ROUND(VALUE(SUBSTITUTE(Table3[[#This Row],[Speed]]," mph",""))*Lookups!$L$2,0) -> 48 | M44: =Table3[[#This Row],[Min Speed (km/h)]]&" – "&Table3[[#This Row],[Max Speed (km/h)]]&" km/h" -> 24 – 48 km/h | N44: =IF(ISNUMBER(SEARCH("mile",Table3[[#This Row],[Distance]])),ROUND(VALUE(SUBSTITUTE(Table3[[#This Row],[Distance]]," miles",""))*Lookups!$L$3,0),ROUND(VALUE(SUBSTITUTE(Table3[[#This Row],[Distance]]," meters",""))*Lookups!$L$4,0)) -> 48 | O44: 303 Ringstraße, Hamburg, 20095 | P44: =TRIM(LEFT(Table3[[#This Row],[Shipping Address]],FIND(",",Table3[[#This Row],[Shipping Address]])-1)) -> 303 Ringstraße | Q44: =TRIM(MID(Table3[[#This Row],[Shipping Address]],FIND(",",Table3[[#This Row],[Shipping Address]])+1,FIND(",",Table3[[#This Row],[Shipping Address]],FIND(",",Table3[[#This Row],[Shipping Address]])+1)-FIND(",",Table3[[#This Row],[Shipping Address]])-1)) -> Hamburg | R44: =TRIM(MID(Table3[[#This Row],[Shipping Address]],FIND(",",Table3[[#This Row],[Shipping Address]],FIND(",",Table3[[#This Row],[Shipping Address]])+1)+1,20)) -> 20095 | S44: DE | T44: =_xlfn.IFNA(_xlfn.XLOOKUP(Table3[[#This Row],[Country Code]],Lookups!$A$2:$A$5,Lookups!$B$2:$B$5),"CHECK CODE") -> Germany | U44: =_xlfn.IFNA(_xlfn.XLOOKUP(Table3[[#This Row],[Country Code]],Lookups!$A$2:$A$5,Lookups!$C$2:$C$5),"CHECK CODE") -> Europe | V44: €1000 | W44: =_xlfn.IFNA(_xlfn.XLOOKUP(Table3[[#This Row],[Country Code]],Lookups!$A$2:$A$5,Lookups!$D$2:$D$5),"CHECK CODE") -> EUR | X44: =VALUE(MID(Table3[[#This Row],[Unit Price]],2,50)) -> 1000 | Y44: =_xlfn.IFNA(_xlfn.XLOOKUP(Table3[[#This Row],[Country Code]],Lookups!$A$2:$A$5,Lookups!$E$2:$E$5),"") -> 1 | Z44: =Table3[[#This Row],[Unit Price (local)]]/Table3[[#This Row],[FX Rate (per EUR)]] -> 1000 | AA44: 160 | AB44: 0 | AC44: =ROUND(Table3[[#This Row],[Unit Price (EUR)]]*Table3[[#This Row],[Units Sold]],0) -> 160000 | AD44: =ROUND(Table3[[#This Row],[Gross Sales (EUR)]]*(1-Table3[[#This Row],[Discount (%)]]/100),0) -> 160000 | AE44: =_xlfn.IFNA(_xlfn.XLOOKUP(Table3[[#This Row],[Month]],Lookups!$N$2:$N$13,Lookups!$O$2:$O$13),"CHECK MONTH") -> 4 | AF44: =TEXT(Table3[[#This Row],[Month No]],"00")&" - "&Table3[[#This Row],[Month]] -> 04 - April | AG44: =_xlfn.IFNA(_xlfn.XLOOKUP(Table3[[#This Row],[Month]],Lookups!$N$2:$N$13,Lookups!$P$2:$P$13),"CHECK MONTH") -> Q2 | AH44: =Table3[[#This Row],[Gross Sales (EUR)]]-Table3[[#This Row],[Total Sales (EUR)]] -> 0 | AI44: =DATE(Lookups!$O$15,Table3[[#This Row],[Month No]],1) -> 45748
A45: 44 | B45: Jonas | C45: Fischer | D45: =TRIM(Table3[[#This Row],[Rep Last Name]])&", "&TRIM(Table3[[#This Row],[Rep First Name]]) -> Fischer, Jonas | E45: April | F45: Electric Scooter | G45: 20 mph | H45: =IF(Table3[[#This Row],[Min Speed (original, incomplete)]]="",_xlfn.IFNA(_xlfn.XLOOKUP(Table3[[#This Row],[Product Type]],Lookups!$G$2:$G$4,Lookups!$H$2:$H$4),"CHECK PRODUCT"),Table3[[#This Row],[Min Speed (original, incomplete)]]) -> 20 mph | I45: 35 mph | J45: 40 miles | K45: =ROUND(VALUE(SUBSTITUTE(Table3[[#This Row],[Min Speed (mph)]]," mph",""))*Lookups!$L$2,0) -> 32 | L45: =ROUND(VALUE(SUBSTITUTE(Table3[[#This Row],[Speed]]," mph",""))*Lookups!$L$2,0) -> 56 | M45: =Table3[[#This Row],[Min Speed (km/h)]]&" – "&Table3[[#This Row],[Max Speed (km/h)]]&" km/h" -> 32 – 56 km/h | N45: =IF(ISNUMBER(SEARCH("mile",Table3[[#This Row],[Distance]])),ROUND(VALUE(SUBSTITUTE(Table3[[#This Row],[Distance]]," miles",""))*Lookups!$L$3,0),ROUND(VALUE(SUBSTITUTE(Table3[[#This Row],[Distance]]," meters",""))*Lookups!$L$4,0)) -> 64 | O45: 304 Ringstraße, Hamburg, 20095 | P45: =TRIM(LEFT(Table3[[#This Row],[Shipping Address]],FIND(",",Table3[[#This Row],[Shipping Address]])-1)) -> 304 Ringstraße | Q45: =TRIM(MID(Table3[[#This Row],[Shipping Address]],FIND(",",Table3[[#This Row],[Shipping Address]])+1,FIND(",",Table3[[#This Row],[Shipping Address]],FIND(",",Table3[[#This Row],[Shipping Address]])+1)-FIND(",",Table3[[#This Row],[Shipping Address]])-1)) -> Hamburg | R45: =TRIM(MID(Table3[[#This Row],[Shipping Address]],FIND(",",Table3[[#This Row],[Shipping Address]],FIND(",",Table3[[#This Row],[Shipping Address]])+1)+1,20)) -> 20095 | S45: DE | T45: =_xlfn.IFNA(_xlfn.XLOOKUP(Table3[[#This Row],[Country Code]],Lookups!$A$2:$A$5,Lookups!$B$2:$B$5),"CHECK CODE") -> Germany | U45: =_xlfn.IFNA(_xlfn.XLOOKUP(Table3[[#This Row],[Country Code]],Lookups!$A$2:$A$5,Lookups!$C$2:$C$5),"CHECK CODE") -> Europe | V45: €800 | W45: =_xlfn.IFNA(_xlfn.XLOOKUP(Table3[[#This Row],[Country Code]],Lookups!$A$2:$A$5,Lookups!$D$2:$D$5),"CHECK CODE") -> EUR | X45: =VALUE(MID(Table3[[#This Row],[Unit Price]],2,50)) -> 800 | Y45: =_xlfn.IFNA(_xlfn.XLOOKUP(Table3[[#This Row],[Country Code]],Lookups!$A$2:$A$5,Lookups!$E$2:$E$5),"") -> 1 | Z45: =Table3[[#This Row],[Unit Price (local)]]/Table3[[#This Row],[FX Rate (per EUR)]] -> 800 | AA45: 280 | AB45: 0 | AC45: =ROUND(Table3[[#This Row],[Unit Price (EUR)]]*Table3[[#This Row],[Units Sold]],0) -> 224000 | AD45: =ROUND(Table3[[#This Row],[Gross Sales (EUR)]]*(1-Table3[[#This Row],[Discount (%)]]/100),0) -> 224000 | AE45: =_xlfn.IFNA(_xlfn.XLOOKUP(Table3[[#This Row],[Month]],Lookups!$N$2:$N$13,Lookups!$O$2:$O$13),"CHECK MONTH") -> 4 | AF45: =TEXT(Table3[[#This Row],[Month No]],"00")&" - "&Table3[[#This Row],[Month]] -> 04 - April | AG45: =_xlfn.IFNA(_xlfn.XLOOKUP(Table3[[#This Row],[Month]],Lookups!$N$2:$N$13,Lookups!$P$2:$P$13),"CHECK MONTH") -> Q2 | AH45: =Table3[[#This Row],[Gross Sales (EUR)]]-Table3[[#This Row],[Total Sales (EUR)]] -> 0 | AI45: =DATE(Lookups!$O$15,Table3[[#This Row],[Month No]],1) -> 45748
A46: 45 | B46: Jonas | C46: Fischer | D46: =TRIM(Table3[[#This Row],[Rep Last Name]])&", "&TRIM(Table3[[#This Row],[Rep First Name]]) -> Fischer, Jonas | E46: April | F46: Electric Skateboard | G46: 18 mph | H46: =IF(Table3[[#This Row],[Min Speed (original, incomplete)]]="",_xlfn.IFNA(_xlfn.XLOOKUP(Table3[[#This Row],[Product Type]],Lookups!$G$2:$G$4,Lookups!$H$2:$H$4),"CHECK PRODUCT"),Table3[[#This Row],[Min Speed (original, incomplete)]]) -> 18 mph | I46: 28 mph | J46: 25 miles | K46: =ROUND(VALUE(SUBSTITUTE(Table3[[#This Row],[Min Speed (mph)]]," mph",""))*Lookups!$L$2,0) -> 29 | L46: =ROUND(VALUE(SUBSTITUTE(Table3[[#This Row],[Speed]]," mph",""))*Lookups!$L$2,0) -> 45 | M46: =Table3[[#This Row],[Min Speed (km/h)]]&" – "&Table3[[#This Row],[Max Speed (km/h)]]&" km/h" -> 29 – 45 km/h | N46: =IF(ISNUMBER(SEARCH("mile",Table3[[#This Row],[Distance]])),ROUND(VALUE(SUBSTITUTE(Table3[[#This Row],[Distance]]," miles",""))*Lookups!$L$3,0),ROUND(VALUE(SUBSTITUTE(Table3[[#This Row],[Distance]]," meters",""))*Lookups!$L$4,0)) -> 40 | O46: 305 Ringstraße, Hamburg, 20095 | P46: =TRIM(LEFT(Table3[[#This Row],[Shipping Address]],FIND(",",Table3[[#This Row],[Shipping Address]])-1)) -> 305 Ringstraße | Q46: =TRIM(MID(Table3[[#This Row],[Shipping Address]],FIND(",",Table3[[#This Row],[Shipping Address]])+1,FIND(",",Table3[[#This Row],[Shipping Address]],FIND(",",Table3[[#This Row],[Shipping Address]])+1)-FIND(",",Table3[[#This Row],[Shipping Address]])-1)) -> Hamburg | R46: =TRIM(MID(Table3[[#This Row],[Shipping Address]],FIND(",",Table3[[#This Row],[Shipping Address]],FIND(",",Table3[[#This Row],[Shipping Address]])+1)+1,20)) -> 20095 | S46: DE | T46: =_xlfn.IFNA(_xlfn.XLOOKUP(Table3[[#This Row],[Country Code]],Lookups!$A$2:$A$5,Lookups!$B$2:$B$5),"CHECK CODE") -> Germany | U46: =_xlfn.IFNA(_xlfn.XLOOKUP(Table3[[#This Row],[Country Code]],Lookups!$A$2:$A$5,Lookups!$C$2:$C$5),"CHECK CODE") -> Europe | V46: €950 | W46: =_xlfn.IFNA(_xlfn.XLOOKUP(Table3[[#This Row],[Country Code]],Lookups!$A$2:$A$5,Lookups!$D$2:$D$5),"CHECK CODE") -> EUR | X46: =VALUE(MID(Table3[[#This Row],[Unit Price]],2,50)) -> 950 | Y46: =_xlfn.IFNA(_xlfn.XLOOKUP(Table3[[#This Row],[Country Code]],Lookups!$A$2:$A$5,Lookups!$E$2:$E$5),"") -> 1 | Z46: =Table3[[#This Row],[Unit Price (local)]]/Table3[[#This Row],[FX Rate (per EUR)]] -> 950 | AA46: 200 | AB46: 0 | AC46: =ROUND(Table3[[#This Row],[Unit Price (EUR)]]*Table3[[#This Row],[Units Sold]],0) -> 190000 | AD46: =ROUND(Table3[[#This Row],[Gross Sales (EUR)]]*(1-Table3[[#This Row],[Discount (%)]]/100),0) -> 190000 | AE46: =_xlfn.IFNA(_xlfn.XLOOKUP(Table3[[#This Row],[Month]],Lookups!$N$2:$N$13,Lookups!$O$2:$O$13),"CHECK MONTH") -> 4 | AF46: =TEXT(Table3[[#This Row],[Month No]],"00")&" - "&Table3[[#This Row],[Month]] -> 04 - April | AG46: =_xlfn.IFNA(_xlfn.XLOOKUP(Table3[[#This Row],[Month]],Lookups!$N$2:$N$13,Lookups!$P$2:$P$13),"CHECK MONTH") -> Q2 | AH46: =Table3[[#This Row],[Gross Sales (EUR)]]-Table3[[#This Row],[Total Sales (EUR)]] -> 0 | AI46: =DATE(Lookups!$O$15,Table3[[#This Row],[Month No]],1) -> 45748
A47: 46 | B47: Théo | C47: Bernard | D47: =TRIM(Table3[[#This Row],[Rep Last Name]])&", "&TRIM(Table3[[#This Row],[Rep First Name]]) -> Bernard, Théo | E47: April | F47: Electric Unicycle | G47: 15 mph | H47: =IF(Table3[[#This Row],[Min Speed (original, incomplete)]]="",_xlfn.IFNA(_xlfn.XLOOKUP(Table3[[#This Row],[Product Type]],Lookups!$G$2:$G$4,Lookups!$H$2:$H$4),"CHECK PRODUCT"),Table3[[#This Row],[Min Speed (original, incomplete)]]) -> 15 mph | I47: 30 mph | J47: 30 miles | K47: =ROUND(VALUE(SUBSTITUTE(Table3[[#This Row],[Min Speed (mph)]]," mph",""))*Lookups!$L$2,0) -> 24 | L47: =ROUND(VALUE(SUBSTITUTE(Table3[[#This Row],[Speed]]," mph",""))*Lookups!$L$2,0) -> 48 | M47: =Table3[[#This Row],[Min Speed (km/h)]]&" – "&Table3[[#This Row],[Max Speed (km/h)]]&" km/h" -> 24 – 48 km/h | N47: =IF(ISNUMBER(SEARCH("mile",Table3[[#This Row],[Distance]])),ROUND(VALUE(SUBSTITUTE(Table3[[#This Row],[Distance]]," miles",""))*Lookups!$L$3,0),ROUND(VALUE(SUBSTITUTE(Table3[[#This Row],[Distance]]," meters",""))*Lookups!$L$4,0)) -> 48 | O47: 56 Boulevard Saint-Germain, Paris, 75005 | P47: =TRIM(LEFT(Table3[[#This Row],[Shipping Address]],FIND(",",Table3[[#This Row],[Shipping Address]])-1)) -> 56 Boulevard Saint-Germain | Q47: =TRIM(MID(Table3[[#This Row],[Shipping Address]],FIND(",",Table3[[#This Row],[Shipping Address]])+1,FIND(",",Table3[[#This Row],[Shipping Address]],FIND(",",Table3[[#This Row],[Shipping Address]])+1)-FIND(",",Table3[[#This Row],[Shipping Address]])-1)) -> Paris | R47: =TRIM(MID(Table3[[#This Row],[Shipping Address]],FIND(",",Table3[[#This Row],[Shipping Address]],FIND(",",Table3[[#This Row],[Shipping Address]])+1)+1,20)) -> 75005 | S47: FR | T47: =_xlfn.IFNA(_xlfn.XLOOKUP(Table3[[#This Row],[Country Code]],Lookups!$A$2:$A$5,Lookups!$B$2:$B$5),"CHECK CODE") -> France | U47: =_xlfn.IFNA(_xlfn.XLOOKUP(Table3[[#This Row],[Country Code]],Lookups!$A$2:$A$5,Lookups!$C$2:$C$5),"CHECK CODE") -> Europe | V47: €1100 | W47: =_xlfn.IFNA(_xlfn.XLOOKUP(Table3[[#This Row],[Country Code]],Lookups!$A$2:$A$5,Lookups!$D$2:$D$5),"CHECK CODE") -> EUR | X47: =VALUE(MID(Table3[[#This Row],[Unit Price]],2,50)) -> 1100 | Y47: =_xlfn.IFNA(_xlfn.XLOOKUP(Table3[[#This Row],[Country Code]],Lookups!$A$2:$A$5,Lookups!$E$2:$E$5),"") -> 1 | Z47: =Table3[[#This Row],[Unit Price (local)]]/Table3[[#This Row],[FX Rate (per EUR)]] -> 1100 | AA47: 130 | AB47: 0 | AC47: =ROUND(Table3[[#This Row],[Unit Price (EUR)]]*Table3[[#This Row],[Units Sold]],0) -> 143000 | AD47: =ROUND(Table3[[#This Row],[Gross Sales (EUR)]]*(1-Table3[[#This Row],[Discount (%)]]/100),0) -> 143000 | AE47: =_xlfn.IFNA(_xlfn.XLOOKUP(Table3[[#This Row],[Month]],Lookups!$N$2:$N$13,Lookups!$O$2:$O$13),"CHECK MONTH") -> 4 | AF47: =TEXT(Table3[[#This Row],[Month No]],"00")&" - "&Table3[[#This Row],[Month]] -> 04 - April | AG47: =_xlfn.IFNA(_xlfn.XLOOKUP(Table3[[#This Row],[Month]],Lookups!$N$2:$N$13,Lookups!$P$2:$P$13),"CHECK MONTH") -> Q2 | AH47: =Table3[[#This Row],[Gross Sales (EUR)]]-Table3[[#This Row],[Total Sales (EUR)]] -> 0 | AI47: =DATE(Lookups!$O$15,Table3[[#This Row],[Month No]],1) -> 45748
A48: 47 | B48: Théo | C48: Bernard | D48: =TRIM(Table3[[#This Row],[Rep Last Name]])&", "&TRIM(Table3[[#This Row],[Rep First Name]]) -> Bernard, Théo | E48: April | F48: Electric Scooter | G48: 20 mph | H48: =IF(Table3[[#This Row],[Min Speed (original, incomplete)]]="",_xlfn.IFNA(_xlfn.XLOOKUP(Table3[[#This Row],[Product Type]],Lookups!$G$2:$G$4,Lookups!$H$2:$H$4),"CHECK PRODUCT"),Table3[[#This Row],[Min Speed (original, incomplete)]]) -> 20 mph | I48: 35 mph | J48: 40 miles | K48: =ROUND(VALUE(SUBSTITUTE(Table3[[#This Row],[Min Speed (mph)]]," mph",""))*Lookups!$L$2,0) -> 32 | L48: =ROUND(VALUE(SUBSTITUTE(Table3[[#This Row],[Speed]]," mph",""))*Lookups!$L$2,0) -> 56 | M48: =Table3[[#This Row],[Min Speed (km/h)]]&" – "&Table3[[#This Row],[Max Speed (km/h)]]&" km/h" -> 32 – 56 km/h | N48: =IF(ISNUMBER(SEARCH("mile",Table3[[#This Row],[Distance]])),ROUND(VALUE(SUBSTITUTE(Table3[[#This Row],[Distance]]," miles",""))*Lookups!$L$3,0),ROUND(VALUE(SUBSTITUTE(Table3[[#This Row],[Distance]]," meters",""))*Lookups!$L$4,0)) -> 64 | O48: 57 Boulevard Saint-Germain, Paris, 75005 | P48: =TRIM(LEFT(Table3[[#This Row],[Shipping Address]],FIND(",",Table3[[#This Row],[Shipping Address]])-1)) -> 57 Boulevard Saint-Germain | Q48: =TRIM(MID(Table3[[#This Row],[Shipping Address]],FIND(",",Table3[[#This Row],[Shipping Address]])+1,FIND(",",Table3[[#This Row],[Shipping Address]],FIND(",",Table3[[#This Row],[Shipping Address]])+1)-FIND(",",Table3[[#This Row],[Shipping Address]])-1)) -> Paris | R48: =TRIM(MID(Table3[[#This Row],[Shipping Address]],FIND(",",Table3[[#This Row],[Shipping Address]],FIND(",",Table3[[#This Row],[Shipping Address]])+1)+1,20)) -> 75005 | S48: FR | T48: =_xlfn.IFNA(_xlfn.XLOOKUP(Table3[[#This Row],[Country Code]],Lookups!$A$2:$A$5,Lookups!$B$2:$B$5),"CHECK CODE") -> France | U48: =_xlfn.IFNA(_xlfn.XLOOKUP(Table3[[#This Row],[Country Code]],Lookups!$A$2:$A$5,Lookups!$C$2:$C$5),"CHECK CODE") -> Europe | V48: €900 | W48: =_xlfn.IFNA(_xlfn.XLOOKUP(Table3[[#This Row],[Country Code]],Lookups!$A$2:$A$5,Lookups!$D$2:$D$5),"CHECK CODE") -> EUR | X48: =VALUE(MID(Table3[[#This Row],[Unit Price]],2,50)) -> 900 | Y48: =_xlfn.IFNA(_xlfn.XLOOKUP(Table3[[#This Row],[Country Code]],Lookups!$A$2:$A$5,Lookups!$E$2:$E$5),"") -> 1 | Z48: =Table3[[#This Row],[Unit Price (local)]]/Table3[[#This Row],[FX Rate (per EUR)]] -> 900 | AA48: 300 | AB48: 0 | AC48: =ROUND(Table3[[#This Row],[Unit Price (EUR)]]*Table3[[#This Row],[Units Sold]],0) -> 270000 | AD48: =ROUND(Table3[[#This Row],[Gross Sales (EUR)]]*(1-Table3[[#This Row],[Discount (%)]]/100),0) -> 270000 | AE48: =_xlfn.IFNA(_xlfn.XLOOKUP(Table3[[#This Row],[Month]],Lookups!$N$2:$N$13,Lookups!$O$2:$O$13),"CHECK MONTH") -> 4 | AF48: =TEXT(Table3[[#This Row],[Month No]],"00")&" - "&Table3[[#This Row],[Month]] -> 04 - April | AG48: =_xlfn.IFNA(_xlfn.XLOOKUP(Table3[[#This Row],[Month]],Lookups!$N$2:$N$13,Lookups!$P$2:$P$13),"CHECK MONTH") -> Q2 | AH48: =Table3[[#This Row],[Gross Sales (EUR)]]-Table3[[#This Row],[Total Sales (EUR)]] -> 0 | AI48: =DATE(Lookups!$O$15,Table3[[#This Row],[Month No]],1) -> 45748
A49: 48 | B49: Théo | C49: Bernard | D49: =TRIM(Table3[[#This Row],[Rep Last Name]])&", "&TRIM(Table3[[#This Row],[Rep First Name]]) -> Bernard, Théo | E49: April | F49: Electric Skateboard | H49: =IF(Table3[[#This Row],[Min Speed (original, incomplete)]]="",_xlfn.IFNA(_xlfn.XLOOKUP(Table3[[#This Row],[Product Type]],Lookups!$G$2:$G$4,Lookups!$H$2:$H$4),"CHECK PRODUCT"),Table3[[#This Row],[Min Speed (original, incomplete)]]) -> 18 mph | I49: 28 mph | J49: 40,230 meters | K49: =ROUND(VALUE(SUBSTITUTE(Table3[[#This Row],[Min Speed (mph)]]," mph",""))*Lookups!$L$2,0) -> 29 | L49: =ROUND(VALUE(SUBSTITUTE(Table3[[#This Row],[Speed]]," mph",""))*Lookups!$L$2,0) -> 45 | M49: =Table3[[#This Row],[Min Speed (km/h)]]&" – "&Table3[[#This Row],[Max Speed (km/h)]]&" km/h" -> 29 – 45 km/h | N49: =IF(ISNUMBER(SEARCH("mile",Table3[[#This Row],[Distance]])),ROUND(VALUE(SUBSTITUTE(Table3[[#This Row],[Distance]]," miles",""))*Lookups!$L$3,0),ROUND(VALUE(SUBSTITUTE(Table3[[#This Row],[Distance]]," meters",""))*Lookups!$L$4,0)) -> 40 | O49: 58 Boulevard Saint-Germain, Paris, 75005 | P49: =TRIM(LEFT(Table3[[#This Row],[Shipping Address]],FIND(",",Table3[[#This Row],[Shipping Address]])-1)) -> 58 Boulevard Saint-Germain | Q49: =TRIM(MID(Table3[[#This Row],[Shipping Address]],FIND(",",Table3[[#This Row],[Shipping Address]])+1,FIND(",",Table3[[#This Row],[Shipping Address]],FIND(",",Table3[[#This Row],[Shipping Address]])+1)-FIND(",",Table3[[#This Row],[Shipping Address]])-1)) -> Paris | R49: =TRIM(MID(Table3[[#This Row],[Shipping Address]],FIND(",",Table3[[#This Row],[Shipping Address]],FIND(",",Table3[[#This Row],[Shipping Address]])+1)+1,20)) -> 75005 | S49: FR | T49: =_xlfn.IFNA(_xlfn.XLOOKUP(Table3[[#This Row],[Country Code]],Lookups!$A$2:$A$5,Lookups!$B$2:$B$5),"CHECK CODE") -> France | U49: =_xlfn.IFNA(_xlfn.XLOOKUP(Table3[[#This Row],[Country Code]],Lookups!$A$2:$A$5,Lookups!$C$2:$C$5),"CHECK CODE") -> Europe | V49: €1050 | W49: =_xlfn.IFNA(_xlfn.XLOOKUP(Table3[[#This Row],[Country Code]],Lookups!$A$2:$A$5,Lookups!$D$2:$D$5),"CHECK CODE") -> EUR | X49: =VALUE(MID(Table3[[#This Row],[Unit Price]],2,50)) -> 1050 | Y49: =_xlfn.IFNA(_xlfn.XLOOKUP(Table3[[#This Row],[Country Code]],Lookups!$A$2:$A$5,Lookups!$E$2:$E$5),"") -> 1 | Z49: =Table3[[#This Row],[Unit Price (local)]]/Table3[[#This Row],[FX Rate (per EUR)]] -> 1050 | AA49: 230 | AB49: 0 | AC49: =ROUND(Table3[[#This Row],[Unit Price (EUR)]]*Table3[[#This Row],[Units Sold]],0) -> 241500 | AD49: =ROUND(Table3[[#This Row],[Gross Sales (EUR)]]*(1-Table3[[#This Row],[Discount (%)]]/100),0) -> 241500 | AE49: =_xlfn.IFNA(_xlfn.XLOOKUP(Table3[[#This Row],[Month]],Lookups!$N$2:$N$13,Lookups!$O$2:$O$13),"CHECK MONTH") -> 4 | AF49: =TEXT(Table3[[#This Row],[Month No]],"00")&" - "&Table3[[#This Row],[Month]] -> 04 - April | AG49: =_xlfn.IFNA(_xlfn.XLOOKUP(Table3[[#This Row],[Month]],Lookups!$N$2:$N$13,Lookups!$P$2:$P$13),"CHECK MONTH") -> Q2 | AH49: =Table3[[#This Row],[Gross Sales (EUR)]]-Table3[[#This Row],[Total Sales (EUR)]] -> 0 | AI49: =DATE(Lookups!$O$15,Table3[[#This Row],[Month No]],1) -> 45748
A50: 49 | B50: Sanya | C50: Joshi | D50: =TRIM(Table3[[#This Row],[Rep Last Name]])&", "&TRIM(Table3[[#This Row],[Rep First Name]]) -> Joshi, Sanya | E50: May | F50: Electric Unicycle | G50: 15 mph | H50: =IF(Table3[[#This Row],[Min Speed (original, incomplete)]]="",_xlfn.IFNA(_xlfn.XLOOKUP(Table3[[#This Row],[Product Type]],Lookups!$G$2:$G$4,Lookups!$H$2:$H$4),"CHECK PRODUCT"),Table3[[#This Row],[Min Speed (original, incomplete)]]) -> 15 mph | I50: 30 mph | J50: 30 miles | K50: =ROUND(VALUE(SUBSTITUTE(Table3[[#This Row],[Min Speed (mph)]]," mph",""))*Lookups!$L$2,0) -> 24 | L50: =ROUND(VALUE(SUBSTITUTE(Table3[[#This Row],[Speed]]," mph",""))*Lookups!$L$2,0) -> 48 | M50: =Table3[[#This Row],[Min Speed (km/h)]]&" – "&Table3[[#This Row],[Max Speed (km/h)]]&" km/h" -> 24 – 48 km/h | N50: =IF(ISNUMBER(SEARCH("mile",Table3[[#This Row],[Distance]])),ROUND(VALUE(SUBSTITUTE(Table3[[#This Row],[Distance]]," miles",""))*Lookups!$L$3,0),ROUND(VALUE(SUBSTITUTE(Table3[[#This Row],[Distance]]," meters",""))*Lookups!$L$4,0)) -> 48 | O50: 456 Brigade Road, Bengaluru, 560001 | P50: =TRIM(LEFT(Table3[[#This Row],[Shipping Address]],FIND(",",Table3[[#This Row],[Shipping Address]])-1)) -> 456 Brigade Road | Q50: =TRIM(MID(Table3[[#This Row],[Shipping Address]],FIND(",",Table3[[#This Row],[Shipping Address]])+1,FIND(",",Table3[[#This Row],[Shipping Address]],FIND(",",Table3[[#This Row],[Shipping Address]])+1)-FIND(",",Table3[[#This Row],[Shipping Address]])-1)) -> Bengaluru | R50: =TRIM(MID(Table3[[#This Row],[Shipping Address]],FIND(",",Table3[[#This Row],[Shipping Address]],FIND(",",Table3[[#This Row],[Shipping Address]])+1)+1,20)) -> 560001 | S50: IN | T50: =_xlfn.IFNA(_xlfn.XLOOKUP(Table3[[#This Row],[Country Code]],Lookups!$A$2:$A$5,Lookups!$B$2:$B$5),"CHECK CODE") -> India | U50: =_xlfn.IFNA(_xlfn.XLOOKUP(Table3[[#This Row],[Country Code]],Lookups!$A$2:$A$5,Lookups!$C$2:$C$5),"CHECK CODE") -> Asia | V50: ₹30,000 | W50: =_xlfn.IFNA(_xlfn.XLOOKUP(Table3[[#This Row],[Country Code]],Lookups!$A$2:$A$5,Lookups!$D$2:$D$5),"CHECK CODE") -> INR | X50: =VALUE(MID(Table3[[#This Row],[Unit Price]],2,50)) -> 30000 | Y50: =_xlfn.IFNA(_xlfn.XLOOKUP(Table3[[#This Row],[Country Code]],Lookups!$A$2:$A$5,Lookups!$E$2:$E$5),"") -> 109.882 | Z50: =Table3[[#This Row],[Unit Price (local)]]/Table3[[#This Row],[FX Rate (per EUR)]] -> 273.02015 | AA50: 200 | AB50: 0 | AC50: =ROUND(Table3[[#This Row],[Unit Price (EUR)]]*Table3[[#This Row],[Units Sold]],0) -> 54604 | AD50: =ROUND(Table3[[#This Row],[Gross Sales (EUR)]]*(1-Table3[[#This Row],[Discount (%)]]/100),0) -> 54604 | AE50: =_xlfn.IFNA(_xlfn.XLOOKUP(Table3[[#This Row],[Month]],Lookups!$N$2:$N$13,Lookups!$O$2:$O$13),"CHECK MONTH") -> 5 | AF50: =TEXT(Table3[[#This Row],[Month No]],"00")&" - "&Table3[[#This Row],[Month]] -> 05 - May | AG50: =_xlfn.IFNA(_xlfn.XLOOKUP(Table3[[#This Row],[Month]],Lookups!$N$2:$N$13,Lookups!$P$2:$P$13),"CHECK MONTH") -> Q2 | AH50: =Table3[[#This Row],[Gross Sales (EUR)]]-Table3[[#This Row],[Total Sales (EUR)]] -> 0 | AI50: =DATE(Lookups!$O$15,Table3[[#This Row],[Month No]],1) -> 45778
A51: 50 | B51: Sanya | C51: Joshi | D51: =TRIM(Table3[[#This Row],[Rep Last Name]])&", "&TRIM(Table3[[#This Row],[Rep First Name]]) -> Joshi, Sanya | E51: May | F51: Electric Scooter | G51: 20 mph | H51: =IF(Table3[[#This Row],[Min Speed (original, incomplete)]]="",_xlfn.IFNA(_xlfn.XLOOKUP(Table3[[#This Row],[Product Type]],Lookups!$G$2:$G$4,Lookups!$H$2:$H$4),"CHECK PRODUCT"),Table3[[#This Row],[Min Speed (original, incomplete)]]) -> 20 mph | I51: 35 mph | J51: 40 miles | K51: =ROUND(VALUE(SUBSTITUTE(Table3[[#This Row],[Min Speed (mph)]]," mph",""))*Lookups!$L$2,0) -> 32 | L51: =ROUND(VALUE(SUBSTITUTE(Table3[[#This Row],[Speed]]," mph",""))*Lookups!$L$2,0) -> 56 | M51: =Table3[[#This Row],[Min Speed (km/h)]]&" – "&Table3[[#This Row],[Max Speed (km/h)]]&" km/h" -> 32 – 56 km/h | N51: =IF(ISNUMBER(SEARCH("mile",Table3[[#This Row],[Distance]])),ROUND(VALUE(SUBSTITUTE(Table3[[#This Row],[Distance]]," miles",""))*Lookups!$L$3,0),ROUND(VALUE(SUBSTITUTE(Table3[[#This Row],[Distance]]," meters",""))*Lookups!$L$4,0)) -> 64 | O51: 457 Brigade Road, Bengaluru, 560001 | P51: =TRIM(LEFT(Table3[[#This Row],[Shipping Address]],FIND(",",Table3[[#This Row],[Shipping Address]])-1)) -> 457 Brigade Road | Q51: =TRIM(MID(Table3[[#This Row],[Shipping Address]],FIND(",",Table3[[#This Row],[Shipping Address]])+1,FIND(",",Table3[[#This Row],[Shipping Address]],FIND(",",Table3[[#This Row],[Shipping Address]])+1)-FIND(",",Table3[[#This Row],[Shipping Address]])-1)) -> Bengaluru | R51: =TRIM(MID(Table3[[#This Row],[Shipping Address]],FIND(",",Table3[[#This Row],[Shipping Address]],FIND(",",Table3[[#This Row],[Shipping Address]])+1)+1,20)) -> 560001 | S51: IN | T51: =_xlfn.IFNA(_xlfn.XLOOKUP(Table3[[#This Row],[Country Code]],Lookups!$A$2:$A$5,Lookups!$B$2:$B$5),"CHECK CODE") -> India | U51: =_xlfn.IFNA(_xlfn.XLOOKUP(Table3[[#This Row],[Country Code]],Lookups!$A$2:$A$5,Lookups!$C$2:$C$5),"CHECK CODE") -> Asia | V51: ₹25,000 | W51: =_xlfn.IFNA(_xlfn.XLOOKUP(Table3[[#This Row],[Country Code]],Lookups!$A$2:$A$5,Lookups!$D$2:$D$5),"CHECK CODE") -> INR | X51: =VALUE(MID(Table3[[#This Row],[Unit Price]],2,50)) -> 25000 | Y51: =_xlfn.IFNA(_xlfn.XLOOKUP(Table3[[#This Row],[Country Code]],Lookups!$A$2:$A$5,Lookups!$E$2:$E$5),"") -> 109.882 | Z51: =Table3[[#This Row],[Unit Price (local)]]/Table3[[#This Row],[FX Rate (per EUR)]] -> 227.51679 | AA51: 450 | AB51: 0 | AC51: =ROUND(Table3[[#This Row],[Unit Price (EUR)]]*Table3[[#This Row],[Units Sold]],0) -> 102383 | AD51: =ROUND(Table3[[#This Row],[Gross Sales (EUR)]]*(1-Table3[[#This Row],[Discount (%)]]/100),0) -> 102383 | AE51: =_xlfn.IFNA(_xlfn.XLOOKUP(Table3[[#This Row],[Month]],Lookups!$N$2:$N$13,Lookups!$O$2:$O$13),"CHECK MONTH") -> 5 | AF51: =TEXT(Table3[[#This Row],[Month No]],"00")&" - "&Table3[[#This Row],[Month]] -> 05 - May | AG51: =_xlfn.IFNA(_xlfn.XLOOKUP(Table3[[#This Row],[Month]],Lookups!$N$2:$N$13,Lookups!$P$2:$P$13),"CHECK MONTH") -> Q2 | AH51: =Table3[[#This Row],[Gross Sales (EUR)]]-Table3[[#This Row],[Total Sales (EUR)]] -> 0 | AI51: =DATE(Lookups!$O$15,Table3[[#This Row],[Month No]],1) -> 45778
A52: 51 | B52: Sanya | C52: Joshi | D52: =TRIM(Table3[[#This Row],[Rep Last Name]])&", "&TRIM(Table3[[#This Row],[Rep First Name]]) -> Joshi, Sanya | E52: May | F52: Electric Skateboard | G52: 18 mph | H52: =IF(Table3[[#This Row],[Min Speed (original, incomplete)]]="",_xlfn.IFNA(_xlfn.XLOOKUP(Table3[[#This Row],[Product Type]],Lookups!$G$2:$G$4,Lookups!$H$2:$H$4),"CHECK PRODUCT"),Table3[[#This Row],[Min Speed (original, incomplete)]]) -> 18 mph | I52: 28 mph | J52: 25 miles | K52: =ROUND(VALUE(SUBSTITUTE(Table3[[#This Row],[Min Speed (mph)]]," mph",""))*Lookups!$L$2,0) -> 29 | L52: =ROUND(VALUE(SUBSTITUTE(Table3[[#This Row],[Speed]]," mph",""))*Lookups!$L$2,0) -> 45 | M52: =Table3[[#This Row],[Min Speed (km/h)]]&" – "&Table3[[#This Row],[Max Speed (km/h)]]&" km/h" -> 29 – 45 km/h | N52: =IF(ISNUMBER(SEARCH("mile",Table3[[#This Row],[Distance]])),ROUND(VALUE(SUBSTITUTE(Table3[[#This Row],[Distance]]," miles",""))*Lookups!$L$3,0),ROUND(VALUE(SUBSTITUTE(Table3[[#This Row],[Distance]]," meters",""))*Lookups!$L$4,0)) -> 40 | O52: 458 Brigade Road, Bengaluru, 560001 | P52: =TRIM(LEFT(Table3[[#This Row],[Shipping Address]],FIND(",",Table3[[#This Row],[Shipping Address]])-1)) -> 458 Brigade Road | Q52: =TRIM(MID(Table3[[#This Row],[Shipping Address]],FIND(",",Table3[[#This Row],[Shipping Address]])+1,FIND(",",Table3[[#This Row],[Shipping Address]],FIND(",",Table3[[#This Row],[Shipping Address]])+1)-FIND(",",Table3[[#This Row],[Shipping Address]])-1)) -> Bengaluru | R52: =TRIM(MID(Table3[[#This Row],[Shipping Address]],FIND(",",Table3[[#This Row],[Shipping Address]],FIND(",",Table3[[#This Row],[Shipping Address]])+1)+1,20)) -> 560001 | S52: IN | T52: =_xlfn.IFNA(_xlfn.XLOOKUP(Table3[[#This Row],[Country Code]],Lookups!$A$2:$A$5,Lookups!$B$2:$B$5),"CHECK CODE") -> India | U52: =_xlfn.IFNA(_xlfn.XLOOKUP(Table3[[#This Row],[Country Code]],Lookups!$A$2:$A$5,Lookups!$C$2:$C$5),"CHECK CODE") -> Asia | V52: ₹22,000 | W52: =_xlfn.IFNA(_xlfn.XLOOKUP(Table3[[#This Row],[Country Code]],Lookups!$A$2:$A$5,Lookups!$D$2:$D$5),"CHECK CODE") -> INR | X52: =VALUE(MID(Table3[[#This Row],[Unit Price]],2,50)) -> 22000 | Y52: =_xlfn.IFNA(_xlfn.XLOOKUP(Table3[[#This Row],[Country Code]],Lookups!$A$2:$A$5,Lookups!$E$2:$E$5),"") -> 109.882 | Z52: =Table3[[#This Row],[Unit Price (local)]]/Table3[[#This Row],[FX Rate (per EUR)]] -> 200.21478 | AA52: 350 | AB52: 0 | AC52: =ROUND(Table3[[#This Row],[Unit Price (EUR)]]*Table3[[#This Row],[Units Sold]],0) -> 70075 | AD52: =ROUND(Table3[[#This Row],[Gross Sales (EUR)]]*(1-Table3[[#This Row],[Discount (%)]]/100),0) -> 70075 | AE52: =_xlfn.IFNA(_xlfn.XLOOKUP(Table3[[#This Row],[Month]],Lookups!$N$2:$N$13,Lookups!$O$2:$O$13),"CHECK MONTH") -> 5 | AF52: =TEXT(Table3[[#This Row],[Month No]],"00")&" - "&Table3[[#This Row],[Month]] -> 05 - May | AG52: =_xlfn.IFNA(_xlfn.XLOOKUP(Table3[[#This Row],[Month]],Lookups!$N$2:$N$13,Lookups!$P$2:$P$13),"CHECK MONTH") -> Q2 | AH52: =Table3[[#This Row],[Gross Sales (EUR)]]-Table3[[#This Row],[Total Sales (EUR)]] -> 0 | AI52: =DATE(Lookups!$O$15,Table3[[#This Row],[Month No]],1) -> 45778
A53: 52 | B53: Fang | C53: Liu | D53: =TRIM(Table3[[#This Row],[Rep Last Name]])&", "&TRIM(Table3[[#This Row],[Rep First Name]]) -> Liu, Fang | E53: May | F53: Electric Unicycle | G53: 15 mph | H53: =IF(Table3[[#This Row],[Min Speed (original, incomplete)]]="",_xlfn.IFNA(_xlfn.XLOOKUP(Table3[[#This Row],[Product Type]],Lookups!$G$2:$G$4,Lookups!$H$2:$H$4),"CHECK PRODUCT"),Table3[[#This Row],[Min Speed (original, incomplete)]]) -> 15 mph | I53: 30 mph | J53: 48,280 meters | K53: =ROUND(VALUE(SUBSTITUTE(Table3[[#This Row],[Min Speed (mph)]]," mph",""))*Lookups!$L$2,0) -> 24 | L53: =ROUND(VALUE(SUBSTITUTE(Table3[[#This Row],[Speed]]," mph",""))*Lookups!$L$2,0) -> 48 | M53: =Table3[[#This Row],[Min Speed (km/h)]]&" – "&Table3[[#This Row],[Max Speed (km/h)]]&" km/h" -> 24 – 48 km/h | N53: =IF(ISNUMBER(SEARCH("mile",Table3[[#This Row],[Distance]])),ROUND(VALUE(SUBSTITUTE(Table3[[#This Row],[Distance]]," miles",""))*Lookups!$L$3,0),ROUND(VALUE(SUBSTITUTE(Table3[[#This Row],[Distance]]," meters",""))*Lookups!$L$4,0)) -> 48 | O53: 99 Nanjing Road, Shanghai, 200001 | P53: =TRIM(LEFT(Table3[[#This Row],[Shipping Address]],FIND(",",Table3[[#This Row],[Shipping Address]])-1)) -> 99 Nanjing Road | Q53: =TRIM(MID(Table3[[#This Row],[Shipping Address]],FIND(",",Table3[[#This Row],[Shipping Address]])+1,FIND(",",Table3[[#This Row],[Shipping Address]],FIND(",",Table3[[#This Row],[Shipping Address]])+1)-FIND(",",Table3[[#This Row],[Shipping Address]])-1)) -> Shanghai | R53: =TRIM(MID(Table3[[#This Row],[Shipping Address]],FIND(",",Table3[[#This Row],[Shipping Address]],FIND(",",Table3[[#This Row],[Shipping Address]])+1)+1,20)) -> 200001 | S53: CN | T53: =_xlfn.IFNA(_xlfn.XLOOKUP(Table3[[#This Row],[Country Code]],Lookups!$A$2:$A$5,Lookups!$B$2:$B$5),"CHECK CODE") -> China | U53: =_xlfn.IFNA(_xlfn.XLOOKUP(Table3[[#This Row],[Country Code]],Lookups!$A$2:$A$5,Lookups!$C$2:$C$5),"CHECK CODE") -> Asia | V53: ¥5,000 | W53: =_xlfn.IFNA(_xlfn.XLOOKUP(Table3[[#This Row],[Country Code]],Lookups!$A$2:$A$5,Lookups!$D$2:$D$5),"CHECK CODE") -> CNY | X53: =VALUE(MID(Table3[[#This Row],[Unit Price]],2,50)) -> 5000 | Y53: =_xlfn.IFNA(_xlfn.XLOOKUP(Table3[[#This Row],[Country Code]],Lookups!$A$2:$A$5,Lookups!$E$2:$E$5),"") -> 7.7255 | Z53: =Table3[[#This Row],[Unit Price (local)]]/Table3[[#This Row],[FX Rate (per EUR)]] -> 647.2073 | AA53: 700 | AB53: 0 | AC53: =ROUND(Table3[[#This Row],[Unit Price (EUR)]]*Table3[[#This Row],[Units Sold]],0) -> 453045 | AD53: =ROUND(Table3[[#This Row],[Gross Sales (EUR)]]*(1-Table3[[#This Row],[Discount (%)]]/100),0) -> 453045 | AE53: =_xlfn.IFNA(_xlfn.XLOOKUP(Table3[[#This Row],[Month]],Lookups!$N$2:$N$13,Lookups!$O$2:$O$13),"CHECK MONTH") -> 5 | AF53: =TEXT(Table3[[#This Row],[Month No]],"00")&" - "&Table3[[#This Row],[Month]] -> 05 - May | AG53: =_xlfn.IFNA(_xlfn.XLOOKUP(Table3[[#This Row],[Month]],Lookups!$N$2:$N$13,Lookups!$P$2:$P$13),"CHECK MONTH") -> Q2 | AH53: =Table3[[#This Row],[Gross Sales (EUR)]]-Table3[[#This Row],[Total Sales (EUR)]] -> 0 | AI53: =DATE(Lookups!$O$15,Table3[[#This Row],[Month No]],1) -> 45778
A54: 53 | B54: Fang | C54: Liu | D54: =TRIM(Table3[[#This Row],[Rep Last Name]])&", "&TRIM(Table3[[#This Row],[Rep First Name]]) -> Liu, Fang | E54: May | F54: Electric Scooter | G54: 20 mph | H54: =IF(Table3[[#This Row],[Min Speed (original, incomplete)]]="",_xlfn.IFNA(_xlfn.XLOOKUP(Table3[[#This Row],[Product Type]],Lookups!$G$2:$G$4,Lookups!$H$2:$H$4),"CHECK PRODUCT"),Table3[[#This Row],[Min Speed (original, incomplete)]]) -> 20 mph | I54: 35 mph | J54: 40 miles | K54: =ROUND(VALUE(SUBSTITUTE(Table3[[#This Row],[Min Speed (mph)]]," mph",""))*Lookups!$L$2,0) -> 32 | L54: =ROUND(VALUE(SUBSTITUTE(Table3[[#This Row],[Speed]]," mph",""))*Lookups!$L$2,0) -> 56 | M54: =Table3[[#This Row],[Min Speed (km/h)]]&" – "&Table3[[#This Row],[Max Speed (km/h)]]&" km/h" -> 32 – 56 km/h | N54: =IF(ISNUMBER(SEARCH("mile",Table3[[#This Row],[Distance]])),ROUND(VALUE(SUBSTITUTE(Table3[[#This Row],[Distance]]," miles",""))*Lookups!$L$3,0),ROUND(VALUE(SUBSTITUTE(Table3[[#This Row],[Distance]]," meters",""))*Lookups!$L$4,0)) -> 64 | O54: 100 Nanjing Road, Shanghai, 200001 | P54: =TRIM(LEFT(Table3[[#This Row],[Shipping Address]],FIND(",",Table3[[#This Row],[Shipping Address]])-1)) -> 100 Nanjing Road | Q54: =TRIM(MID(Table3[[#This Row],[Shipping Address]],FIND(",",Table3[[#This Row],[Shipping Address]])+1,FIND(",",Table3[[#This Row],[Shipping Address]],FIND(",",Table3[[#This Row],[Shipping Address]])+1)-FIND(",",Table3[[#This Row],[Shipping Address]])-1)) -> Shanghai | R54: =TRIM(MID(Table3[[#This Row],[Shipping Address]],FIND(",",Table3[[#This Row],[Shipping Address]],FIND(",",Table3[[#This Row],[Shipping Address]])+1)+1,20)) -> 200001 | S54: CN | T54: =_xlfn.IFNA(_xlfn.XLOOKUP(Table3[[#This Row],[Country Code]],Lookups!$A$2:$A$5,Lookups!$B$2:$B$5),"CHECK CODE") -> China | U54: =_xlfn.IFNA(_xlfn.XLOOKUP(Table3[[#This Row],[Country Code]],Lookups!$A$2:$A$5,Lookups!$C$2:$C$5),"CHECK CODE") -> Asia | V54: ¥3,500 | W54: =_xlfn.IFNA(_xlfn.XLOOKUP(Table3[[#This Row],[Country Code]],Lookups!$A$2:$A$5,Lookups!$D$2:$D$5),"CHECK CODE") -> CNY | X54: =VALUE(MID(Table3[[#This Row],[Unit Price]],2,50)) -> 3500 | Y54: =_xlfn.IFNA(_xlfn.XLOOKUP(Table3[[#This Row],[Country Code]],Lookups!$A$2:$A$5,Lookups!$E$2:$E$5),"") -> 7.7255 | Z54: =Table3[[#This Row],[Unit Price (local)]]/Table3[[#This Row],[FX Rate (per EUR)]] -> 453.04511 | AA54: 1600 | AB54: 0 | AC54: =ROUND(Table3[[#This Row],[Unit Price (EUR)]]*Table3[[#This Row],[Units Sold]],0) -> 724872 | AD54: =ROUND(Table3[[#This Row],[Gross Sales (EUR)]]*(1-Table3[[#This Row],[Discount (%)]]/100),0) -> 724872 | AE54: =_xlfn.IFNA(_xlfn.XLOOKUP(Table3[[#This Row],[Month]],Lookups!$N$2:$N$13,Lookups!$O$2:$O$13),"CHECK MONTH") -> 5 | AF54: =TEXT(Table3[[#This Row],[Month No]],"00")&" - "&Table3[[#This Row],[Month]] -> 05 - May | AG54: =_xlfn.IFNA(_xlfn.XLOOKUP(Table3[[#This Row],[Month]],Lookups!$N$2:$N$13,Lookups!$P$2:$P$13),"CHECK MONTH") -> Q2 | AH54: =Table3[[#This Row],[Gross Sales (EUR)]]-Table3[[#This Row],[Total Sales (EUR)]] -> 0 | AI54: =DATE(Lookups!$O$15,Table3[[#This Row],[Month No]],1) -> 45778
A55: 54 | B55: Fang | C55: Liu | D55: =TRIM(Table3[[#This Row],[Rep Last Name]])&", "&TRIM(Table3[[#This Row],[Rep First Name]]) -> Liu, Fang | E55: May | F55: Electric Skateboard | G55: 18 mph | H55: =IF(Table3[[#This Row],[Min Speed (original, incomplete)]]="",_xlfn.IFNA(_xlfn.XLOOKUP(Table3[[#This Row],[Product Type]],Lookups!$G$2:$G$4,Lookups!$H$2:$H$4),"CHECK PRODUCT"),Table3[[#This Row],[Min Speed (original, incomplete)]]) -> 18 mph | I55: 28 mph | J55: 25 miles | K55: =ROUND(VALUE(SUBSTITUTE(Table3[[#This Row],[Min Speed (mph)]]," mph",""))*Lookups!$L$2,0) -> 29 | L55: =ROUND(VALUE(SUBSTITUTE(Table3[[#This Row],[Speed]]," mph",""))*Lookups!$L$2,0) -> 45 | M55: =Table3[[#This Row],[Min Speed (km/h)]]&" – "&Table3[[#This Row],[Max Speed (km/h)]]&" km/h" -> 29 – 45 km/h | N55: =IF(ISNUMBER(SEARCH("mile",Table3[[#This Row],[Distance]])),ROUND(VALUE(SUBSTITUTE(Table3[[#This Row],[Distance]]," miles",""))*Lookups!$L$3,0),ROUND(VALUE(SUBSTITUTE(Table3[[#This Row],[Distance]]," meters",""))*Lookups!$L$4,0)) -> 40 | O55: 101 Nanjing Road, Shanghai, 200001 | P55: =TRIM(LEFT(Table3[[#This Row],[Shipping Address]],FIND(",",Table3[[#This Row],[Shipping Address]])-1)) -> 101 Nanjing Road | Q55: =TRIM(MID(Table3[[#This Row],[Shipping Address]],FIND(",",Table3[[#This Row],[Shipping Address]])+1,FIND(",",Table3[[#This Row],[Shipping Address]],FIND(",",Table3[[#This Row],[Shipping Address]])+1)-FIND(",",Table3[[#This Row],[Shipping Address]])-1)) -> Shanghai | R55: =TRIM(MID(Table3[[#This Row],[Shipping Address]],FIND(",",Table3[[#This Row],[Shipping Address]],FIND(",",Table3[[#This Row],[Shipping Address]])+1)+1,20)) -> 200001 | S55: CN | T55: =_xlfn.IFNA(_xlfn.XLOOKUP(Table3[[#This Row],[Country Code]],Lookups!$A$2:$A$5,Lookups!$B$2:$B$5),"CHECK CODE") -> China | U55: =_xlfn.IFNA(_xlfn.XLOOKUP(Table3[[#This Row],[Country Code]],Lookups!$A$2:$A$5,Lookups!$C$2:$C$5),"CHECK CODE") -> Asia | V55: ¥4,200 | W55: =_xlfn.IFNA(_xlfn.XLOOKUP(Table3[[#This Row],[Country Code]],Lookups!$A$2:$A$5,Lookups!$D$2:$D$5),"CHECK CODE") -> CNY | X55: =VALUE(MID(Table3[[#This Row],[Unit Price]],2,50)) -> 4200 | Y55: =_xlfn.IFNA(_xlfn.XLOOKUP(Table3[[#This Row],[Country Code]],Lookups!$A$2:$A$5,Lookups!$E$2:$E$5),"") -> 7.7255 | Z55: =Table3[[#This Row],[Unit Price (local)]]/Table3[[#This Row],[FX Rate (per EUR)]] -> 543.65413 | AA55: 1000 | AB55: 0 | AC55: =ROUND(Table3[[#This Row],[Unit Price (EUR)]]*Table3[[#This Row],[Units Sold]],0) -> 543654 | AD55: =ROUND(Table3[[#This Row],[Gross Sales (EUR)]]*(1-Table3[[#This Row],[Discount (%)]]/100),0) -> 543654 | AE55: =_xlfn.IFNA(_xlfn.XLOOKUP(Table3[[#This Row],[Month]],Lookups!$N$2:$N$13,Lookups!$O$2:$O$13),"CHECK MONTH") -> 5 | AF55: =TEXT(Table3[[#This Row],[Month No]],"00")&" - "&Table3[[#This Row],[Month]] -> 05 - May | AG55: =_xlfn.IFNA(_xlfn.XLOOKUP(Table3[[#This Row],[Month]],Lookups!$N$2:$N$13,Lookups!$P$2:$P$13),"CHECK MONTH") -> Q2 | AH55: =Table3[[#This Row],[Gross Sales (EUR)]]-Table3[[#This Row],[Total Sales (EUR)]] -> 0 | AI55: =DATE(Lookups!$O$15,Table3[[#This Row],[Month No]],1) -> 45778
A56: 55 | B56: Jonas | C56: Fischer | D56: =TRIM(Table3[[#This Row],[Rep Last Name]])&", "&TRIM(Table3[[#This Row],[Rep First Name]]) -> Fischer, Jonas | E56: May | F56: Electric Unicycle | G56: 15 mph | H56: =IF(Table3[[#This Row],[Min Speed (original, incomplete)]]="",_xlfn.IFNA(_xlfn.XLOOKUP(Table3[[#This Row],[Product Type]],Lookups!$G$2:$G$4,Lookups!$H$2:$H$4),"CHECK PRODUCT"),Table3[[#This Row],[Min Speed (original, incomplete)]]) -> 15 mph | I56: 30 mph | J56: 30 miles | K56: =ROUND(VALUE(SUBSTITUTE(Table3[[#This Row],[Min Speed (mph)]]," mph",""))*Lookups!$L$2,0) -> 24 | L56: =ROUND(VALUE(SUBSTITUTE(Table3[[#This Row],[Speed]]," mph",""))*Lookups!$L$2,0) -> 48 | M56: =Table3[[#This Row],[Min Speed (km/h)]]&" – "&Table3[[#This Row],[Max Speed (km/h)]]&" km/h" -> 24 – 48 km/h | N56: =IF(ISNUMBER(SEARCH("mile",Table3[[#This Row],[Distance]])),ROUND(VALUE(SUBSTITUTE(Table3[[#This Row],[Distance]]," miles",""))*Lookups!$L$3,0),ROUND(VALUE(SUBSTITUTE(Table3[[#This Row],[Distance]]," meters",""))*Lookups!$L$4,0)) -> 48 | O56: 303 Ringstraße, Hamburg, 20095 | P56: =TRIM(LEFT(Table3[[#This Row],[Shipping Address]],FIND(",",Table3[[#This Row],[Shipping Address]])-1)) -> 303 Ringstraße | Q56: =TRIM(MID(Table3[[#This Row],[Shipping Address]],FIND(",",Table3[[#This Row],[Shipping Address]])+1,FIND(",",Table3[[#This Row],[Shipping Address]],FIND(",",Table3[[#This Row],[Shipping Address]])+1)-FIND(",",Table3[[#This Row],[Shipping Address]])-1)) -> Hamburg | R56: =TRIM(MID(Table3[[#This Row],[Shipping Address]],FIND(",",Table3[[#This Row],[Shipping Address]],FIND(",",Table3[[#This Row],[Shipping Address]])+1)+1,20)) -> 20095 | S56: DE | T56: =_xlfn.IFNA(_xlfn.XLOOKUP(Table3[[#This Row],[Country Code]],Lookups!$A$2:$A$5,Lookups!$B$2:$B$5),"CHECK CODE") -> Germany | U56: =_xlfn.IFNA(_xlfn.XLOOKUP(Table3[[#This Row],[Country Code]],Lookups!$A$2:$A$5,Lookups!$C$2:$C$5),"CHECK CODE") -> Europe | V56: €1000 | W56: =_xlfn.IFNA(_xlfn.XLOOKUP(Table3[[#This Row],[Country Code]],Lookups!$A$2:$A$5,Lookups!$D$2:$D$5),"CHECK CODE") -> EUR | X56: =VALUE(MID(Table3[[#This Row],[Unit Price]],2,50)) -> 1000 | Y56: =_xlfn.IFNA(_xlfn.XLOOKUP(Table3[[#This Row],[Country Code]],Lookups!$A$2:$A$5,Lookups!$E$2:$E$5),"") -> 1 | Z56: =Table3[[#This Row],[Unit Price (local)]]/Table3[[#This Row],[FX Rate (per EUR)]] -> 1000 | AA56: 180 | AB56: 0 | AC56: =ROUND(Table3[[#This Row],[Unit Price (EUR)]]*Table3[[#This Row],[Units Sold]],0) -> 180000 | AD56: =ROUND(Table3[[#This Row],[Gross Sales (EUR)]]*(1-Table3[[#This Row],[Discount (%)]]/100),0) -> 180000 | AE56: =_xlfn.IFNA(_xlfn.XLOOKUP(Table3[[#This Row],[Month]],Lookups!$N$2:$N$13,Lookups!$O$2:$O$13),"CHECK MONTH") -> 5 | AF56: =TEXT(Table3[[#This Row],[Month No]],"00")&" - "&Table3[[#This Row],[Month]] -> 05 - May | AG56: =_xlfn.IFNA(_xlfn.XLOOKUP(Table3[[#This Row],[Month]],Lookups!$N$2:$N$13,Lookups!$P$2:$P$13),"CHECK MONTH") -> Q2 | AH56: =Table3[[#This Row],[Gross Sales (EUR)]]-Table3[[#This Row],[Total Sales (EUR)]] -> 0 | AI56: =DATE(Lookups!$O$15,Table3[[#This Row],[Month No]],1) -> 45778
A57: 56 | B57: Jonas | C57: Fischer | D57: =TRIM(Table3[[#This Row],[Rep Last Name]])&", "&TRIM(Table3[[#This Row],[Rep First Name]]) -> Fischer, Jonas | E57: May | F57: Electric Scooter | G57: 20 mph | H57: =IF(Table3[[#This Row],[Min Speed (original, incomplete)]]="",_xlfn.IFNA(_xlfn.XLOOKUP(Table3[[#This Row],[Product Type]],Lookups!$G$2:$G$4,Lookups!$H$2:$H$4),"CHECK PRODUCT"),Table3[[#This Row],[Min Speed (original, incomplete)]]) -> 20 mph | I57: 35 mph | J57: 40 miles | K57: =ROUND(VALUE(SUBSTITUTE(Table3[[#This Row],[Min Speed (mph)]]," mph",""))*Lookups!$L$2,0) -> 32 | L57: =ROUND(VALUE(SUBSTITUTE(Table3[[#This Row],[Speed]]," mph",""))*Lookups!$L$2,0) -> 56 | M57: =Table3[[#This Row],[Min Speed (km/h)]]&" – "&Table3[[#This Row],[Max Speed (km/h)]]&" km/h" -> 32 – 56 km/h | N57: =IF(ISNUMBER(SEARCH("mile",Table3[[#This Row],[Distance]])),ROUND(VALUE(SUBSTITUTE(Table3[[#This Row],[Distance]]," miles",""))*Lookups!$L$3,0),ROUND(VALUE(SUBSTITUTE(Table3[[#This Row],[Distance]]," meters",""))*Lookups!$L$4,0)) -> 64 | O57: 304 Ringstraße, Hamburg, 20095 | P57: =TRIM(LEFT(Table3[[#This Row],[Shipping Address]],FIND(",",Table3[[#This Row],[Shipping Address]])-1)) -> 304 Ringstraße | Q57: =TRIM(MID(Table3[[#This Row],[Shipping Address]],FIND(",",Table3[[#This Row],[Shipping Address]])+1,FIND(",",Table3[[#This Row],[Shipping Address]],FIND(",",Table3[[#This Row],[Shipping Address]])+1)-FIND(",",Table3[[#This Row],[Shipping Address]])-1)) -> Hamburg | R57: =TRIM(MID(Table3[[#This Row],[Shipping Address]],FIND(",",Table3[[#This Row],[Shipping Address]],FIND(",",Table3[[#This Row],[Shipping Address]])+1)+1,20)) -> 20095 | S57: DE | T57: =_xlfn.IFNA(_xlfn.XLOOKUP(Table3[[#This Row],[Country Code]],Lookups!$A$2:$A$5,Lookups!$B$2:$B$5),"CHECK CODE") -> Germany | U57: =_xlfn.IFNA(_xlfn.XLOOKUP(Table3[[#This Row],[Country Code]],Lookups!$A$2:$A$5,Lookups!$C$2:$C$5),"CHECK CODE") -> Europe | V57: €800 | W57: =_xlfn.IFNA(_xlfn.XLOOKUP(Table3[[#This Row],[Country Code]],Lookups!$A$2:$A$5,Lookups!$D$2:$D$5),"CHECK CODE") -> EUR | X57: =VALUE(MID(Table3[[#This Row],[Unit Price]],2,50)) -> 800 | Y57: =_xlfn.IFNA(_xlfn.XLOOKUP(Table3[[#This Row],[Country Code]],Lookups!$A$2:$A$5,Lookups!$E$2:$E$5),"") -> 1 | Z57: =Table3[[#This Row],[Unit Price (local)]]/Table3[[#This Row],[FX Rate (per EUR)]] -> 800 | AA57: 320 | AB57: 0 | AC57: =ROUND(Table3[[#This Row],[Unit Price (EUR)]]*Table3[[#This Row],[Units Sold]],0) -> 256000 | AD57: =ROUND(Table3[[#This Row],[Gross Sales (EUR)]]*(1-Table3[[#This Row],[Discount (%)]]/100),0) -> 256000 | AE57: =_xlfn.IFNA(_xlfn.XLOOKUP(Table3[[#This Row],[Month]],Lookups!$N$2:$N$13,Lookups!$O$2:$O$13),"CHECK MONTH") -> 5 | AF57: =TEXT(Table3[[#This Row],[Month No]],"00")&" - "&Table3[[#This Row],[Month]] -> 05 - May | AG57: =_xlfn.IFNA(_xlfn.XLOOKUP(Table3[[#This Row],[Month]],Lookups!$N$2:$N$13,Lookups!$P$2:$P$13),"CHECK MONTH") -> Q2 | AH57: =Table3[[#This Row],[Gross Sales (EUR)]]-Table3[[#This Row],[Total Sales (EUR)]] -> 0 | AI57: =DATE(Lookups!$O$15,Table3[[#This Row],[Month No]],1) -> 45778
A58: 57 | B58: Jonas | C58: Fischer | D58: =TRIM(Table3[[#This Row],[Rep Last Name]])&", "&TRIM(Table3[[#This Row],[Rep First Name]]) -> Fischer, Jonas | E58: May | F58: Electric Skateboard | G58: 18 mph | H58: =IF(Table3[[#This Row],[Min Speed (original, incomplete)]]="",_xlfn.IFNA(_xlfn.XLOOKUP(Table3[[#This Row],[Product Type]],Lookups!$G$2:$G$4,Lookups!$H$2:$H$4),"CHECK PRODUCT"),Table3[[#This Row],[Min Speed (original, incomplete)]]) -> 18 mph | I58: 28 mph | J58: 25 miles | K58: =ROUND(VALUE(SUBSTITUTE(Table3[[#This Row],[Min Speed (mph)]]," mph",""))*Lookups!$L$2,0) -> 29 | L58: =ROUND(VALUE(SUBSTITUTE(Table3[[#This Row],[Speed]]," mph",""))*Lookups!$L$2,0) -> 45 | M58: =Table3[[#This Row],[Min Speed (km/h)]]&" – "&Table3[[#This Row],[Max Speed (km/h)]]&" km/h" -> 29 – 45 km/h | N58: =IF(ISNUMBER(SEARCH("mile",Table3[[#This Row],[Distance]])),ROUND(VALUE(SUBSTITUTE(Table3[[#This Row],[Distance]]," miles",""))*Lookups!$L$3,0),ROUND(VALUE(SUBSTITUTE(Table3[[#This Row],[Distance]]," meters",""))*Lookups!$L$4,0)) -> 40 | O58: 305 Ringstraße, Hamburg, 20095 | P58: =TRIM(LEFT(Table3[[#This Row],[Shipping Address]],FIND(",",Table3[[#This Row],[Shipping Address]])-1)) -> 305 Ringstraße | Q58: =TRIM(MID(Table3[[#This Row],[Shipping Address]],FIND(",",Table3[[#This Row],[Shipping Address]])+1,FIND(",",Table3[[#This Row],[Shipping Address]],FIND(",",Table3[[#This Row],[Shipping Address]])+1)-FIND(",",Table3[[#This Row],[Shipping Address]])-1)) -> Hamburg | R58: =TRIM(MID(Table3[[#This Row],[Shipping Address]],FIND(",",Table3[[#This Row],[Shipping Address]],FIND(",",Table3[[#This Row],[Shipping Address]])+1)+1,20)) -> 20095 | S58: DE | T58: =_xlfn.IFNA(_xlfn.XLOOKUP(Table3[[#This Row],[Country Code]],Lookups!$A$2:$A$5,Lookups!$B$2:$B$5),"CHECK CODE") -> Germany | U58: =_xlfn.IFNA(_xlfn.XLOOKUP(Table3[[#This Row],[Country Code]],Lookups!$A$2:$A$5,Lookups!$C$2:$C$5),"CHECK CODE") -> Europe | V58: €950 | W58: =_xlfn.IFNA(_xlfn.XLOOKUP(Table3[[#This Row],[Country Code]],Lookups!$A$2:$A$5,Lookups!$D$2:$D$5),"CHECK CODE") -> EUR | X58: =VALUE(MID(Table3[[#This Row],[Unit Price]],2,50)) -> 950 | Y58: =_xlfn.IFNA(_xlfn.XLOOKUP(Table3[[#This Row],[Country Code]],Lookups!$A$2:$A$5,Lookups!$E$2:$E$5),"") -> 1 | Z58: =Table3[[#This Row],[Unit Price (local)]]/Table3[[#This Row],[FX Rate (per EUR)]] -> 950 | AA58: 220 | AB58: 0 | AC58: =ROUND(Table3[[#This Row],[Unit Price (EUR)]]*Table3[[#This Row],[Units Sold]],0) -> 209000 | AD58: =ROUND(Table3[[#This Row],[Gross Sales (EUR)]]*(1-Table3[[#This Row],[Discount (%)]]/100),0) -> 209000 | AE58: =_xlfn.IFNA(_xlfn.XLOOKUP(Table3[[#This Row],[Month]],Lookups!$N$2:$N$13,Lookups!$O$2:$O$13),"CHECK MONTH") -> 5 | AF58: =TEXT(Table3[[#This Row],[Month No]],"00")&" - "&Table3[[#This Row],[Month]] -> 05 - May | AG58: =_xlfn.IFNA(_xlfn.XLOOKUP(Table3[[#This Row],[Month]],Lookups!$N$2:$N$13,Lookups!$P$2:$P$13),"CHECK MONTH") -> Q2 | AH58: =Table3[[#This Row],[Gross Sales (EUR)]]-Table3[[#This Row],[Total Sales (EUR)]] -> 0 | AI58: =DATE(Lookups!$O$15,Table3[[#This Row],[Month No]],1) -> 45778
A59: 58 | B59: Théo | C59: Bernard | D59: =TRIM(Table3[[#This Row],[Rep Last Name]])&", "&TRIM(Table3[[#This Row],[Rep First Name]]) -> Bernard, Théo | E59: May | F59: Electric Unicycle | G59: 15 mph | H59: =IF(Table3[[#This Row],[Min Speed (original, incomplete)]]="",_xlfn.IFNA(_xlfn.XLOOKUP(Table3[[#This Row],[Product Type]],Lookups!$G$2:$G$4,Lookups!$H$2:$H$4),"CHECK PRODUCT"),Table3[[#This Row],[Min Speed (original, incomplete)]]) -> 15 mph | I59: 30 mph | J59: 30 miles | K59: =ROUND(VALUE(SUBSTITUTE(Table3[[#This Row],[Min Speed (mph)]]," mph",""))*Lookups!$L$2,0) -> 24 | L59: =ROUND(VALUE(SUBSTITUTE(Table3[[#This Row],[Speed]]," mph",""))*Lookups!$L$2,0) -> 48 | M59: =Table3[[#This Row],[Min Speed (km/h)]]&" – "&Table3[[#This Row],[Max Speed (km/h)]]&" km/h" -> 24 – 48 km/h | N59: =IF(ISNUMBER(SEARCH("mile",Table3[[#This Row],[Distance]])),ROUND(VALUE(SUBSTITUTE(Table3[[#This Row],[Distance]]," miles",""))*Lookups!$L$3,0),ROUND(VALUE(SUBSTITUTE(Table3[[#This Row],[Distance]]," meters",""))*Lookups!$L$4,0)) -> 48 | O59: 56 Boulevard Saint-Germain, Paris, 75005 | P59: =TRIM(LEFT(Table3[[#This Row],[Shipping Address]],FIND(",",Table3[[#This Row],[Shipping Address]])-1)) -> 56 Boulevard Saint-Germain | Q59: =TRIM(MID(Table3[[#This Row],[Shipping Address]],FIND(",",Table3[[#This Row],[Shipping Address]])+1,FIND(",",Table3[[#This Row],[Shipping Address]],FIND(",",Table3[[#This Row],[Shipping Address]])+1)-FIND(",",Table3[[#This Row],[Shipping Address]])-1)) -> Paris | R59: =TRIM(MID(Table3[[#This Row],[Shipping Address]],FIND(",",Table3[[#This Row],[Shipping Address]],FIND(",",Table3[[#This Row],[Shipping Address]])+1)+1,20)) -> 75005 | S59: FR | T59: =_xlfn.IFNA(_xlfn.XLOOKUP(Table3[[#This Row],[Country Code]],Lookups!$A$2:$A$5,Lookups!$B$2:$B$5),"CHECK CODE") -> France | U59: =_xlfn.IFNA(_xlfn.XLOOKUP(Table3[[#This Row],[Country Code]],Lookups!$A$2:$A$5,Lookups!$C$2:$C$5),"CHECK CODE") -> Europe | V59: €1100 | W59: =_xlfn.IFNA(_xlfn.XLOOKUP(Table3[[#This Row],[Country Code]],Lookups!$A$2:$A$5,Lookups!$D$2:$D$5),"CHECK CODE") -> EUR | X59: =VALUE(MID(Table3[[#This Row],[Unit Price]],2,50)) -> 1100 | Y59: =_xlfn.IFNA(_xlfn.XLOOKUP(Table3[[#This Row],[Country Code]],Lookups!$A$2:$A$5,Lookups!$E$2:$E$5),"") -> 1 | Z59: =Table3[[#This Row],[Unit Price (local)]]/Table3[[#This Row],[FX Rate (per EUR)]] -> 1100 | AA59: 140 | AB59: 0 | AC59: =ROUND(Table3[[#This Row],[Unit Price (EUR)]]*Table3[[#This Row],[Units Sold]],0) -> 154000 | AD59: =ROUND(Table3[[#This Row],[Gross Sales (EUR)]]*(1-Table3[[#This Row],[Discount (%)]]/100),0) -> 154000 | AE59: =_xlfn.IFNA(_xlfn.XLOOKUP(Table3[[#This Row],[Month]],Lookups!$N$2:$N$13,Lookups!$O$2:$O$13),"CHECK MONTH") -> 5 | AF59: =TEXT(Table3[[#This Row],[Month No]],"00")&" - "&Table3[[#This Row],[Month]] -> 05 - May | AG59: =_xlfn.IFNA(_xlfn.XLOOKUP(Table3[[#This Row],[Month]],Lookups!$N$2:$N$13,Lookups!$P$2:$P$13),"CHECK MONTH") -> Q2 | AH59: =Table3[[#This Row],[Gross Sales (EUR)]]-Table3[[#This Row],[Total Sales (EUR)]] -> 0 | AI59: =DATE(Lookups!$O$15,Table3[[#This Row],[Month No]],1) -> 45778
A60: 59 | B60: Théo | C60: Bernard | D60: =TRIM(Table3[[#This Row],[Rep Last Name]])&", "&TRIM(Table3[[#This Row],[Rep First Name]]) -> Bernard, Théo | E60: May | F60: Electric Scooter | G60: 20 mph | H60: =IF(Table3[[#This Row],[Min Speed (original, incomplete)]]="",_xlfn.IFNA(_xlfn.XLOOKUP(Table3[[#This Row],[Product Type]],Lookups!$G$2:$G$4,Lookups!$H$2:$H$4),"CHECK PRODUCT"),Table3[[#This Row],[Min Speed (original, incomplete)]]) -> 20 mph | I60: 35 mph | J60: 64,370 meters | K60: =ROUND(VALUE(SUBSTITUTE(Table3[[#This Row],[Min Speed (mph)]]," mph",""))*Lookups!$L$2,0) -> 32 | L60: =ROUND(VALUE(SUBSTITUTE(Table3[[#This Row],[Speed]]," mph",""))*Lookups!$L$2,0) -> 56 | M60: =Table3[[#This Row],[Min Speed (km/h)]]&" – "&Table3[[#This Row],[Max Speed (km/h)]]&" km/h" -> 32 – 56 km/h | N60: =IF(ISNUMBER(SEARCH("mile",Table3[[#This Row],[Distance]])),ROUND(VALUE(SUBSTITUTE(Table3[[#This Row],[Distance]]," miles",""))*Lookups!$L$3,0),ROUND(VALUE(SUBSTITUTE(Table3[[#This Row],[Distance]]," meters",""))*Lookups!$L$4,0)) -> 64 | O60: 57 Boulevard Saint-Germain, Paris, 75005 | P60: =TRIM(LEFT(Table3[[#This Row],[Shipping Address]],FIND(",",Table3[[#This Row],[Shipping Address]])-1)) -> 57 Boulevard Saint-Germain | Q60: =TRIM(MID(Table3[[#This Row],[Shipping Address]],FIND(",",Table3[[#This Row],[Shipping Address]])+1,FIND(",",Table3[[#This Row],[Shipping Address]],FIND(",",Table3[[#This Row],[Shipping Address]])+1)-FIND(",",Table3[[#This Row],[Shipping Address]])-1)) -> Paris | R60: =TRIM(MID(Table3[[#This Row],[Shipping Address]],FIND(",",Table3[[#This Row],[Shipping Address]],FIND(",",Table3[[#This Row],[Shipping Address]])+1)+1,20)) -> 75005 | S60: FR | T60: =_xlfn.IFNA(_xlfn.XLOOKUP(Table3[[#This Row],[Country Code]],Lookups!$A$2:$A$5,Lookups!$B$2:$B$5),"CHECK CODE") -> France | U60: =_xlfn.IFNA(_xlfn.XLOOKUP(Table3[[#This Row],[Country Code]],Lookups!$A$2:$A$5,Lookups!$C$2:$C$5),"CHECK CODE") -> Europe | V60: €900 | W60: =_xlfn.IFNA(_xlfn.XLOOKUP(Table3[[#This Row],[Country Code]],Lookups!$A$2:$A$5,Lookups!$D$2:$D$5),"CHECK CODE") -> EUR | X60: =VALUE(MID(Table3[[#This Row],[Unit Price]],2,50)) -> 900 | Y60: =_xlfn.IFNA(_xlfn.XLOOKUP(Table3[[#This Row],[Country Code]],Lookups!$A$2:$A$5,Lookups!$E$2:$E$5),"") -> 1 | Z60: =Table3[[#This Row],[Unit Price (local)]]/Table3[[#This Row],[FX Rate (per EUR)]] -> 900 | AA60: 300 | AB60: 0 | AC60: =ROUND(Table3[[#This Row],[Unit Price (EUR)]]*Table3[[#This Row],[Units Sold]],0) -> 270000 | AD60: =ROUND(Table3[[#This Row],[Gross Sales (EUR)]]*(1-Table3[[#This Row],[Discount (%)]]/100),0) -> 270000 | AE60: =_xlfn.IFNA(_xlfn.XLOOKUP(Table3[[#This Row],[Month]],Lookups!$N$2:$N$13,Lookups!$O$2:$O$13),"CHECK MONTH") -> 5 | AF60: =TEXT(Table3[[#This Row],[Month No]],"00")&" - "&Table3[[#This Row],[Month]] -> 05 - May | AG60: =_xlfn.IFNA(_xlfn.XLOOKUP(Table3[[#This Row],[Month]],Lookups!$N$2:$N$13,Lookups!$P$2:$P$13),"CHECK MONTH") -> Q2 | AH60: =Table3[[#This Row],[Gross Sales (EUR)]]-Table3[[#This Row],[Total Sales (EUR)]] -> 0 | AI60: =DATE(Lookups!$O$15,Table3[[#This Row],[Month No]],1) -> 45778
A61: 60 | B61: Théo | C61: Bernard | D61: =TRIM(Table3[[#This Row],[Rep Last Name]])&", "&TRIM(Table3[[#This Row],[Rep First Name]]) -> Bernard, Théo | E61: May | F61: Electric Skateboard | G61: 18 mph | H61: =IF(Table3[[#This Row],[Min Speed (original, incomplete)]]="",_xlfn.IFNA(_xlfn.XLOOKUP(Table3[[#This Row],[Product Type]],Lookups!$G$2:$G$4,Lookups!$H$2:$H$4),"CHECK PRODUCT"),Table3[[#This Row],[Min Speed (original, incomplete)]]) -> 18 mph | I61: 28 mph | J61: 25 miles | K61: =ROUND(VALUE(SUBSTITUTE(Table3[[#This Row],[Min Speed (mph)]]," mph",""))*Lookups!$L$2,0) -> 29 | L61: =ROUND(VALUE(SUBSTITUTE(Table3[[#This Row],[Speed]]," mph",""))*Lookups!$L$2,0) -> 45 | M61: =Table3[[#This Row],[Min Speed (km/h)]]&" – "&Table3[[#This Row],[Max Speed (km/h)]]&" km/h" -> 29 – 45 km/h | N61: =IF(ISNUMBER(SEARCH("mile",Table3[[#This Row],[Distance]])),ROUND(VALUE(SUBSTITUTE(Table3[[#This Row],[Distance]]," miles",""))*Lookups!$L$3,0),ROUND(VALUE(SUBSTITUTE(Table3[[#This Row],[Distance]]," meters",""))*Lookups!$L$4,0)) -> 40 | O61: 58 Boulevard Saint-Germain, Paris, 75005 | P61: =TRIM(LEFT(Table3[[#This Row],[Shipping Address]],FIND(",",Table3[[#This Row],[Shipping Address]])-1)) -> 58 Boulevard Saint-Germain | Q61: =TRIM(MID(Table3[[#This Row],[Shipping Address]],FIND(",",Table3[[#This Row],[Shipping Address]])+1,FIND(",",Table3[[#This Row],[Shipping Address]],FIND(",",Table3[[#This Row],[Shipping Address]])+1)-FIND(",",Table3[[#This Row],[Shipping Address]])-1)) -> Paris | R61: =TRIM(MID(Table3[[#This Row],[Shipping Address]],FIND(",",Table3[[#This Row],[Shipping Address]],FIND(",",Table3[[#This Row],[Shipping Address]])+1)+1,20)) -> 75005 | S61: FR | T61: =_xlfn.IFNA(_xlfn.XLOOKUP(Table3[[#This Row],[Country Code]],Lookups!$A$2:$A$5,Lookups!$B$2:$B$5),"CHECK CODE") -> France | U61: =_xlfn.IFNA(_xlfn.XLOOKUP(Table3[[#This Row],[Country Code]],Lookups!$A$2:$A$5,Lookups!$C$2:$C$5),"CHECK CODE") -> Europe | V61: €1050 | W61: =_xlfn.IFNA(_xlfn.XLOOKUP(Table3[[#This Row],[Country Code]],Lookups!$A$2:$A$5,Lookups!$D$2:$D$5),"CHECK CODE") -> EUR | X61: =VALUE(MID(Table3[[#This Row],[Unit Price]],2,50)) -> 1050 | Y61: =_xlfn.IFNA(_xlfn.XLOOKUP(Table3[[#This Row],[Country Code]],Lookups!$A$2:$A$5,Lookups!$E$2:$E$5),"") -> 1 | Z61: =Table3[[#This Row],[Unit Price (local)]]/Table3[[#This Row],[FX Rate (per EUR)]] -> 1050 | AA61: 280 | AB61: 0 | AC61: =ROUND(Table3[[#This Row],[Unit Price (EUR)]]*Table3[[#This Row],[Units Sold]],0) -> 294000 | AD61: =ROUND(Table3[[#This Row],[Gross Sales (EUR)]]*(1-Table3[[#This Row],[Discount (%)]]/100),0) -> 294000 | AE61: =_xlfn.IFNA(_xlfn.XLOOKUP(Table3[[#This Row],[Month]],Lookups!$N$2:$N$13,Lookups!$O$2:$O$13),"CHECK MONTH") -> 5 | AF61: =TEXT(Table3[[#This Row],[Month No]],"00")&" - "&Table3[[#This Row],[Month]] -> 05 - May | AG61: =_xlfn.IFNA(_xlfn.XLOOKUP(Table3[[#This Row],[Month]],Lookups!$N$2:$N$13,Lookups!$P$2:$P$13),"CHECK MONTH") -> Q2 | AH61: =Table3[[#This Row],[Gross Sales (EUR)]]-Table3[[#This Row],[Total Sales (EUR)]] -> 0 | AI61: =DATE(Lookups!$O$15,Table3[[#This Row],[Month No]],1) -> 45778
... A63: 62 | B63: Sanya | C63: Joshi | D63: =TRIM(Table3[[#This Row],[Rep Last Name]])&", "&TRIM(Table3[[#This Row],[Rep First Name]]) -> Joshi, Sanya | E63: June | F63: Electric Scooter | G63: 20 mph | H63: =IF(Table3[[#This Row],[Min Speed (original, incomplete)]]="",_xlfn.IFNA(_xlfn.XLOOKUP(Table3[[#This Row],[Product Type]],Lookups!$G$2:$G$4,Lookups!$H$2:$H$4),"CHECK PRODUCT"),Table3[[#This Row],[Min Speed (original, incomplete)]]) -> 20 mph | I63: 35 mph | J63: 40 miles | K63: =ROUND(VALUE(SUBSTITUTE(Table3[[#This Row],[Min Speed (mph)]]," mph",""))*Lookups!$L$2,0) -> 32 | L63: =ROUND(VALUE(SUBSTITUTE(Table3[[#This Row],[Speed]]," mph",""))*Lookups!$L$2,0) -> 56 | M63: =Table3[[#This Row],[Min Speed (km/h)]]&" – "&Table3[[#This Row],[Max Speed (km/h)]]&" km/h" -> 32 – 56 km/h | N63: =IF(ISNUMBER(SEARCH("mile",Table3[[#This Row],[Distance]])),ROUND(VALUE(SUBSTITUTE(Table3[[#This Row],[Distance]]," miles",""))*Lookups!$L$3,0),ROUND(VALUE(SUBSTITUTE(Table3[[#This Row],[Distance]]," meters",""))*Lookups!$L$4,0)) -> 64 | O63: 457 Brigade Road, Bengaluru, 560001 | P63: =TRIM(LEFT(Table3[[#This Row],[Shipping Address]],FIND(",",Table3[[#This Row],[Shipping Address]])-1)) -> 457 Brigade Road | Q63: =TRIM(MID(Table3[[#This Row],[Shipping Address]],FIND(",",Table3[[#This Row],[Shipping Address]])+1,FIND(",",Table3[[#This Row],[Shipping Address]],FIND(",",Table3[[#This Row],[Shipping Address]])+1)-FIND(",",Table3[[#This Row],[Shipping Address]])-1)) -> Bengaluru | R63: =TRIM(MID(Table3[[#This Row],[Shipping Address]],FIND(",",Table3[[#This Row],[Shipping Address]],FIND(",",Table3[[#This Row],[Shipping Address]])+1)+1,20)) -> 560001 | S63: IN | T63: =_xlfn.IFNA(_xlfn.XLOOKUP(Table3[[#This Row],[Country Code]],Lookups!$A$2:$A$5,Lookups!$B$2:$B$5),"CHECK CODE") -> India | U63: =_xlfn.IFNA(_xlfn.XLOOKUP(Table3[[#This Row],[Country Code]],Lookups!$A$2:$A$5,Lookups!$C$2:$C$5),"CHECK CODE") -> Asia | V63: ₹25,000 | W63: =_xlfn.IFNA(_xlfn.XLOOKUP(Table3[[#This Row],[Country Code]],Lookups!$A$2:$A$5,Lookups!$D$2:$D$5),"CHECK CODE") -> INR | X63: =VALUE(MID(Table3[[#This Row],[Unit Price]],2,50)) -> 25000 | Y63: =_xlfn.IFNA(_xlfn.XLOOKUP(Table3[[#This Row],[Country Code]],Lookups!$A$2:$A$5,Lookups!$E$2:$E$5),"") -> 109.882 | Z63: =Table3[[#This Row],[Unit Price (local)]]/Table3[[#This Row],[FX Rate (per EUR)]] -> 227.51679 | AA63: 500 | AB63: 0 | AC63: =ROUND(Table3[[#This Row],[Unit Price (EUR)]]*Table3[[#This Row],[Units Sold]],0) -> 113758 | AD63: =ROUND(Table3[[#This Row],[Gross Sales (EUR)]]*(1-Table3[[#This Row],[Discount (%)]]/100),0) -> 113758 | AE63: =_xlfn.IFNA(_xlfn.XLOOKUP(Table3[[#This Row],[Month]],Lookups!$N$2:$N$13,Lookups!$O$2:$O$13),"CHECK MONTH") -> 6 | AF63: =TEXT(Table3[[#This Row],[Month No]],"00")&" - "&Table3[[#This Row],[Month]] -> 06 - June | AG63: =_xlfn.IFNA(_xlfn.XLOOKUP(Table3[[#This Row],[Month]],Lookups!$N$2:$N$13,Lookups!$P$2:$P$13),"CHECK MONTH") -> Q2 | AH63: =Table3[[#This Row],[Gross Sales (EUR)]]-Table3[[#This Row],[Total Sales (EUR)]] -> 0 | AI63: =DATE(Lookups!$O$15,Table3[[#This Row],[Month No]],1) -> 45809
A64: 63 | B64: Sanya | C64: Joshi | D64: =TRIM(Table3[[#This Row],[Rep Last Name]])&", "&TRIM(Table3[[#This Row],[Rep First Name]]) -> Joshi, Sanya | E64: June | F64: Electric Skateboard | H64: =IF(Table3[[#This Row],[Min Speed (original, incomplete)]]="",_xlfn.IFNA(_xlfn.XLOOKUP(Table3[[#This Row],[Product Type]],Lookups!$G$2:$G$4,Lookups!$H$2:$H$4),"CHECK PRODUCT"),Table3[[#This Row],[Min Speed (original, incomplete)]]) -> 18 mph | I64: 28 mph | J64: 25 miles | K64: =ROUND(VALUE(SUBSTITUTE(Table3[[#This Row],[Min Speed (mph)]]," mph",""))*Lookups!$L$2,0) -> 29 | L64: =ROUND(VALUE(SUBSTITUTE(Table3[[#This Row],[Speed]]," mph",""))*Lookups!$L$2,0) -> 45 | M64: =Table3[[#This Row],[Min Speed (km/h)]]&" – "&Table3[[#This Row],[Max Speed (km/h)]]&" km/h" -> 29 – 45 km/h | N64: =IF(ISNUMBER(SEARCH("mile",Table3[[#This Row],[Distance]])),ROUND(VALUE(SUBSTITUTE(Table3[[#This Row],[Distance]]," miles",""))*Lookups!$L$3,0),ROUND(VALUE(SUBSTITUTE(Table3[[#This Row],[Distance]]," meters",""))*Lookups!$L$4,0)) -> 40 | O64: 458 Brigade Road, Bengaluru, 560001 | P64: =TRIM(LEFT(Table3[[#This Row],[Shipping Address]],FIND(",",Table3[[#This Row],[Shipping Address]])-1)) -> 458 Brigade Road | Q64: =TRIM(MID(Table3[[#This Row],[Shipping Address]],FIND(",",Table3[[#This Row],[Shipping Address]])+1,FIND(",",Table3[[#This Row],[Shipping Address]],FIND(",",Table3[[#This Row],[Shipping Address]])+1)-FIND(",",Table3[[#This Row],[Shipping Address]])-1)) -> Bengaluru | R64: =TRIM(MID(Table3[[#This Row],[Shipping Address]],FIND(",",Table3[[#This Row],[Shipping Address]],FIND(",",Table3[[#This Row],[Shipping Address]])+1)+1,20)) -> 560001 | S64: IN | T64: =_xlfn.IFNA(_xlfn.XLOOKUP(Table3[[#This Row],[Country Code]],Lookups!$A$2:$A$5,Lookups!$B$2:$B$5),"CHECK CODE") -> India | U64: =_xlfn.IFNA(_xlfn.XLOOKUP(Table3[[#This Row],[Country Code]],Lookups!$A$2:$A$5,Lookups!$C$2:$C$5),"CHECK CODE") -> Asia | V64: ₹22,000 | W64: =_xlfn.IFNA(_xlfn.XLOOKUP(Table3[[#This Row],[Country Code]],Lookups!$A$2:$A$5,Lookups!$D$2:$D$5),"CHECK CODE") -> INR | X64: =VALUE(MID(Table3[[#This Row],[Unit Price]],2,50)) -> 22000 | Y64: =_xlfn.IFNA(_xlfn.XLOOKUP(Table3[[#This Row],[Country Code]],Lookups!$A$2:$A$5,Lookups!$E$2:$E$5),"") -> 109.882 | Z64: =Table3[[#This Row],[Unit Price (local)]]/Table3[[#This Row],[FX Rate (per EUR)]] -> 200.21478 | AA64: 400 | AB64: 0 | AC64: =ROUND(Table3[[#This Row],[Unit Price (EUR)]]*Table3[[#This Row],[Units Sold]],0) -> 80086 | AD64: =ROUND(Table3[[#This Row],[Gross Sales (EUR)]]*(1-Table3[[#This Row],[Discount (%)]]/100),0) -> 80086 | AE64: =_xlfn.IFNA(_xlfn.XLOOKUP(Table3[[#This Row],[Month]],Lookups!$N$2:$N$13,Lookups!$O$2:$O$13),"CHECK MONTH") -> 6 | AF64: =TEXT(Table3[[#This Row],[Month No]],"00")&" - "&Table3[[#This Row],[Month]] -> 06 - June | AG64: =_xlfn.IFNA(_xlfn.XLOOKUP(Table3[[#This Row],[Month]],Lookups!$N$2:$N$13,Lookups!$P$2:$P$13),"CHECK MONTH") -> Q2 | AH64: =Table3[[#This Row],[Gross Sales (EUR)]]-Table3[[#This Row],[Total Sales (EUR)]] -> 0 | AI64: =DATE(Lookups!$O$15,Table3[[#This Row],[Month No]],1) -> 45809
A65: 64 | B65: Fang | C65: Liu | D65: =TRIM(Table3[[#This Row],[Rep Last Name]])&", "&TRIM(Table3[[#This Row],[Rep First Name]]) -> Liu, Fang | E65: June | F65: Electric Unicycle | G65: 15 mph | H65: =IF(Table3[[#This Row],[Min Speed (original, incomplete)]]="",_xlfn.IFNA(_xlfn.XLOOKUP(Table3[[#This Row],[Product Type]],Lookups!$G$2:$G$4,Lookups!$H$2:$H$4),"CHECK PRODUCT"),Table3[[#This Row],[Min Speed (original, incomplete)]]) -> 15 mph | I65: 30 mph | J65: 30 miles | K65: =ROUND(VALUE(SUBSTITUTE(Table3[[#This Row],[Min Speed (mph)]]," mph",""))*Lookups!$L$2,0) -> 24 | L65: =ROUND(VALUE(SUBSTITUTE(Table3[[#This Row],[Speed]]," mph",""))*Lookups!$L$2,0) -> 48 | M65: =Table3[[#This Row],[Min Speed (km/h)]]&" – "&Table3[[#This Row],[Max Speed (km/h)]]&" km/h" -> 24 – 48 km/h | N65: =IF(ISNUMBER(SEARCH("mile",Table3[[#This Row],[Distance]])),ROUND(VALUE(SUBSTITUTE(Table3[[#This Row],[Distance]]," miles",""))*Lookups!$L$3,0),ROUND(VALUE(SUBSTITUTE(Table3[[#This Row],[Distance]]," meters",""))*Lookups!$L$4,0)) -> 48 | O65: 99 Nanjing Road, Shanghai, 200001 | P65: =TRIM(LEFT(Table3[[#This Row],[Shipping Address]],FIND(",",Table3[[#This Row],[Shipping Address]])-1)) -> 99 Nanjing Road | Q65: =TRIM(MID(Table3[[#This Row],[Shipping Address]],FIND(",",Table3[[#This Row],[Shipping Address]])+1,FIND(",",Table3[[#This Row],[Shipping Address]],FIND(",",Table3[[#This Row],[Shipping Address]])+1)-FIND(",",Table3[[#This Row],[Shipping Address]])-1)) -> Shanghai | R65: =TRIM(MID(Table3[[#This Row],[Shipping Address]],FIND(",",Table3[[#This Row],[Shipping Address]],FIND(",",Table3[[#This Row],[Shipping Address]])+1)+1,20)) -> 200001 | S65: CN | T65: =_xlfn.IFNA(_xlfn.XLOOKUP(Table3[[#This Row],[Country Code]],Lookups!$A$2:$A$5,Lookups!$B$2:$B$5),"CHECK CODE") -> China | U65: =_xlfn.IFNA(_xlfn.XLOOKUP(Table3[[#This Row],[Country Code]],Lookups!$A$2:$A$5,Lookups!$C$2:$C$5),"CHECK CODE") -> Asia | V65: ¥5,000 | W65: =_xlfn.IFNA(_xlfn.XLOOKUP(Table3[[#This Row],[Country Code]],Lookups!$A$2:$A$5,Lookups!$D$2:$D$5),"CHECK CODE") -> CNY | X65: =VALUE(MID(Table3[[#This Row],[Unit Price]],2,50)) -> 5000 | Y65: =_xlfn.IFNA(_xlfn.XLOOKUP(Table3[[#This Row],[Country Code]],Lookups!$A$2:$A$5,Lookups!$E$2:$E$5),"") -> 7.7255 | Z65: =Table3[[#This Row],[Unit Price (local)]]/Table3[[#This Row],[FX Rate (per EUR)]] -> 647.2073 | AA65: 800 | AB65: 0 | AC65: =ROUND(Table3[[#This Row],[Unit Price (EUR)]]*Table3[[#This Row],[Units Sold]],0) -> 517766 | AD65: =ROUND(Table3[[#This Row],[Gross Sales (EUR)]]*(1-Table3[[#This Row],[Discount (%)]]/100),0) -> 517766 | AE65: =_xlfn.IFNA(_xlfn.XLOOKUP(Table3[[#This Row],[Month]],Lookups!$N$2:$N$13,Lookups!$O$2:$O$13),"CHECK MONTH") -> 6 | AF65: =TEXT(Table3[[#This Row],[Month No]],"00")&" - "&Table3[[#This Row],[Month]] -> 06 - June | AG65: =_xlfn.IFNA(_xlfn.XLOOKUP(Table3[[#This Row],[Month]],Lookups!$N$2:$N$13,Lookups!$P$2:$P$13),"CHECK MONTH") -> Q2 | AH65: =Table3[[#This Row],[Gross Sales (EUR)]]-Table3[[#This Row],[Total Sales (EUR)]] -> 0 | AI65: =DATE(Lookups!$O$15,Table3[[#This Row],[Month No]],1) -> 45809
